Workbook

Sheet BSPR RAS metrics
B1: 42401 | W1: ACTION PLAN OWNER | AC1: PR - BSPR | BR1: Sensitivity | BS1: 0.5
C2: SHUSA RISK APPETITE METRICS | D2: 2015 TRIGGER LIMIT | E2: 2015 RED LIMIT | F2: SOURCE FOR 2016 RAS LIMIT SETTING | H2: SHUSA IN GROUP RAS | I2: 2016 TRIGGER LIMIT | J2: 2016 RED LIMIT | L2: SHUSA US RAS | M2: 2016 TRIGGER LIMIT | N2: 2016 RED LIMIT | P2: BSPR | Q2: 2016 TRIGGER LIMIT | R2: 2016 RED LIMIT | T2: COMMENTS | U2: GROUP DEFINITION | V2: ACTION PLAN | W2: LINE 1 | X2: LINE 2 | Y2: BSPR Comments | Z2: Metric Applicability Confirmed with SHUSA | AA2: Calibration Comments | AC2: Frequency | AD2: Current RTS / RSC metric | AE2: SAN-PR Definition | AF2: SOURCE FOR 2016 RAS LIMIT SETTING | AG2: Source | AH2: Availability | AI2: Level | AJ2: Rationale for threshold definition | AK2: Budget | AL2: Reports Affected | AM2: Reports Consistency Validation | AN2: Differences: SHUSA RAS Glossary vs. BSPR Methodology | AO2: 2015 TRIGGER LIMIT | AP2: 2015 RED LIMIT | AQ2: 2016 GREEN | AR2: 2016 TRIGGER LIMIT | AS2: 2016 RED LIMIT | AT2: 42035 | AU2: 42063 | AV2: 42094 | AW2: 42124 | AX2: 42155 | AY2: 42185 | AZ2: 42216 | BA2: 42247 | BB2: 42277 | BC2: 42308 | BD2: 42338 | BE2: 42369 | BF2: 42400 | BG2: 42401 | BH2: 42430 | BI2: 42461 | BJ2: 42491 | BK2: 42522 | BL2: 42552 | BM2: 42583 | BN2: 42614 | BO2: 42644 | BP2: 42675 | BQ2: 42705 | BR2: Average | BS2: Variance | BT2: Standard Deviation | BU2: AVS | BV2: Local Comments - Cristina's Review | BW2: Comparación 4/8/16
B3: Capital | C3: Common Equity Tier 1 Ratio | D3: 0.11 | E3: 0.105 | F3: Capital Mgmt Group | H3: Y | L3: Y | P3: Y | T3: SIS will report its regulatory ratios. Pending receipt of list and levels | Z3: YES | AC3: Monthly | AD3: RTS BSPR #0048 | AE3: A measurement of core equity capital compared with its total risk-weighted assets. The Tier 1 common capital ratio excludes any preferred shares or non-controlling interests when determining the calculation. | AF3: Leslie Adames (threshold calibration) Comptrollership / Hector Ramos (monthly data) | AG3: ALTAIR system | AH3: Available on day 10th of each month. | AI3: Capital Policy | AJ3: Capital Policy from November 27, 2015 which was approved by the Board on December 8, 2015. Information is located in page 7, Table 3: 2015 SBC/BSPR Capital Expectations. the Planned capital hold was considered for the Amber trigger and the Business-as-usual was consideredfor the Red limit. | AL3: ALCO Risk Scorecard Quarterly Capital Trends | AM3: ALCO: December 2015 and January 2016 OK Quarterly: March. June and September 2015 OK | AO3: 0.1208 | AP3: 0.106 | AR3: 0.1301 | AS3: 0.1101 | AT3: =(881.62-75)/3824.4 -> 0.21091413 | AU3: =(882.69-75)/3827.05 -> 0.21104767 | AV3: =(886.92-75)/3744.03 -> 0.21685724 | AW3: =(890.75234096-75)/3767.184 -> 0.21654168 | AX3: =(893.64630978-75)/3827.715 -> 0.21387337 | AY3: =(896.87773133-75)/3854.980185 -> 0.21319895 | AZ3: =(899.32698133-75)/3832.377 -> 0.21509548 | BA3: =(902.33900133-75)/3790.394 -> 0.21827256 | BB3: =(905.02-75)/3617.54 -> 0.22944321 | BC3: =(906.32-75)/3601.15 -> 0.23084848 | BD3: =(908.344820238001-75)/3544.49459731878 -> 0.23510963 | BE3: =(917.054273058005-75)/3567.9148400942 -> 0.23600739 | BF3: =(845.303335227995-0)/3515.04 -> 0.24048185 | BG3: =(847.509449948007-0)/3475.17933685976 -> 0.24387503 | BH3: =(848.871233227997-0)/3473.86808485756 -> 0.24435909 | BR3: =+IFERROR(AVERAGE(AT3:BQ3),"") -> 0.22506172 | BS3: =+IFERROR(VAR(AT3:BQ3),"") -> 0.00015609551 | BT3: =+IFERROR(STDEV(AT3:BQ3)*(1-$BS$1),"") -> 0.0062469095 | BU3: =+IF(OR(BT3="",OFFSET(AT3,0,MATCH($B$1,AT$2:BQ$2,0)-1)=""),"",IFERROR(IF(ABS(OFFSET(AT3,0,MATCH($B$1,AT$2:BQ$2,0)-1)-OFFSET(AT3,0,MATCH($B$1,AT$2:BQ$2,0)-2))>BT3,"N","µ"),"")) -> µ
C4: Tier 1 Risk-based Capital Ratio | D4: 0.125 | E4: 0.12 | F4: Capital Mgmt Group | H4: Y | L4: Y | P4: Y | Z4: YES | AC4: Monthly | AD4: RTS BSPR #0050 | AE4: Tier 1 capital divided by risk-weighted assets under baseline scenario. | AF4: Leslie Adames (threshold calibration) Comptrollership / Hector Ramos (monthly data) | AG4: ALTAIR system | AH4: Available on day 10th of each month. | AI4: Capital Policy | AJ4: Capital Policy from November 27, 2015 which was approved by the Board on December 8, 2015. Information is located in page 7, Table 3: 2015 SBC/BSPR Capital Expectations. the Planned capital hold was considered for the Amber trigger and the Business-as-usual was consideredfor the Red limit. | AL4: ALCO Risk Scorecard Quarterly Capital Trends | AM4: ALCO: December 2015 and January 2016 OK Quarterly: March. June and September 2015 OK | AO4: 0.152 | AP4: 0.1408 | AR4: 0.1582 | AS4: 0.1382 | AT4: =881.62/3824.4 -> 0.23052505 | AU4: =882.69/3827.05 -> 0.23064501 | AV4: =886.92/3744.04 -> 0.23688849 | AW4: =890.75234096/3767.184 -> 0.23645045 | AX4: =893.64630978/3827.715 -> 0.23346731 | AY4: =896.87773133/3854.980185 -> 0.2326543 | AZ4: =899.32698133/3832.377 -> 0.23466558 | BA4: =902.33900133/3790.394 -> 0.23805942 | BB4: =905.017492977999/3617.53992443135 -> 0.25017485 | BC4: =906.32/3601.15 -> 0.25167516 | BD4: =908.344820238001/3544.49459731878 -> 0.25626921 | BE4: =917.054273058005/3567.9148400942 -> 0.25702807 | BF4: =845.303335227995/3515.04 -> 0.24048185 | BG4: =847.509449948007/3475.17933685976 -> 0.24387503 | BH4: =848.871233227997/3473.86808485756 -> 0.24435909 | BR4: =+IFERROR(AVERAGE(AT4:BQ4),"") -> 0.24114792 | BS4: =+IFERROR(VAR(AT4:BQ4),"") -> 8.1242235e-05 | BT4: =+IFERROR(STDEV(AT4:BQ4)*(1-$BS$1),"") -> 0.0045067237 | BU4: =+IF(OR(BT4="",OFFSET(AT4,0,MATCH($B$1,AT$2:BQ$2,0)-1)=""),"",IFERROR(IF(ABS(OFFSET(AT4,0,MATCH($B$1,AT$2:BQ$2,0)-1)-OFFSET(AT4,0,MATCH($B$1,AT$2:BQ$2,0)-2))>BT4,"N","µ"),"")) -> µ
C5: Total Capital Ratio | D5: 0.145 | E5: 0.14 | F5: Capital Mgmt Group | H5: Y | L5: Y | P5: Y | T5: New from Group Dec-15 / Already in SHUSA RAS | U5: Tier I and Tier II capital based on BIS III regulations with phase in calendar | V5: Ensure alignment with Group definition | W5: Capital Team | X5: RAS Team | Z5: YES | AC5: Monthly | AD5: RTS BSPR #0051 | AE5: Total risk-based capital is the sum of tier 1 plus tier 2 capital under baseline scenario. Tier 1 capital consists of common shareholders equity, perpetual preferred shareholders equity with non-cumulative dividends, retained earnings, and minority interests in the equity accounts of consolidated subsidiaries. Tier 2 capital consists of subordinated debt, intermediate-term preferred stock, cumulative and long-term preferred stock, and a portion of a banks’ allowance for loan and lease losses. | AF5: Leslie Adames (threshold calibration) Comptrollership / Hector Ramos (monthly data) | AG5: ALTAIR system | AH5: Available on day 10th of each month. | AI5: Capital Policy | AJ5: Capital Policy from November 27, 2015 which was approved by the Board on December 8, 2015. Information is located in page 7, Table 3: 2015 SBC/BSPR Capital Expectations. the Planned capital hold was considered for the Amber trigger and the Business-as-usual was consideredfor the Red limit. | AL5: Quarterly Capital Trends | AM5: March 24.9% Different, June and September 2015 OK | AO5: 0.171 | AP5: 0.1608 | AR5: 0.1783 | AS5: 0.1583 | AT5: =929.78/3824.4 -> 0.24311787 | AU5: =930.9/3827.05 -> 0.24324218 | AV5: =934.97339448426/3744.03530307472 -> 0.24972345 | AW5: =938.21927945/3767.184 -> 0.24905056 | AX5: =941.88692978/3827.715 -> 0.24607029 | AY5: =945.44388633/3854.980185 -> 0.24525259 | AZ5: =947.63671533/3832.377 -> 0.24727127 | BA5: =950.13400133/3790.394 -> 0.25066893 | BB5: =950.69/3617.54 -> 0.26280013 | BC5: =951.83/3601.15 -> 0.26431279 | BD5: =953.157389234159/3544.49459731878 -> 0.26891207 | BE5: =962.149080349415/3567.9148400942 -> 0.26966705 | BF5: =889.729997481374/3515.04 -> 0.25312087 | BG5: =891.448349268745/3475.17933685976 -> 0.25651866 | BH5: =892.826478519448/3473.86808485756 -> 0.2570122 | BR5: =+IFERROR(AVERAGE(AT5:BQ5),"") -> 0.25378273 | BS5: =+IFERROR(VAR(AT5:BQ5),"") -> 8.1415052e-05 | BT5: =+IFERROR(STDEV(AT5:BQ5)*(1-$BS$1),"") -> 0.0045115145 | BU5: =+IF(OR(BT5="",OFFSET(AT5,0,MATCH($B$1,AT$2:BQ$2,0)-1)=""),"",IFERROR(IF(ABS(OFFSET(AT5,0,MATCH($B$1,AT$2:BQ$2,0)-1)-OFFSET(AT5,0,MATCH($B$1,AT$2:BQ$2,0)-2))>BT5,"N","µ"),"")) -> µ
C6: Tier 1 Leverage Ratio | D6: 0.1025 | E6: 0.0975 | F6: Capital Mgmt Group | H6: Y | L6: Y | P6: Y | Z6: YES | AC6: Monthly | AD6: RTS BSPR #0049 | AE6: The Tier 1 leverage ratio is calculated by dividing Tier 1 capital ratio by average total consolidated assets. | AF6: Leslie Adames (threshold calibration) Comptrollership / Hector Ramos (monthly data) | AG6: ALTAIR system | AH6: Available on day 10th of each month. | AI6: Capital Policy | AJ6: Capital Policy from November 27, 2015 which was approved by the Board on December 8, 2015. Information is located in page 7, Table 3: 2015 SBC/BSPR Capital Expectations. the Planned capital hold was considered for the Amber trigger and the Business-as-usual was consideredfor the Red limit. | AL6: ALCO Risk Scorecard Quarterly Capital Trends | AM6: ALCO: December 2015 and January 2016 OK Quarterly: March. June and September 2015 OK | AO6: 0.089 | AP6: 0.0812 | AR6: 0.108 | AS6: 0.088 | AT6: =881.62/5437.15 -> 0.16214745 | AU6: =882.69/5405.44 -> 0.1632966 | AV6: =886.92/5454.68 -> 0.16259799 | AW6: =890.75234096/5520.29404333 -> 0.16135958 | AX6: =893.64630978/5491.573 -> 0.16273048 | AY6: =896.87773133/5473.887961 -> 0.16384656 | AZ6: =899.32698133/5432.645 -> 0.16554128 | BA6: =902.33900133/5448.467 -> 0.16561337 | BB6: =905.017492977999/5443.264726678 -> 0.16626373 | BC6: =906.32/5398.96 -> 0.16786937 | BD6: =908.344820238001/5391.366186328 -> 0.16848138 | BE6: =917.054273058005/5379.26621439801 -> 0.17047944 | BF6: =845.303335227995/5317.39 -> 0.1589696 | BG6: =847.509449948007/5298.735556328 -> 0.1599456 | BH6: =848.871233227997/5303.055439328 -> 0.1600721 | BR6: =+IFERROR(AVERAGE(AT6:BQ6),"") -> 0.16394764 | BS6: =+IFERROR(VAR(AT6:BQ6),"") -> 1.1340756e-05 | BT6: =+IFERROR(STDEV(AT6:BQ6)*(1-$BS$1),"") -> 0.001683802 | BU6: =+IF(OR(BT6="",OFFSET(AT6,0,MATCH($B$1,AT$2:BQ$2,0)-1)=""),"",IFERROR(IF(ABS(OFFSET(AT6,0,MATCH($B$1,AT$2:BQ$2,0)-1)-OFFSET(AT6,0,MATCH($B$1,AT$2:BQ$2,0)-2))>BT6,"N","µ"),"")) -> µ
C7: Impairment to Pre-Provision Net Revenue (PPNR) (9Q CCAR stressed) | D7: $3,825MM | E7: $4,100 MM | F7: CCAR | H7: Y | L7: Y | P7: Y | T7: SIS is not subject to CCAR | Z7: YES | AC7: Annual | AE7: RAS Metrics Glossary: The projected 9Q cummulative increase in PPNR impairment between the CCAR BHC Stress and BHC Baseline scenarios and any available capital surplus under the CCAR BHC scenario. Material components include Total Revenue, Expenses due to Operational Risk and Expenses due to Residual Value Risk. | AF7: CCAR | AG7: CCAR | AH7: CCAR | AJ7: The methodology provided by SHUSA and Oliver Wyman is explained in the PDF file 20160426 CCAR-linked RAS methodology.pdf and the final calibration data is included in the PDF file 20160503 BSPR RAS Metrics.pdf. Please refer to slide 3. | AO7: CCAR | AP7: CCAR | AQ7: CCAR/OW | AR7: $296MM | AS7: $319MM | AT7: CCAR/OW | AU7: CCAR/OW | AV7: CCAR/OW | AW7: CCAR/OW | AX7: CCAR/OW | AY7: CCAR/OW | AZ7: CCAR/OW | BA7: CCAR/OW | BB7: CCAR/OW | BC7: CCAR/OW | BD7: CCAR/OW | BE7: CCAR/OW | BF7: CCAR/OW | BG7: CCAR/OW | BH7: 255 | BR7: =+IFERROR(AVERAGE(AT7:BQ7),"") -> 255 | BS7: =+IFERROR(VAR(AT7:BQ7),"") | BT7: =+IFERROR(STDEV(AT7:BQ7)*(1-$BS$1),"") | BU7: =+IF(OR(BT7="",OFFSET(AT7,0,MATCH($B$1,AT$2:BQ$2,0)-1)=""),"",IFERROR(IF(ABS(OFFSET(AT7,0,MATCH($B$1,AT$2:BQ$2,0)-1)-OFFSET(AT7,0,MATCH($B$1,AT$2:BQ$2,0)-2))>BT7,"N","µ"),""))
C8: Common Equity Tier 1 Ratio - stressed | P8: Y | Z8: YES | AC8: Annual | AF8: CCAR | AG8: CCAR | AH8: CCAR | AI8: Capital Policy | AJ8: The Capital Policy was used to calibrate , refer to page 7, Table 3. The Post-stress minimum was used to set the Red limit. To this the Stress absorption (1.71%) was added to calculate the Business-as-usual minimum, which was set as the Ambar trigger. This methodology was discussed and approved between the PR Capital Team and SHUSA's Capital Team. | AR8: =AS8+1.71% -> 0.1101 | AS8: 0.093 | AT8: CCAR/OW | AU8: CCAR/OW | AV8: CCAR/OW | AW8: CCAR/OW | AX8: CCAR/OW | AY8: CCAR/OW | AZ8: CCAR/OW | BA8: CCAR/OW | BB8: CCAR/OW | BC8: CCAR/OW | BD8: CCAR/OW | BE8: CCAR/OW | BF8: CCAR/OW | BG8: CCAR/OW | BH8: CCAR/OW | BR8: =+IFERROR(AVERAGE(AT8:BQ8),"") | BS8: =+IFERROR(VAR(AT8:BQ8),"") | BT8: =+IFERROR(STDEV(AT8:BQ8)*(1-$BS$1),"") | BU8: =+IF(OR(BT8="",OFFSET(AT8,0,MATCH($B$1,AT$2:BQ$2,0)-1)=""),"",IFERROR(IF(ABS(OFFSET(AT8,0,MATCH($B$1,AT$2:BQ$2,0)-1)-OFFSET(AT8,0,MATCH($B$1,AT$2:BQ$2,0)-2))>BT8,"N","µ"),""))
C9: Tier 1 Risk-based Capital Ratio - stressed | P9: Y | Z9: YES | AC9: Annual | AF9: CCAR | AG9: CCAR | AH9: CCAR | AI9: Capital Policy | AJ9: The Capital Policy was used to calibrate , refer to page 7, Table 3. The Post-stress minimum was used to set the Red limit. To this the Management Adjustment was added in order to set as the Ambar trigger (10.75% + 2.00%). This methodology was discussed and approved between the PR Capital Team and SHUSA's Capital Team. | AR9: =AS9+2% -> 0.1275 | AS9: 0.1075 | AT9: CCAR/OW | AU9: CCAR/OW | AV9: CCAR/OW | AW9: CCAR/OW | AX9: CCAR/OW | AY9: CCAR/OW | AZ9: CCAR/OW | BA9: CCAR/OW | BB9: CCAR/OW | BC9: CCAR/OW | BD9: CCAR/OW | BE9: CCAR/OW | BF9: CCAR/OW | BG9: CCAR/OW | BH9: CCAR/OW | BR9: =+IFERROR(AVERAGE(AT9:BQ9),"") | BS9: =+IFERROR(VAR(AT9:BQ9),"") | BT9: =+IFERROR(STDEV(AT9:BQ9)*(1-$BS$1),"") | BU9: =+IF(OR(BT9="",OFFSET(AT9,0,MATCH($B$1,AT$2:BQ$2,0)-1)=""),"",IFERROR(IF(ABS(OFFSET(AT9,0,MATCH($B$1,AT$2:BQ$2,0)-1)-OFFSET(AT9,0,MATCH($B$1,AT$2:BQ$2,0)-2))>BT9,"N","µ"),""))
C10: Total Capital Ratio - stressed | P10: Y | Z10: YES | AC10: Annual | AF10: CCAR | AG10: CCAR | AH10: CCAR | AI10: Capital Policy | AJ10: The Capital Policy was used to calibrate , refer to page 7, Table 3. The Post-stress minimum was used to set the Red limit. To this the Management Adjustment was added in order to set as the Ambar trigger (12.15% + 2.00%). This methodology was discussed and approved between the PR Capital Team and SHUSA's Capital Team. | AR10: =AS10+2% -> 0.1415 | AS10: 0.1215 | AT10: CCAR/OW | AU10: CCAR/OW | AV10: CCAR/OW | AW10: CCAR/OW | AX10: CCAR/OW | AY10: CCAR/OW | AZ10: CCAR/OW | BA10: CCAR/OW | BB10: CCAR/OW | BC10: CCAR/OW | BD10: CCAR/OW | BE10: CCAR/OW | BF10: CCAR/OW | BG10: CCAR/OW | BH10: CCAR/OW | BR10: =+IFERROR(AVERAGE(AT10:BQ10),"") | BS10: =+IFERROR(VAR(AT10:BQ10),"") | BT10: =+IFERROR(STDEV(AT10:BQ10)*(1-$BS$1),"") | BU10: =+IF(OR(BT10="",OFFSET(AT10,0,MATCH($B$1,AT$2:BQ$2,0)-1)=""),"",IFERROR(IF(ABS(OFFSET(AT10,0,MATCH($B$1,AT$2:BQ$2,0)-1)-OFFSET(AT10,0,MATCH($B$1,AT$2:BQ$2,0)-2))>BT10,"N","µ"),""))
C11: Tier 1 Leverage Ratio - stressed | P11: Y | Z11: YES | AC11: Annual | AF11: CCAR | AG11: CCAR | AH11: CCAR | AI11: Capital Policy | AJ11: The Capital Policy was used to calibrate , refer to page 7, Table 3. The Post-stress minimum was used to set the Red limit. To this the Management Adjustment was added in order to set as the Ambar trigger (6.80% + 2.00%). This methodology was discussed and approved between the PR Capital Team and SHUSA's Capital Team. | AR11: =AS11+2% -> 0.088 | AS11: 0.068 | AT11: CCAR/OW | AU11: CCAR/OW | AV11: CCAR/OW | AW11: CCAR/OW | AX11: CCAR/OW | AY11: CCAR/OW | AZ11: CCAR/OW | BA11: CCAR/OW | BB11: CCAR/OW | BC11: CCAR/OW | BD11: CCAR/OW | BE11: CCAR/OW | BF11: CCAR/OW | BG11: CCAR/OW | BH11: CCAR/OW | BR11: =+IFERROR(AVERAGE(AT11:BQ11),"") | BS11: =+IFERROR(VAR(AT11:BQ11),"") | BT11: =+IFERROR(STDEV(AT11:BQ11)*(1-$BS$1),"") | BU11: =+IF(OR(BT11="",OFFSET(AT11,0,MATCH($B$1,AT$2:BQ$2,0)-1)=""),"",IFERROR(IF(ABS(OFFSET(AT11,0,MATCH($B$1,AT$2:BQ$2,0)-1)-OFFSET(AT11,0,MATCH($B$1,AT$2:BQ$2,0)-2))>BT11,"N","µ"),""))
B12: Credit Risk (losses) | C12: Total Credit Losses (9Q stressed CCAR losses) | D12: CCAR | E12: CCAR | F12: CCAR | H12: Y | L12: Y | P12: Y | T12: Included in Loss in Stress calculation | Z12: YES | AC12: Annual | AE12: RAS Metrics Glossary: 9Q stressed cummulativw credit losses and any available capital surplus under the CCAR BHC Stress scenario | AF12: CCAR (threshold calibration) | AJ12: The methodology provided by SHUSA and Oliver Wyman is explained in the PDF file 20160426 CCAR-linked RAS methodology.pdf and the final calibration data is included in the PDF file 20160503 BSPR RAS Metrics.pdf. Please refer to slide 3. | AO12: CCAR | AP12: CCAR | AQ12: CCAR/OW | AR12: $315MM | AS12: $340MM | AT12: CCAR/OW | AU12: CCAR/OW | AV12: CCAR/OW | AW12: CCAR/OW | AX12: CCAR/OW | AY12: CCAR/OW | AZ12: CCAR/OW | BA12: CCAR/OW | BB12: CCAR/OW | BC12: CCAR/OW | BD12: CCAR/OW | BE12: CCAR/OW | BF12: CCAR/OW | BG12: CCAR/OW | BH12: 239 | BR12: =+IFERROR(AVERAGE(AT12:BQ12),"") -> 239 | BS12: =+IFERROR(VAR(AT12:BQ12),"") | BT12: =+IFERROR(STDEV(AT12:BQ12)*(1-$BS$1),"") | BU12: =+IF(OR(BT12="",OFFSET(AT12,0,MATCH($B$1,AT$2:BQ$2,0)-1)=""),"",IFERROR(IF(ABS(OFFSET(AT12,0,MATCH($B$1,AT$2:BQ$2,0)-1)-OFFSET(AT12,0,MATCH($B$1,AT$2:BQ$2,0)-2))>BT12,"N","µ"),""))
C13: NCO PR Mortgages | D13: New 2016 | E13: New 2016 | F13: CCAR | H13: N | L13: Y | P13: Y | Y13: -Please confirm if the Material Portfolios are to be divided between Total Outstanding Portfolio or Total Outstanding of the Material Portfolios. [SA]: Total outstanding of the material portfolios -Are we supposed to use the methodology that SBNA uses included in the RAS Metrics Glossary? (Most recent month's total NCO multiplied by 12 and divided by the Total outstanding balances) [SA]: No - changing to rolling 12-month NCO/rolling 12-month outstanding balance BSPR - shouldn't the denominator of the metric be the average of the rolling 12-month outstanding balance (such as SCUSA) -In order to calculate the annualized amount should we multiply the Most recent month's NCO by 12 or by (number of month/12)? [SA]: As above -In order to be aligned with the Local Credit Trends Report which considers 12 month NCO divided by Average Portfolio, could we consider the local monitoring metric for the RAS? [SA]: As above - we are discussing with Oliver Wyman the possibility of adding change in provisions over 12-mo to the metric | Z13: YES | AC13: Monthly | AE13: NUMERATOR: 12M NCO - Mortgage Portfolio divided by DENOMINATOR: KPI Total 12 Average Portfolio - Mortgage Portfolio | AF13: CCAR (threshold calibration) Risk MI / Rafael Martínez (monthly data) | AG13: CARMOSA PRODUCTO 1 = HIPOTECAS | AH13: day 10th of each month depending on Accounting reconciliation | AJ13: The methodology provided by SHUSA and Oliver Wyman is explained in the PDF file 20160426 CCAR-linked RAS methodology.pdf and the final calibration data is included in the PDF file 20160503 BSPR RAS Metrics.pdf. Please refer to slide 2. | AK13: =20060117.7740878/1278275057.73207 -> 0.015693115 | AL13: Report: Credit Trends as reported by Portfolio Management | AM13: 2015 Q1: 1.5% OK Q2: 1.5% Q3: 1.7% | AQ13: OW | AR13: 0.017 | AS13: 0.019 | AT13: =21001300.1/1443574666.66667 -> 0.014548122 | AU13: =21353526.28/1438131583.33333 -> 0.014848103 | AV13: =20655365.18/1432882916.66667 -> 0.01441525 | AW13: =19656496.58/1427362916.66667 -> 0.013771197 | AX13: =19571143.83/1421325083.33333 -> 0.013769646 | AY13: =20402700.95/1414776583.33333 -> 0.014421147 | AZ13: =21304105.16/1408744750 -> 0.015122757 | BA13: =20565865.8/1401857916.66667 -> 0.014670435 | BB13: =20836772.33/1394724416.66667 -> 0.014939706 | BC13: =21333587.2/1387280916.66667 -> 0.015377986 | BD13: =21717263.97/1379486750 -> 0.015743003 | BE13: =22524389.6/1371939166.66667 -> 0.016417922 | BF13: =22407272.63/1364507916.66667 -> 0.016421504 | BG13: =22227209.44/1356836416.66667 -> 0.016381643 | BH13: =22333149.36/1348510250 -> 0.016561349 | BR13: =+IFERROR(AVERAGE(AT13:BQ13),"") -> 0.015160651 | BS13: =+IFERROR(VAR(AT13:BQ13),"") -> 9.1007371e-07 | BT13: =+IFERROR(STDEV(AT13:BQ13)*(1-$BS$1),"") -> 0.00047698892 | BU13: =+IF(OR(BT13="",OFFSET(AT13,0,MATCH($B$1,AT$2:BQ$2,0)-1)=""),"",IFERROR(IF(ABS(OFFSET(AT13,0,MATCH($B$1,AT$2:BQ$2,0)-1)-OFFSET(AT13,0,MATCH($B$1,AT$2:BQ$2,0)-2))>BT13,"N","µ"),"")) -> µ | BV13: Ask Paola if in the Credit Trends Portfolio management (12-mo Net Ch Offs/AVG Portfolio) the methodology considers Exposure or Outstanding. And is this the result of the last month or an avrage of the Quarter. Here we use outstanding.
C14: NCO PR Commercial Banking | D14: New 2016 | E14: New 2016 | F14: CCAR | H14: N | L14: Y | P14: Y | Z14: YES | AC14: Monthly | AE14: NUMERATOR: 12M NCO - Commercial Portfolio (includes: COMMERCIAL, CONSTRUCTION, OVERDRAFTS, RCS COMMERCIAL) divided by DENOMINATOR: KPI Total 12 Average Portfolio - Commercial Portfolio (includes: COMMERCIAL, CONSTRUCTION, OVERDRAFTS, RCS COMMERCIAL) | AF14: CCAR (threshold calibration) Risk MI / Rafael Martínez (monthly data) | AG14: CARMOSA: PRODUCTO 1 = COMMERCIAL + CONSTRUCTION | AH14: day 10th of each month depending on Accounting reconciliation | AJ14: The methodology provided by SHUSA and Oliver Wyman is explained in the PDF file 20160426 CCAR-linked RAS methodology.pdf and the final calibration data is included in the PDF file 20160503 BSPR RAS Metrics.pdf. Please refer to slide 2. | AK14: =9841038.63514543/1826186084.21375 -> 0.0053888477 | AL14: Report: Credit Trends as reported by Portfolio Management | AM14: ? | AQ14: OW | AR14: 0.005 | AS14: 0.006 | AT14: =5192599.46/2738561858.195 -> 0.0018961045 | AU14: =5439071.96/2656696274.86167 -> 0.0020473067 | AV14: =4684676.98/2581624024.86167 -> 0.001814624 | AW14: =4907338.01/2517439774.86167 -> 0.0019493368 | AX14: =4674975.06/2473308941.52833 -> 0.0018901703 | AY14: =5512214.9/2441755441.52833 -> 0.0022574803 | AZ14: =5612158.96/2408152024.86167 -> 0.0023304837 | BA14: =6126246.17/2377974691.52833 -> 0.0025762453 | BB14: =5290289.24/2338461139.77833 -> 0.0022622951 | BC14: =5514186.35/2301265531.58333 -> 0.0023961539 | BD14: =6765650.66/2267714864.91667 -> 0.0029834662 | BE14: =5699008.93/2247575364.91667 -> 0.0025356253 | BF14: =5988769.71/2234301114.91667 -> 0.0026803772 | BG14: =6935964.59/2219931531.58333 -> 0.0031244047 | BH14: =7429278.09/2206237781.58333 -> 0.0033673968 | BR14: =+IFERROR(AVERAGE(AT14:BQ14),"") -> 0.0024074314 | BS14: =+IFERROR(VAR(AT14:BQ14),"") -> 2.254575e-07 | BT14: =+IFERROR(STDEV(AT14:BQ14)*(1-$BS$1),"") -> 0.00023741183 | BU14: =+IF(OR(BT14="",OFFSET(AT14,0,MATCH($B$1,AT$2:BQ$2,0)-1)=""),"",IFERROR(IF(ABS(OFFSET(AT14,0,MATCH($B$1,AT$2:BQ$2,0)-1)-OFFSET(AT14,0,MATCH($B$1,AT$2:BQ$2,0)-2))>BT14,"N","µ"),"")) -> N | BV14: Ask Paola what is the equivalent metric reported in the Credit Trands report for this.
C15: NCO PR Personal Loans | D15: New 2016 | E15: New 2016 | F15: CCAR | H15: N | L15: Y | P15: Y | Z15: YES | AC15: Monthly | AE15: NUMERATOR: 12M NCO - Personal Loans Portfolio divided by DENOMINATOR: KPI Total 12 Average Portfolio - Personal Loans Portfolio | AF15: CCAR (threshold calibration) Risk MI / Rafael Martínez (monthly data) | AG15: CARMOSA PRODUCTO 1 = CONSUMO | AH15: day 10th of each month depending on Accounting reconciliation | AJ15: The methodology provided by SHUSA and Oliver Wyman is explained in the PDF file 20160426 CCAR-linked RAS methodology.pdf and the final calibration data is included in the PDF file 20160503 BSPR RAS Metrics.pdf. Please refer to slide 2. | AK15: =12885320.0264068/243323603.487228 -> 0.052955487 | AL15: Report: Credit Trends as reported by Portfolio Management | AM15: 2015 Q1: 5.0% Q2: 5.1% Q3: 5.1% | AQ15: OW | AR15: 0.054 | AS15: 0.06 | AT15: =11900742.26/267267083.333333 -> 0.044527527 | AU15: =12011720.34/267490500 -> 0.044905222 | AV15: =12276309.94/267731166.666667 -> 0.045853122 | AW15: =12451267.6/267956333.333333 -> 0.046467525 | AX15: =12578459.62/268305083.333333 -> 0.046881183 | AY15: =12310548.87/268616750 -> 0.045829416 | AZ15: =12178575.37/268901000 -> 0.045290183 | BA15: =12114629.17/268876500 -> 0.045056482 | BB15: =11983748.41/268800916.666667 -> 0.044582245 | BC15: =11844779.7/268531750 -> 0.04410942 | BD15: =11829246.07/268045916.666667 -> 0.044131417 | BE15: =12110431.5/267291798.845 -> 0.045307905 | BF15: =11860979.58/266336382.178333 -> 0.044533832 | BG15: =11903712.79/265031215.511667 -> 0.04491438 | BH15: =11834996.41/263559048.845 -> 0.044904535 | BR15: =+IFERROR(AVERAGE(AT15:BQ15),"") -> 0.04515296 | BS15: =+IFERROR(VAR(AT15:BQ15),"") -> 6.5196707e-07 | BT15: =+IFERROR(STDEV(AT15:BQ15)*(1-$BS$1),"") -> 0.00040372239 | BU15: =+IF(OR(BT15="",OFFSET(AT15,0,MATCH($B$1,AT$2:BQ$2,0)-1)=""),"",IFERROR(IF(ABS(OFFSET(AT15,0,MATCH($B$1,AT$2:BQ$2,0)-1)-OFFSET(AT15,0,MATCH($B$1,AT$2:BQ$2,0)-2))>BT15,"N","µ"),"")) -> µ | BV15: Ask Paola if Net Write Off 12m (%) from the Credit Trends report is the equivalent. If so, what is the methodology? Esposure or Outstanding? Can we compare against this metric?
C16: NCO PR Credit Cards | D16: New 2016 | E16: New 2016 | F16: CCAR | H16: N | L16: Y | P16: Y | Z16: YES | AC16: Monthly | AE16: NUMERATOR: 12M NCO - Credit Cards Portfolio divided by DENOMINATOR: KPI Total 12 Average Portfolio - Credit Cards Portfolio | AF16: CCAR (threshold calibration) Risk MI / Rafael Martínez (monthly data) | AG16: CARMOSA PRODUCTO 1 = TARJETAS | AH16: day 10th of each month depending on Accounting reconciliation | AJ16: The methodology provided by SHUSA and Oliver Wyman is explained in the PDF file 20160426 CCAR-linked RAS methodology.pdf and the final calibration data is included in the PDF file 20160503 BSPR RAS Metrics.pdf. Please refer to slide 2. | AK16: =15036935.4473544/238217331.128349 -> 0.06312276 | AL16: Report: Credit Trends as reported by Portfolio Management | AM16: 2015 Q1: 6.8% Q2: 6.8% Q3: 6.8% | AQ16: OW | AR16: 0.064 | AS16: 0.074 | AT16: =14750662.42/236322583.333333 -> 0.06241749 | AU16: =14710669.36/237218500 -> 0.062013162 | AV16: =14881019.21/237856166.666667 -> 0.0625631 | AW16: =15070394.47/238445083.333333 -> 0.06320279 | AX16: =15373030.78/238897916.666667 -> 0.06434979 | AY16: =15201929.06/239192000 -> 0.063555341 | AZ16: =15193929.08/239308166.666667 -> 0.06349106 | BA16: =14831436.24/239452916.666667 -> 0.061938841 | BB16: =15127496.74/239363479.833333 -> 0.06319885 | BC16: =14987897.0205/239135313.166667 -> 0.062675382 | BD16: =14795608.4407/238787896.5 -> 0.0619613 | BE16: =15175513.0107/238161809.885 -> 0.063719339 | BF16: =15236139.3807/237437893.218333 -> 0.064168946 | BG16: =15022513.4007/236594476.551667 -> 0.063494776 | BH16: =14667857.8107/235718559.885 -> 0.062226147 | BR16: =+IFERROR(AVERAGE(AT16:BQ16),"") -> 0.062998421 | BS16: =+IFERROR(VAR(AT16:BQ16),"") -> 6.4242996e-07 | BT16: =+IFERROR(STDEV(AT16:BQ16)*(1-$BS$1),"") -> 0.00040075864 | BU16: =+IF(OR(BT16="",OFFSET(AT16,0,MATCH($B$1,AT$2:BQ$2,0)-1)=""),"",IFERROR(IF(ABS(OFFSET(AT16,0,MATCH($B$1,AT$2:BQ$2,0)-1)-OFFSET(AT16,0,MATCH($B$1,AT$2:BQ$2,0)-2))>BT16,"N","µ"),"")) -> N | BV16: Ask Paola if Net Write Off 12m (%) from the Credit Trends report is the equivalent. If so, what is the methodology? Esposure or Outstanding? Can we compare against this metric?
C17: NCO PR TOTAL | P17: Y | Z17: YES | AC17: Monthly | AD17: RSC BSPR #0089 | AE17: It is calculated as twelve month rolling Net Charge Offs (NCO) (i.e., charge off’s less recoveries, excluding the sale of charge off portfolio) divided by average loans portfolio. NCO are the total loans and leases removed from the balance sheet due to their uncollectability minus amounts recovered on loans and leases previously charged-off. NUMERATOR: 12M NCO PR Total divided by DENOMINATOR: KPI Total 12 Average Portfolio - Total | AF17: CCAR (threshold calibration) Risk MI / Rafael Martínez (monthly data) | AG17: Database 1001 | AH17: day 5th of each month | AI17: Budget | AJ17: The methodology provided by SHUSA and Oliver Wyman is explained in the PDF file 20160426 CCAR-linked RAS methodology.pdf and the final calibration data is included in the PDF file 20160503 BSPR RAS Metrics.pdf. Please refer to slide 2. | AK17: 0.016 | AO17: 0.014 | AP17: 0.016 | AQ17: OW | AR17: 0.017 | AS17: 0.018 | AT17: =52845304.24/4685726191.52833 -> 0.011277933 | AU17: =53514987.94/4599536858.195 -> 0.011634864 | AV17: =52497371.31/4520094274.86167 -> 0.01161422 | AW17: =52085496.66/4451204108.195 -> 0.01170144 | AX17: =52197609.29/4401837024.86167 -> 0.011858142 | AY17: =53427393.78/4364340774.86167 -> 0.012241802 | AZ17: =54288768.57/4325105941.52833 -> 0.012552009 | BA17: =53638177.38/4288162024.86167 -> 0.012508431 | BB17: =53238306.72/4241349952.945 -> 0.012552208 | BC17: =53680450.2705/4196213511.41667 -> 0.012792593 | BD17: =55107769.1407/4154035428.08333 -> 0.013266081 | BE17: =55509343.0407/4124968140.31333 -> 0.013456914 | BF17: 0.014 | BG17: =56.0894002207/4078.39359031583 -> 0.013752817 | BH17: =56265281.6707/4054025640.31333 -> 0.013878867 | BR17: =+IFERROR(AVERAGE(AT17:BQ17),"") -> 0.012605888 | BS17: =+IFERROR(VAR(AT17:BQ17),"") -> 8.0636975e-07 | BT17: =+IFERROR(STDEV(AT17:BQ17)*(1-$BS$1),"") -> 0.00044899046 | BU17: =+IF(OR(BT17="",OFFSET(AT17,0,MATCH($B$1,AT$2:BQ$2,0)-1)=""),"",IFERROR(IF(ABS(OFFSET(AT17,0,MATCH($B$1,AT$2:BQ$2,0)-1)-OFFSET(AT17,0,MATCH($B$1,AT$2:BQ$2,0)-2))>BT17,"N","µ"),"")) -> µ | BV17: Cristina - revisar presupuesto e incluir en columna 'Budget' y resultado de Enero/2016 debe dar igual que RTS. Los niveles deben dar igual a lo presentado por Blanca en el BSPR RSC Review
C18: 60+ PR Mortgages | D18: New 2016 | E18: New 2016 | F18: CCAR | H18: N | L18: Y | P18: Y | Y18: Please confirm if the Material Portfolios are to be divided between Total Outstanding Portfolio or Total Outstanding of the Material Portfolios. [SA]: Outstanding of material portfolios | Z18: YES | AC18: Monthly | AE18: NUMERATOR: 60+ days past due Mortgage Portfolio divided by DENOMINATOR: Total Outstanding Balance of Mortgage Portfolio | AF18: CCAR (threshold calibration) Risk MI / Rafael Martínez (monthly data) | AG18: TABLA 1001 = QUERY 0700 | AH18: day 10th of each month depending on Accounting reconciliation | AJ18: The methodology provided by SHUSA and Oliver Wyman is explained in the PDF file 20160426 CCAR-linked RAS methodology.pdf and the final calibration data is included in the PDF file 20160503 BSPR RAS Metrics.pdf. Please refer to slide 4. | AK18: =126.249963851156/1297.64620955215 -> 0.097291514 | AQ18: OW | AR18: 0.106 | AS18: 0.12 | AT18: =135528625.18/1410797000 -> 0.096065292 | AU18: =132504856.2/1403633000 -> 0.094401354 | AV18: =132409704.94/1404930000 -> 0.094246478 | AW18: =134792740.47/1398378000 -> 0.096392206 | AX18: =133821996.92/1386142000 -> 0.096542776 | AY18: =132546435.15/1375241000 -> 0.096380515 | AZ18: =135227944.09/1376171000 -> 0.098263911 | BA18: =132998905.85/1357761000 -> 0.097954578 | BB18: =129996579.14/1348720000 -> 0.09638515 | BC18: =128809994.53/1341648000 -> 0.096008785 | BD18: =132068871.11/1332006000 -> 0.099150358 | BE18: =127596797.49/1327843000 -> 0.096093286 | BF18: =127308962.19/1321622000 -> 0.096327817 | BG18: =123254702.18/1311575000 -> 0.093974574 | BH18: =110803287.35/1305016000 -> 0.084905693 | BR18: =+IFERROR(AVERAGE(AT18:BQ18),"") -> 0.095539518 | BS18: =+IFERROR(VAR(AT18:BQ18),"") -> 1.0669168e-05 | BT18: =+IFERROR(STDEV(AT18:BQ18)*(1-$BS$1),"") -> 0.0016331846 | BU18: =+IF(OR(BT18="",OFFSET(AT18,0,MATCH($B$1,AT$2:BQ$2,0)-1)=""),"",IFERROR(IF(ABS(OFFSET(AT18,0,MATCH($B$1,AT$2:BQ$2,0)-1)-OFFSET(AT18,0,MATCH($B$1,AT$2:BQ$2,0)-2))>BT18,"N","µ"),"")) -> N | BV18: OK Confirmed 3/10/2016
C19: 60+ PR Personal Loans | D19: New 2016 | E19: New 2016 | F19: CCAR | H19: N | L19: Y | P19: Y | Z19: YES | AC19: Monthly | AE19: NUMERATOR: 60+ days past due Personal Loans Portfolio divided by DENOMINATOR: Total Outstanding Balance of Personal Loans Portfolio | AF19: CCAR (threshold calibration) Risk MI / Rafael Martínez (monthly data) | AG19: TABLA 1001 = QUERY 0700 | AH19: day 10th of each month depending on Accounting reconciliation | AJ19: The methodology provided by SHUSA and Oliver Wyman is explained in the PDF file 20160426 CCAR-linked RAS methodology.pdf and the final calibration data is included in the PDF file 20160503 BSPR RAS Metrics.pdf. Please refer to slide 4. | AK19: =2.92728882971842/243.309059327228 -> 0.012031154 | AQ19: OW | AR19: 0.015 | AS19: 0.017 | AT19: =3281975.77/267760000 -> 0.012257155 | AU19: =3368994.58/268881000 -> 0.012529686 | AV19: =3184008.85/268031000 -> 0.011879256 | AW19: =3106624.74/269291000 -> 0.011536311 | AX19: =3069150.7/270174000 -> 0.011359904 | AY19: =3106639.83/270540000 -> 0.011483107 | AZ19: =3367879.94/269777000 -> 0.01248394 | BA19: =3694288.27/268404000 -> 0.013763909 | BB19: =3185553.77/267138000 -> 0.01192475 | BC19: =3088628.47/265938000 -> 0.011614092 | BD19: =3248285.83/262427000 -> 0.012377864 | BE19: =3433970.14/259140586.14 -> 0.013251379 | BF19: =3569446.67/256295000 -> 0.013927102 | BG19: =3735624.25/253219000 -> 0.014752543 | BH19: =3739986.58/250365000 -> 0.014938137 | BR19: =+IFERROR(AVERAGE(AT19:BQ19),"") -> 0.012671942 | BS19: =+IFERROR(VAR(AT19:BQ19),"") -> 1.4008815e-06 | BT19: =+IFERROR(STDEV(AT19:BQ19)*(1-$BS$1),"") -> 0.0005917942 | BU19: =+IF(OR(BT19="",OFFSET(AT19,0,MATCH($B$1,AT$2:BQ$2,0)-1)=""),"",IFERROR(IF(ABS(OFFSET(AT19,0,MATCH($B$1,AT$2:BQ$2,0)-1)-OFFSET(AT19,0,MATCH($B$1,AT$2:BQ$2,0)-2))>BT19,"N","µ"),"")) -> N | BV19: OK Confirmed 3/10/2016
C20: 60+ PR Credit Cards | D20: New 2016 | E20: New 2016 | F20: CCAR | H20: N | L20: Y | P20: Y | Z20: YES | AC20: Monthly | AE20: NUMERATOR: 60+ days past due Credit Cards Portfolio divided by DENOMINATOR: Total Outstanding Balance of Credit Cards Portfolio | AF20: CCAR (threshold calibration) Risk MI / Rafael Martínez (monthly data) | AG20: TABLA 1001 = QUERY 0700 | AH20: day 10th of each month depending on Accounting reconciliation | AJ20: The methodology provided by SHUSA and Oliver Wyman is explained in the PDF file 20160426 CCAR-linked RAS methodology.pdf and the final calibration data is included in the PDF file 20160503 BSPR RAS Metrics.pdf. Please refer to slide 4. | AK20: =11.9094024173571/237.970414168349 -> 0.050045727 | AQ20: OW | AR20: 0.023 | AS20: 0.026 | AT20: =6124188.16/241348000 -> 0.025374928 | AU20: =6154544.16/240428000 -> 0.025598284 | AV20: =5586644.79/237669000 -> 0.023505989 | AW20: =5088717.14/239372000 -> 0.021258615 | AX20: =5063346.41/239138000 -> 0.021173324 | AY20: =4864548.23/239704000 -> 0.02029398 | AZ20: =4915238.59/238959000 -> 0.02056938 | BA20: =5214333.41/239065000 -> 0.021811363 | BB20: =5031679.62/237211758 -> 0.021211763 | BC20: =5120391.01/235516000 -> 0.02174116 | BD20: =5442722.97/236229000 -> 0.023040029 | BE20: =5358917.61/233301960.62 -> 0.022969878 | BF20: =5495221.35/232661000 -> 0.023619005 | BG20: =5572586.62/230307000 -> 0.024196341 | BH20: =5380531.07/227158000 -> 0.023686294 | BR20: =+IFERROR(AVERAGE(AT20:BQ20),"") -> 0.022670022 | BS20: =+IFERROR(VAR(AT20:BQ20),"") -> 2.7926401e-06 | BT20: =+IFERROR(STDEV(AT20:BQ20)*(1-$BS$1),"") -> 0.00083555971 | BU20: =+IF(OR(BT20="",OFFSET(AT20,0,MATCH($B$1,AT$2:BQ$2,0)-1)=""),"",IFERROR(IF(ABS(OFFSET(AT20,0,MATCH($B$1,AT$2:BQ$2,0)-1)-OFFSET(AT20,0,MATCH($B$1,AT$2:BQ$2,0)-2))>BT20,"N","µ"),"")) -> µ | BV20: OK Confirmed 3/10/2016
C21: 60+ PR Commercial Banking | P21: Y | Z21: YES | AC21: Monthly | AE21: NUMERATOR: 60+ days past due Commercial Portfolio divided by DENOMINATOR: Total Outstanding Balance of Commercial Portfolio | AF21: CCAR (threshold calibration) Risk MI / Rafael Martínez (monthly data) | AG21: TABLA 1001 = QUERY 0700 | AH21: day 10th of each month depending on Accounting reconciliation | AJ21: The methodology provided by SHUSA and Oliver Wyman is explained in the PDF file 20160426 CCAR-linked RAS methodology.pdf and the final calibration data is included in the PDF file 20160503 BSPR RAS Metrics.pdf. Please refer to slide 4. | AQ21: OW | AR21: 0.042 | AS21: 0.05 | AT21: =38054535.65/2271638000 -> 0.016752025 | AU21: =36338797.18/2255504000 -> 0.016111165 | AV21: =34670646.47/2261434000 -> 0.015331266 | AW21: =34766026.29/2274490000 -> 0.015285196 | AX21: =34357712.53/2332033000 -> 0.014732944 | AY21: =33551187.93/2369839000 -> 0.014157581 | AZ21: =51090472.45/2347412000 -> 0.021764595 | BA21: =42035363.2/2316949000 -> 0.01814255 | BB21: =45809367.39/2162084379 -> 0.021187595 | BC21: =42045568.68/2141807000 -> 0.019630886 | BD21: =51483463.03/2103880000 -> 0.024470722 | BE21: =45016281.34/2133834000 -> 0.021096431 | BF21: =42846996.51/2112347000 -> 0.020284071 | BG21: =43308674.27/2083069000 -> 0.020790802 | BH21: =43802749.65/2097109000 -> 0.020887207 | BR21: =+IFERROR(AVERAGE(AT21:BQ21),"") -> 0.018708336 | BS21: =+IFERROR(VAR(AT21:BQ21),"") -> 9.810134e-06 | BT21: =+IFERROR(STDEV(AT21:BQ21)*(1-$BS$1),"") -> 0.0015660567 | BU21: =+IF(OR(BT21="",OFFSET(AT21,0,MATCH($B$1,AT$2:BQ$2,0)-1)=""),"",IFERROR(IF(ABS(OFFSET(AT21,0,MATCH($B$1,AT$2:BQ$2,0)-1)-OFFSET(AT21,0,MATCH($B$1,AT$2:BQ$2,0)-2))>BT21,"N","µ"),"")) -> µ | BV21: OK Confirmed 3/10/2016
C22: 60+ PR TOTAL | P22: Y | Y22: Included a new 60+ Total Metric to monitor NCOs at a Consolidadted Bank level Portfolio Management: 60+ Total PR: sugiero eliminarlo pues en realidad no hay un gestor identificado en el Banco que observe esta cifra agregada. Aún más, las estrategias para los productos/segmentos son tan distintas que se recogen en PEC’s distintos administrados por grupos ejecutivos distintos. | Z22: YES | AE22: NUMERATOR: 60+ Total Portfolio divided by DENOMINATOR: Total Portfolio % | AF22: CCAR (threshold calibration) Risk MI / Rafael Martínez (monthly data) | AG22: TABLA 1001 = QUERY 0700 | AH22: day 10th of each month depending on Accounting reconciliation | AJ22: The methodology provided by SHUSA and Oliver Wyman is explained in the PDF file 20160426 CCAR-linked RAS methodology.pdf and the final calibration data is included in the PDF file 20160503 BSPR RAS Metrics.pdf. Please refer to slide 4. | AQ22: OW | AR22: 0.061 | AS22: 0.07 | AT22: =182989324.76/4191543000 -> 0.043656793 | AU22: =178367192.12/4168446000 -> 0.042789853 | AV22: =175851005.05/4172064000 -> 0.042149642 | AW22: =177754108.64/4181531000 -> 0.042509337 | AX22: =176312206.56/4227487000 -> 0.04170615 | AY22: =174068811.14/4255324000 -> 0.040906124 | AZ22: =194601535.07/4232319000 -> 0.045979884 | BA22: =183942890.73/4182179000 -> 0.043982549 | BB22: =184023179.92/4015154137 -> 0.045832158 | BC22: =179064582.69/3984909000 -> 0.044935677 | BD22: =192243342.94/3934542000 -> 0.048860412 | BE22: =181405966.58/3954119546.76 -> 0.045877714 | BF22: =179220626.72/3922925000 -> 0.045685458 | BG22: =175871587.32/3878170000 -> 0.045349118 | BH22: =163726554.65/3879648000 -> 0.042201394 | BR22: =+IFERROR(AVERAGE(AT22:BQ22),"") -> 0.044161484 | BS22: =+IFERROR(VAR(AT22:BQ22),"") -> 4.6334737e-06 | BT22: =+IFERROR(STDEV(AT22:BQ22)*(1-$BS$1),"") -> 0.0010762753 | BU22: =+IF(OR(BT22="",OFFSET(AT22,0,MATCH($B$1,AR$2:BO$2,0)-1)=""),"",IFERROR(IF(ABS(OFFSET(AT22,0,MATCH($B$1,AR$2:BO$2,0)-1)-OFFSET(AT22,0,MATCH($B$1,AR$2:BO$2,0)-2))>BT22,"N","µ"),"")) | BV22: Used 'Concentration To One Obligor Without Guarantee' | BY22: Comparamos
B23: Credit risk (concentration) | C23: Single Obligor (Corp. and IFIs) Exposure Without Guarantee | D23: N/A | E23: $500 MM | F23: Solvency | H23: Y | L23: Y | P23: Y | Z23: YES | AA23: Used 'Concentration To One Obligor Without Guarantee' RTS metric | AC23: Monthly | AD23: RTS BSPR 0020 | AE23: Used 'Concentration To One Obligor Without Guarantee' Total exposure of largest one obligor without guarantee (excluding U.S. and P.R. Government authorities, agencies, dependencies and municipalities’ loans) is compared with legal lending limit permitted by the Banking Law of Puerto Rico. The maximum loan limit to one obligor permitted by the Banking Law of Puerto Rico is up to 15% of the 50% of the bank’s undistributed earnings. To identify the highest obligor without guarantee in the Database 1001 BSPR, it shoud be filtered as follows: 1- Bank column select “004” (BSPR bank) 2- Product column select “05” (Commercial Risk) 3- Group name column exclude “Abengoa” (Abengoa group is the highest exposure however only $25MM is without guarantee). 4- Segment Column exclude “Institucional Público” (U.S and P R Government authorities, agencies, dependencies and municipalities’ loans) 5- Guarantee group select “Sin Garantía” The balance used is “Riesgo del cliente”, after filters have been applied, it should be sorted in order to identify the highest balance. The legal lending limit is calculated by Contropllership Unit in a quarterly basis and reported to ERM officers. | AF23: Risk MI / Rafael Martínez | AG23: TABLA 1001 | AH23: day 10th of each month depending on Accounting reconciliation | AJ23: Considered the Legal Lending Limit as of 3/31/2016 ($69.6MM). The 20% deviation from the Red (Limit) to the Green level represents the buffer permitted by the BOD to the Senior Management to manage the risks without risking the Bank’s capital. Per the Capital Stress Test (CCAR), there is ~20% distance from the baseline to the adverse scenario (stressed) while still maintaining the capital levels above the limits required by the regulator. That ~20% deviation is used from the Red (Limit) to the Green level in the RAS thus integrating the Capital Stress Test (CCAR) into the RAS. | AQ23: $55.7MM | AR23: $55.8MM | AS23: $69.6MM | AT23: 37.927291 | AU23: 37.927291 | AV23: 37.927202 | AW23: 37.779458 | AX23: 37.779458 | AY23: 36.03334 | AZ23: 36.033226 | BA23: 36.033226 | BB23: 36.033132 | BC23: 35.588046 | BD23: 35.588046 | BE23: 40 | BF23: 26 | BG23: 26 | BH23: 26 | BR23: =+IFERROR(AVERAGE(AT23:BQ23),"") -> 34.843314 | BS23: =+IFERROR(VAR(AT23:BQ23),"") -> 22.410783 | BT23: =+IFERROR(STDEV(AT24:BQ24)*(1-$BS$1),"") -> 32.31606 | BU23: =+IF(OR(BT23="",OFFSET(AT24,0,MATCH($B$1,AT$2:BQ$2,0)-1)=""),"",IFERROR(IF(ABS(OFFSET(AT24,0,MATCH($B$1,AT$2:BQ$2,0)-1)-OFFSET(AT24,0,MATCH($B$1,AT$2:BQ$2,0)-2))>BT23,"N","µ"),"")) -> µ | BW23: Used to be Single obligor exposure, included (Corp. and IFIs) to the name
C24: Top 20 Corporates Exposure | D24: $7.0B | E24: $8.0 B | F24: Solvency | H24: Y | L24: Y | P24: Y | Y24: 4/28/2016 Excludes Public Sector | Z24: YES | AC24: Monthly | AE24: Top 20 Total Exposure. Segment Column exclude “Institucional Público” (U.S and P R Government authorities, agencies, dependencies and municipalities’ loans) | AF24: Risk MI / Rafael Martínez | AG24: TABLA 1001 | AH24: day 10th of each month depending on Accounting reconciliation | AJ24: Thresholds defined per Historical Data: The the Green level is defined considering the average of Jan15 - Dec15 and the added the Standard Deviation for the same period. After Green Level is defined, the Red Limit is set using a 20% deviation. The Amber threshold is the remaining range between the Green and the Red threshold. The 20% deviation from the Green to the Red (Limit) represents the buffer permitted by the BOD to the Senior Management to manage the risks without risking the Bank’s capital. Per the Capital Stress Test (CCAR), there is ~20% distance from the baseline to the adverse scenario (stressed) while still maintaining the capital levels above the limits required by the regulator. That ~20% deviation is used from the Green level to the Red (Limit) in the RAS thus integrating the Capital Stress Test (CCAR) into the RAS. | AQ24: =STDEV(AT24:BE24)+(AVERAGE(AT24:BE24)) -> 827.25576 | AR24: =AQ24+1 -> 828.25576 | AS24: =AQ24*1.2 -> 992.70691 | AT24: 836.27936 | AU24: 802.55633 | AV24: 800.59972 | AW24: 801.34267 | AX24: 809.52345 | AY24: 806.86273 | AZ24: 798.30047 | BA24: 790.27428 | BB24: 680.28242 | BC24: 684.70841 | BD24: 658.98479 | BE24: 691.24722 | BF24: 689.08854 | BG24: 687.3231 | BH24: 687.61237 | BR24: =+IFERROR(AVERAGE(AT24:BQ24),"") -> 748.33239 | BS24: =+IFERROR(VAR(AT24:BQ24),"") -> 4177.311 | BW24: Used to be Top 20
C25: # of counterparties with Santander Risk Rating (internal) < 4.5 and exposure>$10MM (PR) | D25: New 2016 | E25: New 2016 | F25: Solvency | H25: Y | L25: Y | P25: Y | Z25: YES | AC25: Monthly | AE25: # of counterparties with Santander Risk Rating (internal) < 4.5 and exposure>$10MM | AF25: Risk MI / Rafael Martínez | AG25: TABLA 1001 | AH25: day 10th of each month depending on Accounting reconciliation | AJ25: Thresholds defined per Historical Data - The average of Jan15 - Dec15 is calculated and the added the Standard Deviation for the same period to define the Green level. In this case since the difference the 20% deviation to the Red Limit is not significant, the gap between the thresholds were be manually adjusted. | AQ25: =STDEV(AT25:BE25)+(AVERAGE(AT25:BE25)) -> 4.2598196 | AR25: 5 | AS25: 6 | AT25: 2 | AU25: 5 | AV25: 5 | AW25: 5 | AX25: 4 | AY25: 2 | AZ25: 1 | BA25: 1 | BB25: 1 | BC25: 1 | BD25: 2 | BE25: 2 | BF25: 2 | BG25: 3 | BH25: 3 | BT25: =+IFERROR(STDEV(AT26:BQ26)*(1-$BS$1),"") -> 5.7074072 | BU25: =+IF(OR(BT25="",OFFSET(AT26,0,MATCH($B$1,AT$2:BQ$2,0)-1)=""),"",IFERROR(IF(ABS(OFFSET(AT26,0,MATCH($B$1,AT$2:BQ$2,0)-1)-OFFSET(AT26,0,MATCH($B$1,AT$2:BQ$2,0)-2))>BT25,"N","µ"),"")) | BV25: Per SBNA methodology for calibration of OCC limit - We set a max $ amount for all industries (e.g. SBNA is $5 bn max per industry), any industry which goes above that needs special approval from the Board; SBNA set the limit as being approx. 50% of SBNA CET1+ACL) | BY25: ?
C26: Industry Exposure (by OCC group) | D26: New 2016 | E26: New 2016 | F26: Solvency | H26: Y | L26: Y | P26: Y | T26: PR analysing Altair system | Y26: 1) Confirm with SHUSA if we can use Outstanding instead of Exposure to be aligned with BSPR local Concentration Guideline. 2) Will this metrics be divided per industry? All the industries will be included in the RAS or just the material industries? 3) Compared the SBNA OCC grouping vs. BSPR current local Concentration Guideline. Overall we can work on the segmentation however in some cases locally we would need another level of segregation (for risk management purposes as well as definition of strategies per our credit policies) which we can later aggregate to reach the SBNA OCC grouping. Groups which BSPR will have a higher level of segregation for further aggregation for the RAS: Government & Education: -Government & Education (Municipalities) -Government & Education (Indirect Risk (PRIDCO)) -Government & Education (Sovereign Risk / Agencies / Public Corp.) -Government & Education (Education) Health Care & Pharmaceuticals -Health Care & Pharmaceuticals (Health Care) -Health Care & Pharmaceuticals (Hospital) Real Estate & Construction -Real Estate & Construction (Commercial Real Estate) -Real Estate & Construction (Construction Developers) Restaurant & Hotel -Hotels and Tourism (Excluding Restaurant) Retail Stores Exc. Food & Drug -Retail Stores Exc. Food & Drug (Retail Sales including Auto Sales and Restaurant) -Retail Stores Exc. Food & Drug (Construction Related) | Z26: YES | AA26: Excludes CRE and Public Sector because there are separate specific metrics to monitor these exposures. SHUSA: Per SBNA methodology for calibration of OCC limit - We set a max $ amount for all industries (e.g. SBNA is $5 bn max per industry), any industry which goes above that needs special approval from the Board; SBNA set the limit as being approx. 50% of SBNA CET1+ACL) BSPR: Currently, the BSPR Concentration Guideline (which is approved by the BOD) has a maximum exposure of 10% (excluding CRE and Public Sector). This means that 10% of our total portfolio would be $3,880MM x 10% = $388MM. Therefore, we would have to apply the max concentration approved by the BOD for an industry to set the Red Limit and apply as a standard max limit for the rest of the industries in order to remain consistent with the BSPR Concentration Guideline. SHUSA said they will discuss further and provide feedback | AC26: Monthly | AE26: Highest industry exposure according to OCC segmentation excluding Realestate & Construction (which includes CRE) and Government and Education (which inclides Public Sector). Excludes CRE and Public Sector because there are specific metrics to monitor those portfolios. | AF26: Concentration Guideline (threshold calibration) Risk MI / Rafael Martínez | AG26: TABLA 1001 | AH26: day 10th of each month depending on Accounting reconciliation | AI26: Concentration Guideline | AJ26: Currently, the BSPR Concentration Guideline (which is approved by the BOD) has a maximum exposure of 10% (excluding CRE and Public Sector). This means that 10% of BSPR total portfolio would be $3,880MM x 10% = $388MM (considered the March 2016 Total Exposure Portfolio of $3,880MM). Therefore, we would have to apply the max concentration approved by the BOD for an industry to set the Red Limit and apply as a standard max limit for the rest of the industries in order to remain consistent with the BSPR Concentration Guideline. After Red Limit is defined, the Green Limit is set using a 20% deviation. The Amber threshold is the remaining range between the Green and the Red threshold. The 20% deviation from the Red (Limit) to the Green level represents the buffer permitted by the BOD to the Senior Management to manage the risks without risking the Bank’s capital. Per the Capital Stress Test (CCAR), there is ~20% distance from the baseline to the adverse scenario (stressed) while still maintaining the capital levels above the limits required by the regulator. That ~20% deviation is used from the Red (Limit) to the Green level in the RAS thus integrating the Capital Stress Test (CCAR) into the RAS. | AQ26: =AS26*(1-0.2) -> 310.4 | AR26: =AQ26+1 -> 311.4 | AS26: =3880*0.1 -> 388 | AZ26: ='Industry Exposure OCC'!H43 -> 314.925 | BB26: ='Industry Exposure OCC'!K43 -> 296.575 | BE26: ='Industry Exposure OCC'!N43 -> 291.76 | BH26: ='Industry Exposure OCC'!T43 -> 290.008 | BR26: =+IFERROR(AVERAGE(AT26:BQ26),"") -> 298.317 | BS26: =+IFERROR(VAR(AT26:BQ26),"") -> 130.29799 | BT26: =+IFERROR(STDEV(AT27:BQ27)*(1-$BS$1),"") -> 17.012161 | BU26: =+IF(OR(BT26="",OFFSET(AT27,0,MATCH($B$1,AT$2:BQ$2,0)-1)=""),"",IFERROR(IF(ABS(OFFSET(AT27,0,MATCH($B$1,AT$2:BQ$2,0)-1)-OFFSET(AT27,0,MATCH($B$1,AT$2:BQ$2,0)-2))>BT26,"N","µ"),"")) -> N | BV26: Pending to confirm with SHUSA how metric will be calibrated. Shouldn't this limit be the same as the 'Industry exposure (by OCC group) (PR)'? The local Concentration Guideline indicates 150% of Tier 1 | BY26: Concentration Guideline
C27: CRE Exposure | D27: New 2016 | E27: New 2016 | F27: Solvency | H27: Y | L27: Y | P27: Y | Y27: Confirm with SHUSA if we can use Outstanding instead of Exposure to be aligned with BSPR local Concentration Guideline. [SA]: As above - align to SBNA | Z27: YES | AC27: Monthly | AE27: CRE exposure - pendiente confirmar cual es la metodología de calculo CRE exposure (excl. Multifamily) (PR) | AF27: Risk MI / Rafael Martínez | AG27: PROBLEMA IDENTIFICANDO STOCK, NO HAY MARCA EN SISTEMA Y LO QUE SE LLEVA ES MANUAL. Data included is Exposure provided by Rafa in 0000 RISK TOLERANCE | AH27: day 10th of each month depending on Accounting reconciliation | AI27: Concentration Guideline | AJ27: Currently, the BSPR Concentration Guideline (which is approved by the BOD) has a maximum exposure of 28% for the industry of CRE (portfolio with the highest allowed concentration). This means that 28% of our total portfolio would be $3,880MM x 28% = $1,086MM (considered the March 2016 Total Exposure Portfolio of $3,880MM). Therefore, we would have to apply the max concentration approved by the BOD for an industry to set the Red Limit and apply as a standard max limit for the rest of the industries in order to remain consistent with the BSPR Concentration Guideline. After Red Limit is defined, the Green Limit is set using a 20% deviation. The Amber threshold is the remaining range between the Green and the Red threshold. The 20% deviation from the Green to the Red (Limit) represents the buffer permitted by the BOD to the Senior Management to manage the risks without risking the Bank’s capital. Per the Capital Stress Test (CCAR), there is ~20% distance from the baseline to the adverse scenario (stressed) while still maintaining the capital levels above the limits required by the regulator. That ~20% deviation is used from the Red level (Limit) to the Green in the RAS thus integrating the Capital Stress Test (CCAR) into the RAS | AQ27: =AS27*(1-0.2) -> 869.12 | AR27: =AQ27+1 -> 870.12 | AS27: =3880*0.28 -> 1086.4 | AT27: 559.48319 | AU27: 565.52119 | AV27: 570.67219 | AW27: 583.10147 | AX27: 613.8976 | AY27: 611.92483 | AZ27: 614.45283 | BA27: 607.52577 | BB27: 602.1959 | BC27: 599.09236 | BD27: 598.03638 | BE27: 587.22652 | BF27: 590.60458 | BG27: 510.02835 | BH27: 508.19472 | BR27: =+IFERROR(AVERAGE(AT27:BQ27),"") -> 581.46386 | BS27: =+IFERROR(VAR(AT27:BQ27),"") -> 1157.6545 | BT27: =+IFERROR(STDEV(AT28:BQ28)*(1-$BS$1),"") -> 33.353077 | BU27: =+IF(OR(BT27="",OFFSET(AT28,0,MATCH($B$1,AT$2:BQ$2,0)-1)=""),"",IFERROR(IF(ABS(OFFSET(AT28,0,MATCH($B$1,AT$2:BQ$2,0)-1)-OFFSET(AT28,0,MATCH($B$1,AT$2:BQ$2,0)-2))>BT27,"N","µ"),"")) -> µ | BV27: Pending to confirm with SHUSA how metric will be calibrated. Shouldn't this limit be the same as the 'Industry exposure (by OCC group) (PR)'? The local Concentration Guideline indicates 75% of Tier 1 | BY27: Aplicamos el max de CRE
C28: Public Sector Exposure | D28: New 2016 | E28: New 2016 | F28: Solvency | H28: Y | L28: Y | P28: Y | Y28: Metric was change from 'Institutional exposure (PR)' to 'Public sector exposure (PR)' in order to include all exposure with PR government, municipalities, government agencies, etc. [SA]: OK Confirm with SHUSA if we can use Outstanding instead of Exposure to be aligned with local Concentration Guideline. Concenration Guideline presented Quarterly. [SA]: As above - align to SBNA | Z28: YES | AC28: Monthly | AE28: Total Exposure equals Drawn plus Available plus Contingencies for PR Government, Municipalities, Government Agencies, etc. | AF28: Risk MI / Rafael Martínez | AG28: TABLA 1001 | AH28: day 10th of each month depending on Accounting reconciliation | AI28: Concentration Guideline | AJ28: Currently, the BSPR Concentration Guideline (which is approved by the BOD) has a maximum exposure of 14% for the Public Sector. This means that 14% of our total portfolio would be $3,880MM x 14% = $543MM (considered the March 2016 Total Exposure Portfolio of $3,880MM). Therefore, we would have to apply the max concentration approved by the BOD for an industry to set the Red Limit and apply as a standard max limit for the rest of the industries in order to remain consistent with the BSPR Concentration Guideline. After Red Limit is defined, the Green Limit is set using a 20% deviation. The Amber threshold is the remaining range between the Green and the Red threshold. The 20% deviation from the Green to the Red (Limit) represents the buffer permitted by the BOD to the Senior Management to manage the risks without risking the Bank’s capital. Per the Capital Stress Test (CCAR), there is ~20% distance from the baseline to the adverse scenario (stressed) while still maintaining the capital levels above the limits required by the regulator. That ~20% deviation is used from the Red level (Limit) to the Green in the RAS thus integrating the Capital Stress Test (CCAR) into the RAS. | AQ28: =AS28*(1-0.2) -> 434.56 | AR28: =AQ28+1 -> 435.56 | AS28: =3880*0.14 -> 543.2 | AT28: 474.77383 | AU28: 471.88535 | AV28: 471.47619 | AW28: 471.08293 | AX28: 468.20172 | AY28: 460.37746 | AZ28: 456.86937 | BA28: 453.97987 | BB28: 326.12961 | BC28: 325.71993 | BD28: 321.74299 | BE28: 349.69984 | BF28: 349.13849 | BG28: 348.5808 | BH28: 347.97281 | BR28: =+IFERROR(AVERAGE(AT28:BQ28),"") -> 406.50875 | BS28: =+IFERROR(VAR(AT28:BQ28),"") -> 4449.7109 | BT28: =+IFERROR(STDEV(AT29:BQ29)*(1-$BS$1),"") | BU28: =+IF(OR(BT28="",OFFSET(AT29,0,MATCH($B$1,AT$2:BQ$2,0)-1)=""),"",IFERROR(IF(ABS(OFFSET(AT29,0,MATCH($B$1,AT$2:BQ$2,0)-1)-OFFSET(AT29,0,MATCH($B$1,AT$2:BQ$2,0)-2))>BT28,"N","µ"),""))
B29: Liquidity / Funding Risk | C29: Stressed Survival Period (days) | D29: 90 | E29: 60 | F29: Market Risk | H29: Y | L29: Y | P29: Y | Z29: YES | AA29: Historical Data is not available as this is a newly implemented metric | AC29: Monthly | AE29: The amount of days remaining until there is a cash shortfall under stressed conditions. | AF29: Market Risk / Marilena Castro | AG29: Metric is stored in EXCEL in a Local Network. Currently data is extracted from Balance Sheet statements for BSPR, SSC LLC and BanCorp, OFSA system, NMD Calculador (corporate system), which are consolidated into one spreadsheet (Excel). As part of the Market Risk Efficiency Plan, a server is being developed in which this data will be stored. | AH29: The availability depends on ALCO Committee date towards the end of the month. | AI29: Liquidity Policy | AJ29: Liquidity Policy Pending updated Liquidity Policy, triggers and limits provided by Market Risk Department according to analysis and presentation done and approved by the Board on February 2016. Refer to document Market Risk 2016 Limits Analysis v2 - Copy.docx, section 2.2. The Local Limit 2016 was set as the Ambar trigger and the 2016 RAS was set as the Red limit. | AL29: Market Risk Update Risk Committee as Liquidity Horizon ALCO Risk Scorecard | AQ29: > 90 days | AR29: < 90 days | AS29: <= 60 days | AT29: N/Avail | AU29: N/Avail | AV29: N/Avail | AW29: N/Avail | AX29: N/Avail | AY29: N/Avail | AZ29: N/Avail | BA29: N/Avail | BB29: N/Avail | BC29: N/Avail | BD29: N/Avail | BE29: > 90 days | BF29: N/Avail | BG29: N/Avail | BH29: > 90 days | BR29: =+IFERROR(AVERAGE(AT29:BQ29),"") | BS29: =+IFERROR(VAR(AT29:BQ29),"") | BT29: =+IFERROR(STDEV(AT30:BQ30)*(1-$BS$1),"") -> 0.011265596 | BU29: =+IF(OR(BT29="",OFFSET(AT30,0,MATCH($B$1,AT$2:BQ$2,0)-1)=""),"",IFERROR(IF(ABS(OFFSET(AT30,0,MATCH($B$1,AT$2:BQ$2,0)-1)-OFFSET(AT30,0,MATCH($B$1,AT$2:BQ$2,0)-2))>BT29,"N","µ"),"")) -> µ
C30: Structural funding ratio (%) | D30: 1.05 | E30: 1 | F30: Market Risk | H30: Y | L30: Y | P30: Y | Z30: YES | AC30: Monthly | AD30: RTS BSPR #0170 | AE30: Calculation is adapted based on the additional assets that require stable funding (illiquid assets in the portfolio). As a general rule, wholesale short term financing cannot be considered as stable funding. The limit will be set according to the situation, generally >100% and with a minimum surplus. In some cases a limit under 100% could be set, but adding a maximum deficit amount. | AF30: Market Risk / Marilena Castro | AG30: Metric is stored in EXCEL in a Local Network. Currently data is extracted from Balance Sheet statements for BSPR, SSC LLC and BanCorp, OFSA system, NMD Calculador (corporate system), which are consolidated into one spreadsheet (Excel). As part of the Market Risk Efficiency Plan, a server is being developed in which this data will be stored. | AH30: The availability depends on ALCO Committee date towards the end of the month. | AI30: Liquidity Policy | AJ30: Liquidity Policy Pending updated Liquidity Policy, triggers and limits provided by Market Risk Department according to analysis and presentation done and approved by the Board on February 2016. Refer to document Market Risk 2016 Limits Analysis v2 - Copy.docx, section 2.2. The Local Limit 2016 was set as the Ambar trigger and the 2016 RAS was set as the Red limit. | AL30: Market Risk Update Risk Committee ALCO Risk Scorecard | AM30: 2015 February, March, May, June, August, September, November and December OK In Alco Risk Scorecard December is 107.72% Dec 2015 different than Dec 2015 in ALCO Risk Scorecard report (107.72%) (Jan 2016 107.87%) | AP30: 1 | AQ30: > 104% | AR30: <=104% | AS30: <= 102% | AT30: N/Avail | AU30: N/Avail | AV30: 1.0681 | AW30: 1.0657 | AX30: 1.0377 | AY30: 1.0237 | AZ30: 1.0352352 | BA30: 1.0426862 | BB30: 1.0831699 | BC30: 1.0771823 | BD30: 1.0838 | BE30: 1.0754 | BF30: 1.0787 | BG30: 1.0804 | BH30: 1.0947 | BR30: =+IFERROR(AVERAGE(AT30:BQ30),"") -> 1.0651134 | BS30: =+IFERROR(VAR(AT30:BQ30),"") -> 0.00050765461 | BT30: =+IFERROR(STDEV(#REF!)*(1-$BS$1),"") | BU30: =+IF(OR(BT30="",OFFSET(#REF!,0,MATCH($B$1,AT$2:BQ$2,0)-1)=""),"",IFERROR(IF(ABS(OFFSET(#REF!,0,MATCH($B$1,AT$2:BQ$2,0)-1)-OFFSET(#REF!,0,MATCH($B$1,AT$2:BQ$2,0)-2))>BT30,"N","µ"),"")) -> #REF!
C31: Liquidity Coverage Ratio (%) | E31: YES | F31: Historical Data is not available as this is a newly implemented metric | Y31: 4/27/2016 Eliminated from the RAS according to email from Scott Amarucci stating it would be redundant considering BSPR’s profile. However it will be maintained as operating limit and monitored by local market risk area. | Z31: YES | AC31: Monthly | AF31: Market Risk / Marilena Castro | AI31: Liquidity Policy | AJ31: Liquidity Policy Pending updated Liquidity Policy, triggers and limits provided by Market Risk Department according to analysis and presentation done and approved by the Board on February 2016. Refer to document Market Risk 2016 Limits Analysis v2 - Copy.docx, section 2.2. The Local Limit 2016 was set as the Ambar trigger and the 2016 RAS was set as the Red limit. | AL31: ALCO Risk Scorecard | AQ31: >110% | AR31: <= 110% | AS31: <= 100% | AT31: N/Avail | AU31: N/Avail | AV31: N/Avail | AW31: N/Avail | AX31: N/Avail | AY31: N/Avail | AZ31: N/Avail | BA31: N/Avail | BB31: N/Avail | BC31: N/Avail | BD31: N/Avail | BE31: 1.3073 | BF31: 1.3774 | BG31: 1.427 | BH31: 1.5002 | BR31: =+IFERROR(AVERAGE(AT31:BQ31),"") -> 1.402975 | BS31: =+IFERROR(VAR(AT31:BQ31),"") -> 0.0066125625 | BT31: =+IFERROR(STDEV(AT31:BQ31)*(1-$CL$1),"") -> 0.081317664 | BU31: =+IF(OR(BT31="",OFFSET(AT31,0,MATCH($B$1,AT$2:BQ$2,0)-1)=""),"",IFERROR(IF(ABS(OFFSET(AT31,0,MATCH($B$1,AT$2:BQ$2,0)-1)-OFFSET(AT31,0,MATCH($B$1,AT$2:BQ$2,0)-2))>BT31,"N","µ"),"")) -> µ
B32: Interest Rate Risk | C32: ALM NII (+/-100bps) | D32: ($120)MM | E32: ($140)MM | F32: Market Risk | H32: Y | L32: Y | P32: Y | T32: New for Group Dec-15 - with 100bps | V32: Ensure alignment with Group definition | W32: Finance / Treasury | X32: Market & Liquidity | Y32: 4/27/2016 Required to be calculated in percentage | Z32: YES | AC32: Monthly | AF32: Market Risk / Marilena Castro | AG32: Metric is stored in EXCEL in a Local Network. Currently data is extracted from ORACLE, OFSA, MIAC, Calculador (corporate system), and other working papers (Excels) which are consolidated into one spreadsheet (Excel). As part of the Market Risk Efficiency Plan, a server is being developed in which this data will be stored. | AH32: The availability depends on ALCO Committee date towards the end of the month. | AI32: IRR Policy | AJ32: IRR Policy Pending updated IRR Policy, triggers and limits provided by Market Risk Department according to analysis and presentation done and approved by the Board on February 2016. Refer to document Market Risk 2016 Limits Analysis v2 - Copy.docx, section 2.1. The Local Limit 2016 was set as the Ambar trigger and the RAS 2016 was set as the Red limit. These were then translated into percentages as per SHUSA's request, which is included in RAS Limits porcentual v3 excel document provided by the Market Risk Department. | AL32: Market Risk Update Risk Committee as NIM | AM32: 2015 March OK June OK September OK | AO32: ($12.0MM) | AP32: ($15.0MM) | AQ32: > -4.0% | AR32: <=-4.0% | AS32: <= -5.0% | AT32: N/Avail | AU32: N/Avail | AV32: N/Avail | AW32: N/Avail | AX32: N/Avail | AY32: N/Avail | AZ32: N/Avail | BA32: N/Avail | BB32: N/Avail | BC32: N/Avail | BD32: N/Avail | BE32: N/Avail | BF32: 0.0163 | BG32: 0.0205 | BH32: 0.0233 | BR32: =+IFERROR(AVERAGE(AT32:BQ32),"") -> 0.020033333 | BS32: =+IFERROR(VAR(AT32:BQ32),"") -> 1.2413333e-05 | BT32: =+IFERROR(STDEV(AT33:BQ33)*(1-$BS$1),"") -> 0.0016479786 | BU32: =+IF(OR(BT32="",OFFSET(AT33,0,MATCH($B$1,AT$2:BQ$2,0)-1)=""),"",IFERROR(IF(ABS(OFFSET(AT33,0,MATCH($B$1,AT$2:BQ$2,0)-1)-OFFSET(AT33,0,MATCH($B$1,AT$2:BQ$2,0)-2))>BT32,"N","µ"),"")) -> N | BV32: Used 'ALM MVE (+ 200bps)'
C33: ALM MVE (+/-100bps) | D33: ($1,070)MM | E33: ($1,220)MM | F33: Market Risk | H33: Y | L33: Y | P33: TBD | T33: New for Group Dec-15 - with 100bps | V33: Ensure alignment with Group definition | W33: Finance / Treasury | X33: Market & Liquidity | Y33: 4/27/2016 Agreed to be +/- 100 and required to be calculated in percentage. Currently the Market Risk area calculates the 'ALM MVE (+200bps)' since interest curve cannot go down to (-200bps). The risk is with the (+200bps) which is the more severe since it's where we could experience losses. [SA]: Ok - will need to follow up with M. Lasso As discussed with Beatriz Shapiro on 2/12/2016 - Manolo Lasso will be discussing metric with Spain. 4/19/16 Confirmed with Market Risk Area. OK | Z33: YES | AC33: Monthly | AF33: Market Risk / Marilena Castro | AG33: Metric is stored in EXCEL in a Local Network. Currently data is extracted from ORACLE, OFSA, MIAC, Calculador (corporate system), and other working papers (Excels) which are consolidated into one spreadsheet (Excel). As part of the Market Risk Efficiency Plan, a server is being developed in which this data will be stored. | AH33: The availability depends on ALCO Committee date towards the end of the month. | AI33: IRR Policy | AJ33: IRR Policy Pending updated IRR Policy, triggers and limits provided by Market Risk Department according to analysis and presentation done and approved by the Board on February 2016. Refer to document Market Risk 2016 Limits Analysis v2 - Copy.docx, section 2.1. The Local Limit 2016 was set as the Ambar trigger and the RAS 2016 was set as the Red limit. These were then translated into percentages as per SHUSA's request, which is included in RAS Limits porcentual v3 excel document provided by the Market Risk Department. | AL33: Market Risk Update Risk Committee | AM33: 2015 February, March, May, June, August, September, November and December OK | AQ33: > -5.4% | AR33: <=-5.4% | AS33: <= -6.0% | AT33: N/Avail | AU33: N/Avail | AV33: N/Avail | AW33: N/Avail | AX33: N/Avail | AY33: N/Avail | AZ33: N/Avail | BA33: N/Avail | BB33: N/Avail | BC33: N/Avail | BD33: N/Avail | BE33: N/Avail | BF33: -0.0217 | BG33: -0.0175 | BH33: -0.0152 | BR33: =+IFERROR(AVERAGE(AT33:BQ33),"") -> -0.018133333 | BS33: =+IFERROR(VAR(AT33:BQ33),"") -> 1.0863333e-05 | BT33: =+IFERROR(STDEV(AT34:BQ34)*(1-$BS$1),"") | BU33: =+IF(OR(BT33="",OFFSET(AT34,0,MATCH($B$1,AT$2:BQ$2,0)-1)=""),"",IFERROR(IF(ABS(OFFSET(AT34,0,MATCH($B$1,AT$2:BQ$2,0)-1)-OFFSET(AT34,0,MATCH($B$1,AT$2:BQ$2,0)-2))>BT33,"N","µ"),"")) | BV33: Under discussion between SHUSA and Local Operational Teams | BW33: Slide 7: Indicates it is included
B34: Operational Risk | C34: Gross Operational Risk Losses / Gross Margin on a 12 month trailing basis | D34: 0.03 | E34: 0.05 | F34: OP Risk Team | H34: Y | L34: Y | P34: Y | Z34: YES | AA34: Pending calibration confirmation from SHUSA Operational Team | AC34: Quarterly | AE34: Total Gross Operational Risk Losses / Total Gross Margin on a 12 month trailing basis | AF34: Operational Risk Team | AG34: Altair/MOB Excel file sent by the Operations team | AJ34: Calibration provided by the SHUSA Operaterational Risk Team in coordination with the PR Ops Risk Team. Data is extracted from the Excel file New Group Metrics_ORM_020516 - Consolidated v6 on the sheet Gross Loss Gross Margin. | AK34: =1.781092/(261.891872409047+6.4759) -> 0.0066367581 | AR34: 0.02 | AS34: 0.025 | BR34: =+IFERROR(AVERAGE(AT34:BQ34),"") | BS34: =+IFERROR(VAR(AT34:BQ34),"") | BT34: =+IFERROR(STDEV(#REF!)*(1-$BS$1),"") | BU34: =+IF(OR(BT34="",OFFSET(#REF!,0,MATCH($B$1,AT$2:BQ$2,0)-1)=""),"",IFERROR(IF(ABS(OFFSET(#REF!,0,MATCH($B$1,AT$2:BQ$2,0)-1)-OFFSET(#REF!,0,MATCH($B$1,AT$2:BQ$2,0)-2))>BT34,"N","µ"),"")) -> #REF! | BV34: Under discussion between SHUSA and Local Operational Teams
C35: Total Number of Material Operational Risk Events | D35: 9 | E35: 16 | F35: OP Risk Team | H35: Y | L35: Y | P35: Y | T35: SIS Levels TBD | Z35: YES | AA35: Pending calibration confirmation from SHUSA Operational Team | AC35: Quarterly | AE35: The number of material operational risk events (as Defined by the SHUSA Operational Risk Event Escalation) . Methodology: No calculation necessary. Data extraction of Operational Risk Events Measures the ratio of gross operational risk losses to gross margin - Operational Risk Losses reported in the period (excluding recoveries – direct or indirect, excluding legal reserves and including legal settlements) Gross Margin (Net Revenue) is defined as: Net Interest Income + Fees + Other Fees + Security and Related Derivatives Gains – Security and Related Derivatives losses reported in the period | AF35: Operational Risk Team | AG35: Altair | AJ35: Zero tolerance to Operational Risk events | AR35: 0 | AS35: 0 | BR35: =+IFERROR(AVERAGE(AT35:BQ35),"") | BS35: =+IFERROR(VAR(AT35:BQ35),"") | BT35: =+IFERROR(STDEV(AT36:BQ36)*(1-$BS$1),"") -> 0.17593289 | BU35: =+IF(OR(BT35="",OFFSET(AT36,0,MATCH($B$1,AT$2:BQ$2,0)-1)=""),"",IFERROR(IF(ABS(OFFSET(AT36,0,MATCH($B$1,AT$2:BQ$2,0)-1)-OFFSET(AT36,0,MATCH($B$1,AT$2:BQ$2,0)-2))>BT35,"N","µ"),"")) -> N | BV35: Under discussion between SHUSA and Local MRM Teams | BW35: Changed from Frequency of material risk events >$200k in losses.
B36: Model | C36: Legacy Tier 1 Models in Production w/o Appropriate Approval | D36: N/A | E36: 4Q15-102 / 2Q16-90 / 4Q16-60 / 2Q17-30 / 4Q17-0 | F36: MRMG | H36: N | L36: Y | P36: Y | Z36: YES | AC36: Monthly | AE36: Currently there are 3 Tier I Models: 1) NMD (model id: 558 / use id: 521) 2) OFSA – Cash Flow (model id: 568 / use id: 531) 3) Anti Money Laundering (model id: 366 / use id: 364) 1) Model NMD (model id: 558 / use id: 521) approved on 2/26/2016. 2) OFSA – Cash Flow (model id: 568 / use id: 531) - Thsi model will be eliminated upon migration to QRM on 3Q16. Therefore model will not be validated nor approved. 3) Anti Money Laundering (model id: 366 / use id: 364) - Validation process should begin in July 2016 upon implementation of IHC. Due to the model's complexity, the validation / approval for this model is expected to take 60-90 days finishing on 4Q 2016. | AF36: Model Risk Managament | AG36: Metric is stored in EXCEL in a Local Network. | AJ36: Currently there are 3 Tier I Models: 1) NMD (model id: 558 / use id: 521) 2) OFSA – Cash Flow (model id: 568 / use id: 531) 3) Anti Money Laundering (model id: 366 / use id: 364) 1) Model NMD (model id: 558 / use id: 521) approved on 2/26/2016. 2) OFSA – Cash Flow (model id: 568 / use id: 531) - Thsi model will be eliminated upon migration to QRM on 3Q16. Therefore model will not be validated nor approved. 3) Anti Money Laundering (model id: 366 / use id: 364) - Validation process should begin in July 2016 upon implementation of IHC. Due to the model's complexity, the validation / approval for this model is expected to take 60-90 days finishing on 4Q 2016. | AQ36: N/A | AR36: N/A | AS36: 4Q15-3 / 1Q16-2 / 2Q16-2 / 3Q16-2 / 4Q16-0 | AT36: 3 | AU36: 3 | AV36: 3 | AW36: 3 | AX36: 3 | AY36: 3 | AZ36: 3 | BA36: 3 | BB36: 3 | BC36: 3 | BD36: 3 | BE36: 3 | BF36: 3 | BG36: 2 | BH36: 2 | BR36: =+IFERROR(AVERAGE(AT36:BQ36),"") -> 2.8666667 | BS36: =+IFERROR(VAR(AT36:BQ36),"") -> 0.12380952 | BT36: =+IFERROR(STDEV(AT37:BQ37)*(1-$BS$1),"") -> 0 | BU36: =+IF(OR(BT36="",OFFSET(AT37,0,MATCH($B$1,AT$2:BQ$2,0)-1)=""),"",IFERROR(IF(ABS(OFFSET(AT37,0,MATCH($B$1,AT$2:BQ$2,0)-1)-OFFSET(AT37,0,MATCH($B$1,AT$2:BQ$2,0)-2))>BT36,"N","µ"),"")) -> µ
B37: Compliance and Reputational | C37: Open MRIAs or equivalent regulatory matters requiring immediate attention (MRIA) | D37: N/A | E37: 0 | F37: Compliance | H37: N | L37: Y | P37: Y | T37: MRIAs / OCC, whatever is relevant for the entity | Z37: YES | AC37: Monthly | AE37: Considers only regulatory matters no Internal Audit recommendations. Includes MRIA's and MRA's | AF37: Internal Controls | AG37: Regulators -Recommendations Database | AJ37: As established in the BSPR Strategic Plan “Visión 360 (2016-2018)”, there will be 0 tolerance regarding Laws and Regulatory Compliance. Any indicator measuring compliance or related to a regulatory requirement, the Green level is established as 0 or 100% compliance. | AO37: 0 | AP37: 0 | AQ37: 0 | AR37: N/A | AS37: 0 | AT37: 0 | AU37: 0 | AV37: 0 | AW37: 0 | AX37: 0 | AY37: 0 | AZ37: 0 | BA37: 0 | BB37: 0 | BC37: 0 | BD37: 0 | BE37: 0 | BF37: 0 | BG37: 0 | BH37: 0 | BR37: =+IFERROR(AVERAGE(AT37:BQ37),"") -> 0 | BS37: =+IFERROR(VAR(AT37:BQ37),"") -> 0 | BT37: =+IFERROR(STDEV(#REF!)*(1-$BS$1),"") | BU37: =+IF(OR(BT37="",OFFSET(#REF!,0,MATCH($B$1,AT$2:BQ$2,0)-1)=""),"",IFERROR(IF(ABS(OFFSET(#REF!,0,MATCH($B$1,AT$2:BQ$2,0)-1)-OFFSET(#REF!,0,MATCH($B$1,AT$2:BQ$2,0)-2))>BT37,"N","µ"),"")) -> #REF!
C41: Corporate Metric

Sheet Bancorp RAS metrics
B1: 42401 | W1: ACTION PLAN OWNER | AC1: PR - BANCORP | BR1: Sensitivity | BS1: 0.5
C2: SHUSA RISK APPETITE METRICS | D2: 2015 TRIGGER LIMIT | E2: 2015 RED LIMIT | F2: SOURCE FOR 2016 RAS LIMIT SETTING | H2: SHUSA IN GROUP RAS | I2: 2016 TRIGGER LIMIT | J2: 2016 RED LIMIT | L2: SHUSA US RAS | M2: 2016 TRIGGER LIMIT | N2: 2016 RED LIMIT | P2: BSPR | Q2: 2016 TRIGGER LIMIT | R2: 2016 RED LIMIT | T2: COMMENTS | U2: GROUP DEFINITION | V2: ACTION PLAN | W2: LINE 1 | X2: LINE 2 | Y2: Bancorp Comments | Z2: Metric Applicability Confirmed with SHUSA | AA2: Calibration Comments | AC2: Frequency | AD2: Current RTS / RSC metric | AE2: SAN-PR Definition | AF2: SOURCE FOR 2016 RAS LIMIT SETTING | AG2: Source | AH2: Availability | AI2: Level | AJ2: Rationale for threshold definition | AK2: Budget | AL2: Reports Affected | AM2: Reports Consistency Validation | AN2: Differences: SHUSA RAS Glossary vs. BSPR Methodology | AO2: 2015 TRIGGER LIMIT | AP2: 2015 RED LIMIT | AQ2: 2016 GREEN | AR2: 2016 TRIGGER LIMIT | AS2: 2016 RED LIMIT | AT2: 42035 | AU2: 42063 | AV2: 42094 | AW2: 42124 | AX2: 42155 | AY2: 42185 | AZ2: 42216 | BA2: 42247 | BB2: 42277 | BC2: 42308 | BD2: 42338 | BE2: 42369 | BF2: 42400 | BG2: 42401 | BH2: 42430 | BI2: 42461 | BJ2: 42491 | BK2: 42522 | BL2: 42552 | BM2: 42583 | BN2: 42614 | BO2: 42644 | BP2: 42675 | BQ2: 42705 | BR2: Average | BS2: Variance | BT2: Standard Deviation | BU2: AVS | BV2: Local Comments - Cristina's Review | BW2: Comparación 4/8/16
B3: Capital | C3: Common Equity Tier 1 Ratio | D3: 0.11 | E3: 0.105 | F3: Capital Mgmt Group | H3: Y | L3: Y | P3: Y | T3: SIS will report its regulatory ratios. Pending receipt of list and levels | Z3: YES | AC3: Monthly | AD3: RTS SBC #0048 | AE3: A measurement of core equity capital compared with its total risk-weighted assets. The Tier 1 common capital ratio excludes any preferred shares or non-controlling interests when determining the calculation. | AF3: Leslie Adames (threshold calibration) Comptrollership / Hector Ramos (monthly data) | AG3: ALTAIR system | AH3: Available on day 10th of each month. | AI3: Capital Policy | AJ3: Capital Policy from November 27, 2015 which was approved by the Board on December 8, 2015. Information is located in page 7, Table 3: 2015 SBC/BSPR Capital Expectations. the Planned capital hold was considered for the Amber trigger and the Business-as-usual was considered for the Red limit. | AL3: ALCO Risk Scorecard Quarterly Capital Trends | AM3: ALCO: December 2015 and January 2016 OK Quarterly: March. June and September 2015 OK | AO3: 0.1208 | AP3: 0.106 | AR3: 0.1301 | AS3: 0.1101 | AT3: 0.25492001 | AU3: 0.25474324 | AV3: 0.26203649 | AW3: 0.26140044 | AX3: 0.25799632 | AY3: 0.25688005 | AZ3: 0.2579 | BA3: 0.26036566 | BB3: 0.27249536 | BC3: 0.2738473 | BD3: 0.27888295 | BE3: 0.27612173 | BF3: 0.28124164 | BG3: 0.28191391 | BH3: 0.28207302 | BR3: =+IFERROR(AVERAGE(AT3:BQ3),"") -> 0.26752121 | BS3: =+IFERROR(VAR(AT3:BQ3),"") -> 0.00011516537 | BT3: =+IFERROR(STDEV(AT3:BQ3)*(1-$BS$1),"") -> 0.0053657565 | BU3: =+IF(OR(BT3="",OFFSET(AT3,0,MATCH($B$1,AT$2:BQ$2,0)-1)=""),"",IFERROR(IF(ABS(OFFSET(AT3,0,MATCH($B$1,AT$2:BQ$2,0)-1)-OFFSET(AT3,0,MATCH($B$1,AT$2:BQ$2,0)-2))>BT3,"N","µ"),"")) -> µ
C4: Tier 1 Risk-based Capital Ratio | D4: 0.125 | E4: 0.12 | F4: Capital Mgmt Group | H4: Y | L4: Y | P4: Y | Z4: YES | AC4: Monthly | AD4: RTS SBC #0050 | AE4: Tier 1 capital divided by risk-weighted assets under baseline scenario. | AF4: Leslie Adames (threshold calibration) Comptrollership / Hector Ramos (monthly data) | AG4: ALTAIR system | AH4: Available on day 10th of each month. | AI4: Capital Policy | AJ4: Capital Policy from November 27, 2015 which was approved by the Board on December 8, 2015. Information is located in page 7, Table 3: 2015 SBC/BSPR Capital Expectations. the Planned capital hold was considered for the Amber trigger and the Business-as-usual was considered for the Red limit. | AL4: ALCO Risk Scorecard Quarterly Capital Trends | AM4: ALCO: December 2015 and January 2016 OK Quarterly: March. June and September 2015 OK | AO4: 0.152 | AP4: 0.1408 | AR4: 0.1582 | AS4: 0.1382 | AT4: 0.27363203 | AU4: 0.2734518 | AV4: 0.28120995 | AW4: 0.28048291 | AX4: 0.27679901 | AY4: 0.2755627 | AZ4: 0.2766961 | BA4: 0.27931027 | BB4: 0.29228716 | BC4: 0.29373166 | BD4: 0.29914098 | BE4: 0.29627738 | BF4: 0.28124164 | BG4: 0.28191391 | BH4: 0.28207302 | BR4: =+IFERROR(AVERAGE(AT4:BQ4),"") -> 0.2829207 | BS4: =+IFERROR(VAR(AT4:BQ4),"") -> 6.9918739e-05 | BT4: =+IFERROR(STDEV(AT4:BQ4)*(1-$BS$1),"") -> 0.0041808713 | BU4: =+IF(OR(BT4="",OFFSET(AT4,0,MATCH($B$1,AT$2:BQ$2,0)-1)=""),"",IFERROR(IF(ABS(OFFSET(AT4,0,MATCH($B$1,AT$2:BQ$2,0)-1)-OFFSET(AT4,0,MATCH($B$1,AT$2:BQ$2,0)-2))>BT4,"N","µ"),"")) -> µ
C5: Total Capital Ratio | D5: 0.145 | E5: 0.14 | F5: Capital Mgmt Group | H5: Y | L5: Y | P5: Y | T5: New from Group Dec-15 / Already in SHUSA RAS | U5: Tier I and Tier II capital based on BIS III regulations with phase in calendar | V5: Ensure alignment with Group definition | W5: Capital Team | X5: RAS Team | Z5: YES | AC5: Monthly | AD5: RTS SBC #0051 | AE5: Total risk-based capital is the sum of tier 1 plus tier 2 capital under baseline scenario. Tier 1 capital consists of common shareholders equity, perpetual preferred shareholders equity with non-cumulative dividends, retained earnings, and minority interests in the equity accounts of consolidated subsidiaries. Tier 2 capital consists of subordinated debt, intermediate-term preferred stock, cumulative and long-term preferred stock, and a portion of a banks’ allowance for loan and lease losses. | AF5: Leslie Adames (threshold calibration) Comptrollership / Hector Ramos (monthly data) | AG5: ALTAIR system | AH5: Available on day 10th of each month. | AI5: Capital Policy | AJ5: Capital Policy from November 27, 2015 which was approved by the Board on December 8, 2015. Information is located in page 7, Table 3: 2015 SBC/BSPR Capital Expectations. the Planned capital hold was considered for the Amber trigger and the Business-as-usual was considered for the Red limit. | AL5: Quarterly Capital Trends | AM5: March 24.9% Different, June and September 2015 OK | AO5: 0.171 | AP5: 0.1608 | AR5: 0.1783 | AS5: 0.1583 | AT5: 0.28621399 | AU5: 0.28603892 | AV5: 0.29380032 | AW5: 0.29307325 | AX5: 0.28939239 | AY5: 0.28815181 | AZ5: 0.28929199 | BA5: 0.29190972 | BB5: 0.30490211 | BC5: 0.30635689 | BD5: 0.31177243 | BE5: 0.30890289 | BF5: 0.2938706 | BG5: 0.29454605 | BH5: 0.29471424 | BR5: =+IFERROR(AVERAGE(AT5:BQ5),"") -> 0.29552917 | BS5: =+IFERROR(VAR(AT5:BQ5),"") -> 7.0151382e-05 | BT5: =+IFERROR(STDEV(AT5:BQ5)*(1-$BS$1),"") -> 0.0041878211 | BU5: =+IF(OR(BT5="",OFFSET(AT5,0,MATCH($B$1,AT$2:BQ$2,0)-1)=""),"",IFERROR(IF(ABS(OFFSET(AT5,0,MATCH($B$1,AT$2:BQ$2,0)-1)-OFFSET(AT5,0,MATCH($B$1,AT$2:BQ$2,0)-2))>BT5,"N","µ"),"")) -> µ
C6: Tier 1 Leverage Ratio | D6: 0.1025 | E6: 0.0975 | F6: Capital Mgmt Group | H6: Y | L6: Y | P6: Y | Z6: YES | AC6: Monthly | AD6: RTS SBC #0049 | AE6: The Tier 1 leverage ratio is calculated by dividing Tier 1 capital ratio by average total consolidated assets. | AF6: Leslie Adames (threshold calibration) Comptrollership / Hector Ramos (monthly data) | AG6: ALTAIR system | AH6: Available on day 10th of each month. | AI6: Capital Policy | AJ6: Capital Policy from November 27, 2015 which was approved by the Board on December 8, 2015. Information is located in page 7, Table 3: 2015 SBC/BSPR Capital Expectations. the Planned capital hold was considered for the Amber trigger and the Business-as-usual was considered for the Red limit. | AL6: ALCO Risk Scorecard Quarterly Capital Trends | AM6: ALCO: December 2015 and January 2016 OK Quarterly: March. June and September 2015 OK | AO6: 0.089 | AP6: 0.0812 | AR6: 0.108 | AS6: 0.088 | AT6: 0.19390501 | AU6: 0.19493905 | AV6: 0.19397339 | AW6: 0.19221897 | AX6: 0.19356803 | AY6: 0.19460351 | AZ6: 0.1958505 | BA6: 0.19561485 | BB6: 0.19617924 | BC6: 0.19803414 | BD6: 0.19815899 | BE6: 0.19774003 | BF6: 0.18673319 | BG6: 0.18662467 | BH6: 0.18638304 | BR6: =+IFERROR(AVERAGE(AT6:BQ6),"") -> 0.19363511 | BS6: =+IFERROR(VAR(AT6:BQ6),"") -> 1.6155555e-05 | BT6: =+IFERROR(STDEV(AT6:BQ6)*(1-$BS$1),"") -> 0.0020096987 | BU6: =+IF(OR(BT6="",OFFSET(AT6,0,MATCH($B$1,AT$2:BQ$2,0)-1)=""),"",IFERROR(IF(ABS(OFFSET(AT6,0,MATCH($B$1,AT$2:BQ$2,0)-1)-OFFSET(AT6,0,MATCH($B$1,AT$2:BQ$2,0)-2))>BT6,"N","µ"),"")) -> µ
C7: Impairment to Pre-Provision Net Revenue (PPNR) (9Q CCAR stressed) | Z7: YES | AC7: Annual | AE7: RAS Metrics Glossary: The projected 9Q cummulative increase in PPNR impairment between the CCAR BHC Stress and BHC Baseline scenarios and any available capital surplus under the CCAR BHC scenario. Material components include Total Revenue, Expenses due to Operational Risk and Expenses due to Residual Value Risk. | AF7: CCAR | AJ7: The methodology provided by SHUSA and Oliver Wyman is explained in the PDF file 20160426 CCAR-linked RAS methodology.pdf and the final calibration data is included in the PDF file 20160503 BSPR RAS Metrics.pdf. Please refer to slide 3. | AO7: CCAR | AP7: CCAR | AQ7: CCAR/OW | AR7: $296MM | AS7: $319MM | AT7: CCAR/OW | AU7: CCAR/OW | AV7: CCAR/OW | AW7: CCAR/OW | AX7: CCAR/OW | AY7: CCAR/OW | AZ7: CCAR/OW | BA7: CCAR/OW | BB7: CCAR/OW | BC7: CCAR/OW | BD7: CCAR/OW | BE7: CCAR/OW | BF7: CCAR/OW | BG7: CCAR/OW | BH7: CCAR/OW
C8: Common Equity Tier 1 Ratio - stressed | P8: Y | Z8: YES | AC8: Annual | AF8: CCAR | AI8: Capital Policy | AJ8: Methodology provided by SHUSA and Oliver Wyman is explained in the PDF file 20160426 CCAR-linked RAS methodology.pdf and the final calibration data is included in the PDF file 20160503 BSPR RAS Metrics.pdf. Please refer to slide 1. | AR8: 0.093 | AS8: 0.045 | AT8: CCAR/OW | AU8: CCAR/OW | AV8: CCAR/OW | AW8: CCAR/OW | AX8: CCAR/OW | AY8: CCAR/OW | AZ8: CCAR/OW | BA8: CCAR/OW | BB8: CCAR/OW | BC8: CCAR/OW | BD8: CCAR/OW | BE8: CCAR/OW | BF8: CCAR/OW | BG8: CCAR/OW | BH8: CCAR/OW | BR8: =+IFERROR(AVERAGE(AT8:BQ8),"") | BS8: =+IFERROR(VAR(AT8:BQ8),"") | BT8: =+IFERROR(STDEV(AT8:BQ8)*(1-$BS$1),"") | BU8: =+IF(OR(BT8="",OFFSET(AT8,0,MATCH($B$1,AT$2:BQ$2,0)-1)=""),"",IFERROR(IF(ABS(OFFSET(AT8,0,MATCH($B$1,AT$2:BQ$2,0)-1)-OFFSET(AT8,0,MATCH($B$1,AT$2:BQ$2,0)-2))>BT8,"N","µ"),""))
C9: Tier 1 Risk-based Capital Ratio - stressed | P9: Y | Z9: YES | AC9: Annual | AF9: CCAR | AI9: Capital Policy | AJ9: Methodology provided by SHUSA and Oliver Wyman is explained in the PDF file 20160426 CCAR-linked RAS methodology.pdf and the final calibration data is included in the PDF file 20160503 BSPR RAS Metrics.pdf. Please refer to slide 1. | AR9: 0.1075 | AS9: 0.06 | AT9: CCAR/OW | AU9: CCAR/OW | AV9: CCAR/OW | AW9: CCAR/OW | AX9: CCAR/OW | AY9: CCAR/OW | AZ9: CCAR/OW | BA9: CCAR/OW | BB9: CCAR/OW | BC9: CCAR/OW | BD9: CCAR/OW | BE9: CCAR/OW | BF9: CCAR/OW | BG9: CCAR/OW | BH9: CCAR/OW | BR9: =+IFERROR(AVERAGE(AT9:BQ9),"") | BS9: =+IFERROR(VAR(AT9:BQ9),"") | BT9: =+IFERROR(STDEV(AT9:BQ9)*(1-$BS$1),"") | BU9: =+IF(OR(BT9="",OFFSET(AT9,0,MATCH($B$1,AT$2:BQ$2,0)-1)=""),"",IFERROR(IF(ABS(OFFSET(AT9,0,MATCH($B$1,AT$2:BQ$2,0)-1)-OFFSET(AT9,0,MATCH($B$1,AT$2:BQ$2,0)-2))>BT9,"N","µ"),""))
C10: Total Capital Ratio - stressed | P10: Y | Z10: YES | AC10: Annual | AF10: CCAR | AI10: Capital Policy | AJ10: Methodology provided by SHUSA and Oliver Wyman is explained in the PDF file 20160426 CCAR-linked RAS methodology.pdf and the final calibration data is included in the PDF file 20160503 BSPR RAS Metrics.pdf. Please refer to slide 1. | AR10: 0.1215 | AS10: 0.08 | AT10: CCAR/OW | AU10: CCAR/OW | AV10: CCAR/OW | AW10: CCAR/OW | AX10: CCAR/OW | AY10: CCAR/OW | AZ10: CCAR/OW | BA10: CCAR/OW | BB10: CCAR/OW | BC10: CCAR/OW | BD10: CCAR/OW | BE10: CCAR/OW | BF10: CCAR/OW | BG10: CCAR/OW | BH10: CCAR/OW | BR10: =+IFERROR(AVERAGE(AT10:BQ10),"") | BS10: =+IFERROR(VAR(AT10:BQ10),"") | BT10: =+IFERROR(STDEV(AT10:BQ10)*(1-$BS$1),"") | BU10: =+IF(OR(BT10="",OFFSET(AT10,0,MATCH($B$1,AT$2:BQ$2,0)-1)=""),"",IFERROR(IF(ABS(OFFSET(AT10,0,MATCH($B$1,AT$2:BQ$2,0)-1)-OFFSET(AT10,0,MATCH($B$1,AT$2:BQ$2,0)-2))>BT10,"N","µ"),""))
C11: Tier 1 Leverage Ratio - stressed | P11: Y | Z11: YES | AC11: Annual | AF11: CCAR | AI11: Capital Policy | AJ11: Methodology provided by SHUSA and Oliver Wyman is explained in the PDF file 20160426 CCAR-linked RAS methodology.pdf and the final calibration data is included in the PDF file 20160503 BSPR RAS Metrics.pdf. Please refer to slide 1. | AR11: 0.068 | AS11: 0.04 | AT11: CCAR/OW | AU11: CCAR/OW | AV11: CCAR/OW | AW11: CCAR/OW | AX11: CCAR/OW | AY11: CCAR/OW | AZ11: CCAR/OW | BA11: CCAR/OW | BB11: CCAR/OW | BC11: CCAR/OW | BD11: CCAR/OW | BE11: CCAR/OW | BF11: CCAR/OW | BG11: CCAR/OW | BH11: CCAR/OW | BR11: =+IFERROR(AVERAGE(AT11:BQ11),"") | BS11: =+IFERROR(VAR(AT11:BQ11),"") | BT11: =+IFERROR(STDEV(AT11:BQ11)*(1-$BS$1),"") | BU11: =+IF(OR(BT11="",OFFSET(AT11,0,MATCH($B$1,AT$2:BQ$2,0)-1)=""),"",IFERROR(IF(ABS(OFFSET(AT11,0,MATCH($B$1,AT$2:BQ$2,0)-1)-OFFSET(AT11,0,MATCH($B$1,AT$2:BQ$2,0)-2))>BT11,"N","µ"),""))
B12: Credit Risk | C12: Total Credit Losses (9Q stressed CCAR losses) | D12: CCAR | E12: CCAR | F12: CCAR | H12: Y | L12: Y | P12: Y | T12: Included in Loss in Stress calculation | Z12: YES | AC12: Annual | AE12: RAS Metrics Glossary: 9Q stressed cummulativw credit losses and any available capital surplus under the CCAR BHC Stress scenario allocated by material portfolio | AF12: CCAR (threshold calibration) | AJ12: The methodology provided by SHUSA and Oliver Wyman is explained in the PDF file 20160426 CCAR-linked RAS methodology.pdf and the final calibration data is included in the PDF file 20160503 BSPR RAS Metrics.pdf. Please refer to slide 3. | AO12: CCAR | AP12: CCAR | AQ12: CCAR/OW | AR12: $315MM | AS12: $340MM | AT12: CCAR/OW | AU12: CCAR/OW | AV12: CCAR/OW | AW12: CCAR/OW | AX12: CCAR/OW | AY12: CCAR/OW | AZ12: CCAR/OW | BA12: CCAR/OW | BB12: CCAR/OW | BC12: CCAR/OW | BD12: CCAR/OW | BE12: CCAR/OW | BF12: CCAR/OW | BG12: CCAR/OW | BH12: CCAR/OW | BR12: =+IFERROR(AVERAGE(AT12:BQ12),"") | BS12: =+IFERROR(VAR(AT12:BQ12),"") | BT12: =+IFERROR(STDEV(AT12:BQ12)*(1-$BS$1),"") | BU12: =+IF(OR(BT12="",OFFSET(AT12,0,MATCH($B$1,AT$2:BQ$2,0)-1)=""),"",IFERROR(IF(ABS(OFFSET(AT12,0,MATCH($B$1,AT$2:BQ$2,0)-1)-OFFSET(AT12,0,MATCH($B$1,AT$2:BQ$2,0)-2))>BT12,"N","µ"),""))
C13: NCO PR Mortgages | D13: New 2016 | E13: New 2016 | F13: CCAR | H13: N | L13: Y | P13: Y | Y13: -Please confirm if the Material Portfolios are to be divided between Total Outstanding Portfolio or Total Outstanding of the Material Portfolios. [SA]: Total outstanding of the material portfolios -Are we supposed to use the methodology that SBNA uses included in the RAS Metrics Glossary? (Most recent month's total NCO multiplied by 12 and divided by the Total outstanding balances) [SA]: No - changing to rolling 12-month NCO/rolling 12-month outstanding balance BSPR - shouldn't the denominator of the metric be the average of the rolling 12-month outstanding balance (such as SCUSA) -In order to calculate the annualized amount should we multiply the Most recent month's NCO by 12 or by (number of month/12)? [SA]: As above -In order to be aligned with the Local Credit Trends Report which considers 12 month NCO divided by Average Portfolio, could we consider the local monitoring metric for the RAS? [SA]: As above - we are discussing with Oliver Wyman the possibility of adding change in provisions over 12-mo to the metric 4/22/2016 Pendiente información de KPI Total 12 Average Portfolio para completar la información histórica. | Z13: YES | AC13: Monthly | AE13: NUMERATOR: 12M NCO - Mortgage Portfolio divided by DENOMINATOR: KPI Total 12 Average Portfolio - Mortgage Portfolio | AF13: CCAR (threshold calibration) Risk MI / Rafael Martínez (monthly data) | AG13: CARMOSA PRODUCTO 1 = HIPOTECAS | AH13: day 10th of each month depending on Accounting reconciliation | AJ13: The methodology provided by SHUSA and Oliver Wyman is explained in the PDF file 20160426 CCAR-linked RAS methodology.pdf and the final calibration data is included in the PDF file 20160503 BSPR RAS Metrics.pdf. Please refer to slide 2. | AK13: =20060117.7740878/1278275057.73207 -> 0.015693115 | AL13: Report: Credit Trends as reported by Portfolio Management | AM13: 2015 Q1: 1.5% OK Q2: 1.5% Q3: 1.7% | AQ13: OW | AR13: 0.017 | AS13: 0.019 | AT13: =21001300.1/1458562170.45083 -> 0.014398632 | AU13: =21353526.28/1453095106.3375 -> 0.014695202 | AV13: =20655365.18/1447822382.40583 -> 0.014266505 | AW13: =19656496.58/1442278059.75417 -> 0.013628784 | AX13: =19571143.83/1436216140.8325 -> 0.013626879 | AY13: =20402700.95/1429643604.5925 -> 0.01427118 | AZ13: =21304105.16/1423587766.20667 -> 0.01496508 | BA13: =20565865.8/1416677120.80917 -> 0.014516975 | BB13: =20836772.33/1409519546.70917 -> 0.01478289 | BC13: =21365311.1/1402023201.61333 -> 0.015238914 | BD13: =21748987.87/1394176527.56417 -> 0.015599881 | BE13: =22556113.5/1386576381.79333 -> 0.016267487 | BF13: =22438996.53/1379092174.40333 -> 0.016270846 | BG13: =22258933.34/1371357488.51667 -> 0.016231314 | BH13: =22364873.26/1362968240.25833 -> 0.016408947 | BR13: =+IFERROR(AVERAGE(AT13:BQ13),"") -> 0.015011301 | BS13: =+IFERROR(VAR(AT13:BQ13),"") -> 9.0778291e-07 | BT13: =+IFERROR(STDEV(AT13:BQ13)*(1-$BS$1),"") -> 0.00047638821 | BU13: =+IF(OR(BT13="",OFFSET(AT13,0,MATCH($B$1,AT$2:BQ$2,0)-1)=""),"",IFERROR(IF(ABS(OFFSET(AT13,0,MATCH($B$1,AT$2:BQ$2,0)-1)-OFFSET(AT13,0,MATCH($B$1,AT$2:BQ$2,0)-2))>BT13,"N","µ"),"")) -> µ | BV13: Ask Paola if in the Credit Trends Portfolio management (12-mo Net Ch Offs/AVG Portfolio) the methodology considers Exposure or Outstanding. And is this the result of the last month or an avrage of the Quarter. Here we use outstanding.
C14: NCO PR Commercial Banking | D14: New 2016 | E14: New 2016 | F14: CCAR | H14: N | L14: Y | P14: Y | Z14: YES | AC14: Monthly | AE14: NUMERATOR: 12M NCO - Commercial Portfolio (includes: COMMERCIAL, CONSTRUCTION, OVERDRAFTS, RCS COMMERCIAL) divided by DENOMINATOR: KPI Total 12 Average Portfolio - Commercial Portfolio (includes: COMMERCIAL, CONSTRUCTION, OVERDRAFTS, RCS COMMERCIAL) | AF14: CCAR (threshold calibration) Risk MI / Rafael Martínez (monthly data) | AG14: CARMOSA: PRODUCTO 1 = COMMERCIAL + CONSTRUCTION | AH14: day 10th of each month depending on Accounting reconciliation | AJ14: The methodology provided by SHUSA and Oliver Wyman is explained in the PDF file 20160426 CCAR-linked RAS methodology.pdf and the final calibration data is included in the PDF file 20160503 BSPR RAS Metrics.pdf. Please refer to slide 2. | AK14: =9841038.63514543/1826186084.21375 -> 0.0053888477 | AL14: Report: Credit Trends as reported by Portfolio Management | AM14: ? | AQ14: OW | AR14: 0.005 | AS14: 0.006 | AT14: =5192599.46/2846044996.57083 -> 0.0018244966 | AU14: =5439071.96/2764554958.61083 -> 0.0019674313 | AV14: =4684676.98/2689804141.36917 -> 0.0017416424 | AW14: =4907338.01/2625953584.28667 -> 0.0018687832 | AX14: =4674975.06/2582158105.69583 -> 0.0018104914 | AY14: =5512214.9/2550936900.76417 -> 0.002160859 | AZ14: =5612158.96/2517666533.7 -> 0.0022291113 | BA14: =6126246.17/2487822750.26917 -> 0.002462493 | BB14: =5290289.24/2448634870.89917 -> 0.0021605056 | BC14: =5514186.35/2411773404.39 -> 0.0022863617 | BD14: =6765650.66/2378558269.705 -> 0.0028444334 | BE14: =5699008.93/2358337502.21083 -> 0.0024165366 | BF14: =5988769.71/2344983292.485 -> 0.0025538646 | BG14: =6935964.59/2330533830.445 -> 0.002976127 | BH14: =7429278.09/2316835030.11 -> 0.0032066496 | BR14: =+IFERROR(AVERAGE(AT14:BQ14),"") -> 0.0023006524 | BS14: =+IFERROR(VAR(AT14:BQ14),"") -> 1.9986142e-07 | BT14: =+IFERROR(STDEV(AT14:BQ14)*(1-$BS$1),"") -> 0.00022352931 | BU14: =+IF(OR(BT14="",OFFSET(AT14,0,MATCH($B$1,AT$2:BQ$2,0)-1)=""),"",IFERROR(IF(ABS(OFFSET(AT14,0,MATCH($B$1,AT$2:BQ$2,0)-1)-OFFSET(AT14,0,MATCH($B$1,AT$2:BQ$2,0)-2))>BT14,"N","µ"),"")) -> N | BV14: Ask Paola what is the equivalent metric reported in the Credit Trands report for this.
C15: NCO PR Personal Loans | D15: New 2016 | E15: New 2016 | F15: CCAR | H15: N | L15: Y | P15: Y | Z15: YES | AC15: Monthly | AE15: NUMERATOR: 12M NCO - Personal Loans Portfolio divided by DENOMINATOR: KPI Total 12 Average Portfolio - Personal Loans Portfolio | AF15: CCAR (threshold calibration) Risk MI / Rafael Martínez (monthly data) | AG15: CARMOSA PRODUCTO 1 = CONSUMO | AH15: day 10th of each month depending on Accounting reconciliation | AJ15: The methodology provided by SHUSA and Oliver Wyman is explained in the PDF file 20160426 CCAR-linked RAS methodology.pdf and the final calibration data is included in the PDF file 20160503 BSPR RAS Metrics.pdf. Please refer to slide 2. | AK15: =12885320.0264068/243323603.487228 -> 0.052955487 | AL15: Report: Credit Trends as reported by Portfolio Management | AM15: 2015 Q1: 5.0% Q2: 5.1% Q3: 5.1% | AQ15: OW | AR15: 0.054 | AS15: 0.06 | AT15: =11900742.26/267263911.540833 -> 0.044528055 | AU15: =12011720.34/267487328.2075 -> 0.044905755 | AV15: =12276309.94/267731166.666667 -> 0.045853122 | AW15: =12451267.6/267956333.333333 -> 0.046467525 | AX15: =12578459.62/268305083.333333 -> 0.046881183 | AY15: =12310548.87/268616750.949167 -> 0.045829416 | AZ15: =12178575.37/268901000.949167 -> 0.045290182 | BA15: =12114629.17/268876500.949167 -> 0.045056482 | BB15: =11983748.41/268800917.615833 -> 0.044582245 | BC15: =11844779.7/268531750.949167 -> 0.04410942 | BD15: =11829246.07/268045917.615833 -> 0.044131417 | BE15: =12110431.5/267291799.794167 -> 0.045307905 | BF15: =11860979.58/266336299.794167 -> 0.044533845 | BG15: =11903712.79/265031049.794167 -> 0.044914408 | BH15: =11834996.41/263558883.1275 -> 0.044904563 | BR15: =+IFERROR(AVERAGE(AT15:BQ15),"") -> 0.045153035 | BS15: =+IFERROR(VAR(AT15:BQ15),"") -> 6.518979e-07 | BT15: =+IFERROR(STDEV(AT15:BQ15)*(1-$BS$1),"") -> 0.00040370097 | BU15: =+IF(OR(BT15="",OFFSET(AT15,0,MATCH($B$1,AT$2:BQ$2,0)-1)=""),"",IFERROR(IF(ABS(OFFSET(AT15,0,MATCH($B$1,AT$2:BQ$2,0)-1)-OFFSET(AT15,0,MATCH($B$1,AT$2:BQ$2,0)-2))>BT15,"N","µ"),"")) -> µ | BV15: Ask Paola if Net Write Off 12m (%) from the Credit Trends report is the equivalent. If so, what is the methodology? Esposure or Outstanding? Can we compare against this metric?
C16: NCO PR Credit Cards | D16: New 2016 | E16: New 2016 | F16: CCAR | H16: N | L16: Y | P16: Y | Z16: YES | AC16: Monthly | AE16: NUMERATOR: 12M NCO - Credit Cards Portfolio divided by DENOMINATOR: KPI Total 12 Average Portfolio - Credit Cards Portfolio | AF16: CCAR (threshold calibration) Risk MI / Rafael Martínez (monthly data) | AG16: CARMOSA PRODUCTO 1 = TARJETAS | AH16: day 10th of each month depending on Accounting reconciliation | AJ16: The methodology provided by SHUSA and Oliver Wyman is explained in the PDF file 20160426 CCAR-linked RAS methodology.pdf and the final calibration data is included in the PDF file 20160503 BSPR RAS Metrics.pdf. Please refer to slide 2. | AK16: =15036935.4473544/238217331.128349 -> 0.06312276 | AL16: Report: Credit Trends as reported by Portfolio Management | AM16: 2015 Q1: 6.8% Q2: 6.8% Q3: 6.8% | AQ16: OW | AR16: 0.064 | AS16: 0.074 | AT16: =14750662.42/236314072.244167 -> 0.062419738 | AU16: =14710669.36/237209988.910833 -> 0.062015387 | AV16: =14881019.21/237847655.5775 -> 0.062565339 | AW16: =15070394.47/238436572.244167 -> 0.063205046 | AX16: =15373030.78/238889405.5775 -> 0.064352083 | AY16: =15201929.06/239183518.864167 -> 0.063557594 | AZ16: =15193929.08/239299685.530833 -> 0.06349331 | BA16: =14831436.24/239444435.530833 -> 0.061941035 | BB16: =15127496.74/239363509.728333 -> 0.063198842 | BC16: =14987897.0205/239135343.061667 -> 0.062675374 | BD16: =14795608.4407/238787926.395 -> 0.061961292 | BE16: =15175513.0107/238161839.78 -> 0.063719331 | BF16: =15236139.3807/237438006.446667 -> 0.064168916 | BG16: =15022513.4007/236594673.113333 -> 0.063494724 | BH16: =14667857.8107/235718756.446667 -> 0.062226095 | BR16: =+IFERROR(AVERAGE(AT16:BQ16),"") -> 0.062999607 | BS16: =+IFERROR(VAR(AT16:BQ16),"") -> 6.4230374e-07 | BT16: =+IFERROR(STDEV(AT16:BQ16)*(1-$BS$1),"") -> 0.00040071927 | BU16: =+IF(OR(BT16="",OFFSET(AT16,0,MATCH($B$1,AT$2:BQ$2,0)-1)=""),"",IFERROR(IF(ABS(OFFSET(AT16,0,MATCH($B$1,AT$2:BQ$2,0)-1)-OFFSET(AT16,0,MATCH($B$1,AT$2:BQ$2,0)-2))>BT16,"N","µ"),"")) -> N | BV16: Ask Paola if Net Write Off 12m (%) from the Credit Trends report is the equivalent. If so, what is the methodology? Esposure or Outstanding? Can we compare against this metric?
C17: NCO PR TOTAL | P17: Y | Z17: YES | AC17: Monthly | AD17: RSC BSPR #0089 | AE17: It is calculated as twelve month rolling Net Charge Offs (NCO) (i.e., charge off’s less recoveries, excluding the sale of charge off portfolio) divided by average loans portfolio. NCO are the total loans and leases removed from the balance sheet due to their uncollectability minus amounts recovered on loans and leases previously charged-off. NUMERATOR: 12M NCO PR Total divided by DENOMINATOR: KPI Total 12 Average Portfolio - Total | AF17: CCAR (threshold calibration) Risk MI / Rafael Martínez (monthly data) | AG17: Database 1001 | AH17: day 5th of each month | AI17: Budget | AJ17: The methodology provided by SHUSA and Oliver Wyman is explained in the PDF file 20160426 CCAR-linked RAS methodology.pdf and the final calibration data is included in the PDF file 20160503 BSPR RAS Metrics.pdf. Please refer to slide 2. | AK17: 0.016 | AO17: 0.014 | AP17: 0.016 | AQ17: OW | AR17: 0.017 | AS17: 0.018 | AT17: =52845304.24/4808185150.80667 -> 0.010990697 | AU17: =53514987.94/4722347382.06667 -> 0.011332285 | AV17: =52497371.31/4643205346.01917 -> 0.011306278 | AW17: =52085496.66/4574624549.61833 -> 0.011385742 | AX17: =52197609.29/4525568735.43917 -> 0.011533934 | AY17: =53427393.78/4488380775.17 -> 0.01190349 | AZ17: =54288768.57/4449454986.38667 -> 0.012201218 | BA17: =53638177.38/4412820807.55833 -> 0.012155077 | BB17: =53238306.72/4366318844.9525 -> 0.01219295 | BC17: =53712174.1705/4321463700.01417 -> 0.012429162 | BD17: =55139493.0407/4279568641.28 -> 0.012884358 | BE17: =55541066.9407/4250367523.57833 -> 0.013067356 | BF17: =55524885.2007/4227849773.12917 -> 0.013133126 | BG17: =56121124.1207/4203517041.86917 -> 0.013350992 | BH17: =56297005.5707/4179080909.9425 -> 0.013471145 | BR17: =+IFERROR(AVERAGE(AT17:BQ17),"") -> 0.012222521 | BS17: =+IFERROR(VAR(AT17:BQ17),"") -> 6.6340058e-07 | BT17: =+IFERROR(STDEV(AT17:BQ17)*(1-$BS$1),"") -> 0.00040724703 | BU17: =+IF(OR(BT17="",OFFSET(AT17,0,MATCH($B$1,AT$2:BQ$2,0)-1)=""),"",IFERROR(IF(ABS(OFFSET(AT17,0,MATCH($B$1,AT$2:BQ$2,0)-1)-OFFSET(AT17,0,MATCH($B$1,AT$2:BQ$2,0)-2))>BT17,"N","µ"),"")) -> µ | BV17: Cristina - revisar presupuesto e incluir en columna 'Budget' y resultado de Enero/2016 debe dar igual que RTS. Los niveles deben dar igual a lo presentado por Blanca en el BSPR RSC Review
C18: 60+ PR Mortgages | D18: New 2016 | E18: New 2016 | F18: CCAR | H18: N | L18: Y | P18: Y | Y18: Please confirm if the Material Portfolios are to be divided between Total Outstanding Portfolio or Total Outstanding of the Material Portfolios. [SA]: Outstanding of material portfolios 4/22/2016 Pendiente información de 60+ para carteras de bancorp y Total outtstanding balance para completar la información histórica. | Z18: YES | AC18: Monthly | AE18: NUMERATOR: 60+ days past due Mortgage Portfolio divided by DENOMINATOR: Total Outstanding Balance of Mortgage Portfolio | AF18: CCAR (threshold calibration) Risk MI / Rafael Martínez (monthly data) | AG18: TABLA 1001 = QUERY 0700 | AH18: day 10th of each month depending on Accounting reconciliation | AJ18: The methodology provided by SHUSA and Oliver Wyman is explained in the PDF file 20160426 CCAR-linked RAS methodology.pdf and the final calibration data is included in the PDF file 20160503 BSPR RAS Metrics.pdf. Please refer to slide 4. | AK18: =126.249963851156/1297.64620955215 -> 0.097291514 | AQ18: OW | AR18: 0.106 | AS18: 0.12 | AT18: =135528625.18/1425653488.68 -> 0.095064212 | AU18: =132504856.2/1418464230.64 -> 0.093414309 | AV18: =132409704.94/1419735773.83 -> 0.093263625 | AW18: =134792740.47/1413157453 -> 0.095384092 | AX18: =133821996.92/1400898510.29 -> 0.095525833 | AY18: =132546435.15/1389975612.59 -> 0.095358821 | AZ18: =135227944.09/1390882444.19 -> 0.097224568 | BA18: =132998905.85/1372450098.04 -> 0.096906187 | BB18: =129996579.14/1363384266.34 -> 0.095348452 | BC18: =128809994.53/1355941168.45 -> 0.094996743 | BD18: =132068871.11/1346281050.71 -> 0.098099034 | BE18: =127596797.49/1342092484.76 -> 0.095073029 | BF18: =127308962.19/1335843000 -> 0.095302339 | BG18: =123254702.18/1325648000 -> 0.092976946 | BH18: =110803287.35/1319064794.73 -> 0.084001398 | BR18: =+IFERROR(AVERAGE(AT18:BQ18),"") -> 0.094529306 | BS18: =+IFERROR(VAR(AT18:BQ18),"") -> 1.044496e-05 | BT18: =+IFERROR(STDEV(AT18:BQ18)*(1-$BS$1),"") -> 0.0016159332 | BU18: =+IF(OR(BT18="",OFFSET(AT18,0,MATCH($B$1,AT$2:BQ$2,0)-1)=""),"",IFERROR(IF(ABS(OFFSET(AT18,0,MATCH($B$1,AT$2:BQ$2,0)-1)-OFFSET(AT18,0,MATCH($B$1,AT$2:BQ$2,0)-2))>BT18,"N","µ"),"")) -> N | BV18: OK Confirmed 3/10/2016
C19: 60+ PR Personal Loans | D19: New 2016 | E19: New 2016 | F19: CCAR | H19: N | L19: Y | P19: Y | Z19: YES | AC19: Monthly | AE19: NUMERATOR: 60+ days past due Personal Loans Portfolio divided by DENOMINATOR: Total Outstanding Balance of Personal Loans Portfolio | AF19: CCAR (threshold calibration) Risk MI / Rafael Martínez (monthly data) | AG19: TABLA 1001 = QUERY 0700 | AH19: day 10th of each month depending on Accounting reconciliation | AJ19: The methodology provided by SHUSA and Oliver Wyman is explained in the PDF file 20160426 CCAR-linked RAS methodology.pdf and the final calibration data is included in the PDF file 20160503 BSPR RAS Metrics.pdf. Please refer to slide 4. | AK19: =2.92728882971842/243.309059327228 -> 0.012031154 | AQ19: OW | AR19: 0.015 | AS19: 0.017 | AT19: =3281975.77/267760000 -> 0.012257155 | AU19: =3368994.58/268881000 -> 0.012529686 | AV19: =3184008.85/268031000 -> 0.011879256 | AW19: =3106624.74/269291000 -> 0.011536311 | AX19: =3069150.7/270174000 -> 0.011359904 | AY19: =3106639.83/270540011.39 -> 0.011483107 | AZ19: =3367879.94/269777000 -> 0.01248394 | BA19: =3694288.27/268404000 -> 0.013763909 | BB19: =3185553.77/267138000 -> 0.01192475 | BC19: =3088628.47/265938000 -> 0.011614092 | BD19: =3248285.83/262427000 -> 0.012377864 | BE19: =3433970.14/259140586.14 -> 0.013251379 | BF19: =3569446.67/256294000 -> 0.013927157 | BG19: =3735624.25/253218000 -> 0.014752602 | BH19: =3739986.58/250365000 -> 0.014938137 | BR19: =+IFERROR(AVERAGE(AT19:BQ19),"") -> 0.01267195 | BS19: =+IFERROR(VAR(AT19:BQ19),"") -> 1.4009086e-06 | BT19: =+IFERROR(STDEV(AT19:BQ19)*(1-$BS$1),"") -> 0.00059179993 | BU19: =+IF(OR(BT19="",OFFSET(AT19,0,MATCH($B$1,AT$2:BQ$2,0)-1)=""),"",IFERROR(IF(ABS(OFFSET(AT19,0,MATCH($B$1,AT$2:BQ$2,0)-1)-OFFSET(AT19,0,MATCH($B$1,AT$2:BQ$2,0)-2))>BT19,"N","µ"),"")) -> N | BV19: OK Confirmed 3/10/2016
C20: 60+ PR Credit Cards | D20: New 2016 | E20: New 2016 | F20: CCAR | H20: N | L20: Y | P20: Y | Z20: YES | AC20: Monthly | AE20: NUMERATOR: 60+ days past due Credit Cards Portfolio divided by DENOMINATOR: Total Outstanding Balance of Credit Cards Portfolio | AF20: CCAR (threshold calibration) Risk MI / Rafael Martínez (monthly data) | AG20: TABLA 1001 = QUERY 0700 | AH20: day 10th of each month depending on Accounting reconciliation | AJ20: The methodology provided by SHUSA and Oliver Wyman is explained in the PDF file 20160426 CCAR-linked RAS methodology.pdf and the final calibration data is included in the PDF file 20160503 BSPR RAS Metrics.pdf. Please refer to slide 4. | AK20: =11.9094024173571/237.970414168349 -> 0.050045727 | AQ20: OW | AR20: 0.023 | AS20: 0.026 | AT20: =6124188.16/241348000 -> 0.025374928 | AU20: =6154544.16/240428000 -> 0.025598284 | AV20: =5586644.79/237669000 -> 0.023505989 | AW20: =5088717.14/239372000 -> 0.021258615 | AX20: =5063346.41/239138000 -> 0.021173324 | AY20: =4864548.23/239704359.44 -> 0.02029395 | AZ20: =4915238.59/238959000 -> 0.02056938 | BA20: =5214333.41/239065000 -> 0.021811363 | BB20: =5031679.62/237211757.3 -> 0.021211763 | BC20: =5120391.01/235516000 -> 0.02174116 | BD20: =5442722.97/236229000 -> 0.023040029 | BE20: =5358917.61/233301960.62 -> 0.022969878 | BF20: =5495221.35/232662000 -> 0.023618904 | BG20: =5572586.62/230308000 -> 0.024196236 | BH20: =5380531.07/227158000 -> 0.023686294 | BR20: =+IFERROR(AVERAGE(AT20:BQ20),"") -> 0.022670006 | BS20: =+IFERROR(VAR(AT20:BQ20),"") -> 2.7926138e-06 | BT20: =+IFERROR(STDEV(AT20:BQ20)*(1-$BS$1),"") -> 0.00083555577 | BU20: =+IF(OR(BT20="",OFFSET(AT20,0,MATCH($B$1,AT$2:BQ$2,0)-1)=""),"",IFERROR(IF(ABS(OFFSET(AT20,0,MATCH($B$1,AT$2:BQ$2,0)-1)-OFFSET(AT20,0,MATCH($B$1,AT$2:BQ$2,0)-2))>BT20,"N","µ"),"")) -> µ | BV20: OK Confirmed 3/10/2016
C21: 60+ PR Commercial Banking | P21: Y | Z21: YES | AC21: Monthly | AE21: NUMERATOR: 60+ days past due Commercial Portfolio divided by DENOMINATOR: Total Outstanding Balance of Commercial Portfolio | AF21: CCAR (threshold calibration) Risk MI / Rafael Martínez (monthly data) | AG21: TABLA 1001 = QUERY 0700 | AH21: day 10th of each month depending on Accounting reconciliation | AJ21: The methodology provided by SHUSA and Oliver Wyman is explained in the PDF file 20160426 CCAR-linked RAS methodology.pdf and the final calibration data is included in the PDF file 20160503 BSPR RAS Metrics.pdf. Please refer to slide 4. | AQ21: OW | AR21: 0.042 | AS21: 0.05 | AT21: =38054535.65/2383182516.71 -> 0.015967948 | AU21: =36338797.18/2367045544.48 -> 0.015351964 | AV21: =34670646.47/2372077073.17 -> 0.014616155 | AW21: =34766026.29/2385131202.73 -> 0.014576148 | AX21: =34357712.53/2442673377.98 -> 0.014065619 | AY21: =33551187.93/2480434050.21 -> 0.013526337 | AZ21: =51090472.45/2458006793.4 -> 0.020785326 | BA21: =42035363.2/2427541712.44 -> 0.017316021 | BB21: =45809367.39/2272674898.89 -> 0.020156586 | BC21: =42045568.68/2252395762.52 -> 0.018667043 | BD21: =51483463.03/2214467185.8 -> 0.023248691 | BE21: =45016281.34/2244419908.2 -> 0.020056978 | BF21: =42846996.51/2222932000 -> 0.019274992 | BG21: =43308674.27/2193652000 -> 0.019742728 | BH21: =43802749.65/2207691469.15 -> 0.019840974 | BR21: =+IFERROR(AVERAGE(AT21:BQ21),"") -> 0.017812901 | BS21: =+IFERROR(VAR(AT21:BQ21),"") -> 8.7454215e-06 | BT21: =+IFERROR(STDEV(AT21:BQ21)*(1-$BS$1),"") -> 0.0014786329 | BU21: =+IF(OR(BT21="",OFFSET(AT21,0,MATCH($B$1,AT$2:BQ$2,0)-1)=""),"",IFERROR(IF(ABS(OFFSET(AT21,0,MATCH($B$1,AT$2:BQ$2,0)-1)-OFFSET(AT21,0,MATCH($B$1,AT$2:BQ$2,0)-2))>BT21,"N","µ"),"")) -> µ | BV21: OK Confirmed 3/10/2016
C22: 60+ PR TOTAL | P22: Y | Z22: YES | AE22: NUMERATOR: 60+ Total Portfolio divided by DENOMINATOR: Total Portfolio % | AF22: CCAR (threshold calibration) Risk MI / Rafael Martínez (monthly data) | AG22: TABLA 1001 = QUERY 0700 | AH22: day 10th of each month depending on Accounting reconciliation | AJ22: The methodology provided by SHUSA and Oliver Wyman is explained in the PDF file 20160426 CCAR-linked RAS methodology.pdf and the final calibration data is included in the PDF file 20160503 BSPR RAS Metrics.pdf. Please refer to slide 4. | AQ22: OW | AR22: 0.061 | AS22: 0.07 | AT22: =182989324.76/4317944005.39 -> 0.042378809 | AU22: =178367192.12/4317944005.39 -> 0.041308362 | AV22: =175851005.05/4297512847 -> 0.040919251 | AW22: =177754108.64/4306951655.73 -> 0.041271443 | AX22: =176312206.56/4352883888.27 -> 0.040504689 | AY22: =174068811.14/4380654033.63 -> 0.039735804 | AZ22: =194601535.07/4357625237.59 -> 0.044657703 | BA22: =183942890.73/4307460810.48 -> 0.042703323 | BB22: =184023179.92/4140408922.53 -> 0.044445653 | BC22: =179064582.69/4109790930.97 -> 0.043570241 | BD22: =192243342.94/4059404236.51 -> 0.047357526 | BE22: =181405966.58/4078954939.72 -> 0.044473638 | BF22: =179220626.72/4047731000 -> 0.044276813 | BG22: =175871587.32/4002826000 -> 0.043936855 | BH22: =163726554.65/4004279263.88 -> 0.040887896 | BR22: =+IFERROR(AVERAGE(AT22:BQ22),"") -> 0.042828534 | BS22: =+IFERROR(VAR(AT22:BQ22),"") -> 4.3132252e-06 | BT22: =+IFERROR(STDEV(AT22:BQ22)*(1-$BS$1),"") -> 0.0010384153 | BU22: =+IF(OR(BT22="",OFFSET(AT22,0,MATCH($B$1,AR$2:BO$2,0)-1)=""),"",IFERROR(IF(ABS(OFFSET(AT22,0,MATCH($B$1,AR$2:BO$2,0)-1)-OFFSET(AT22,0,MATCH($B$1,AR$2:BO$2,0)-2))>BT22,"N","µ"),"")) | BV22: Used 'Concentration To One Obligor Without Guarantee' | BY22: Comparamos
B23: Credit risk (concentration) | C23: Single Obligor (Corp. and IFIs) Exposure Without Guarantee | D23: N/A | E23: $500 MM | F23: Solvency | H23: Y | L23: Y | P23: Y | Z23: YES | AA23: Used 'Concentration To One Obligor Without Guarantee' RTS metric | AC23: Monthly | AD23: RTS SBC #0020 | AE23: Used 'Concentration To One Obligor Without Guarantee' Total exposure of largest one obligor without guarantee (excluding U.S. and P.R. Government authorities, agencies, dependencies and municipalities’ loans) is compared with legal lending limit permitted by the Banking Law of Puerto Rico. The maximum loan limit to one obligor permitted by the Banking Law of Puerto Rico is up to 15% of the 50% of the bank’s undistributed earnings. To identify the highest obligor without guarantee in the Database 1001 BSPR, it shoud be filtered as follows: 1- Bank column select “004” (BSPR bank) 2- Product column select “05” (Commercial Risk) 3- Group name column exclude “Abengoa” (Abengoa group is the highest exposure however only $25MM is without guarantee). 4- Segment Column exclude “Institucional Público” (U.S and P R Government authorities, agencies, dependencies and municipalities’ loans) 5- Guarantee group select “Sin Garantía” The balance used is “Riesgo del cliente”, after filters have been applied, it should be sorted in order to identify the highest balance. The legal lending limit is calculated by Contropllership Unit in a quarterly basis and reported to ERM officers. | AF23: Risk MI / Rafael Martínez | AG23: TABLA 1001 | AH23: day 10th of each month depending on Accounting reconciliation | AJ23: Considered the Legal Lending Limit as of 3/31/2016 ($69.6MM). The 20% deviation from the Red (Limit) to the Green level represents the buffer permitted by the BOD to the Senior Management to manage the risks without risking the Bank’s capital. Per the Capital Stress Test (CCAR), there is ~20% distance from the baseline to the adverse scenario (stressed) while still maintaining the capital levels above the limits required by the regulator. That ~20% deviation is used from the Red (Limit) to the Green level in the RAS thus integrating the Capital Stress Test (CCAR) into the RAS. | AQ23: $55.7MM | AR23: $55.8MM | AS23: $69.6MM | AT23: 37.927291 | AU23: 37.927291 | AV23: 37.927202 | AW23: 37.779458 | AX23: 37.779458 | AY23: 36.03334 | AZ23: 36.033226 | BA23: 36.033226 | BB23: 36.033132 | BC23: 35.588046 | BD23: 35.588046 | BE23: 40 | BF23: 26 | BG23: 26 | BH23: 26 | BR23: =+IFERROR(AVERAGE(AT23:BQ23),"") -> 34.843314 | BS23: =+IFERROR(VAR(AT23:BQ23),"") -> 22.410783 | BT23: =+IFERROR(STDEV(AT23:BQ23)*(1-$BS$1),"") -> 2.3670014 | BU23: =+IF(OR(BT23="",OFFSET(AT23,0,MATCH($B$1,AT$2:BQ$2,0)-1)=""),"",IFERROR(IF(ABS(OFFSET(AT23,0,MATCH($B$1,AT$2:BQ$2,0)-1)-OFFSET(AT23,0,MATCH($B$1,AT$2:BQ$2,0)-2))>BT23,"N","µ"),"")) -> µ | BV23: Used 'Concentration To One Obligor Without Guarantee' | BW23: Used to be Single obligor exposure, included (Corp. and IFIs) to the name | BY23: Comparamos
C24: Top 20 Corporates Exposure | D24: $7.0B | E24: $8.0 B | F24: Solvency | H24: Y | L24: Y | P24: Y | Y24: 4/28/2016 Incudes Public Sector | Z24: YES | AC24: Monthly | AE24: Top 20 Total Exposure | AF24: Risk MI / Rafael Martínez | AG24: TABLA 1001 | AH24: day 10th of each month depending on Accounting reconciliation | AJ24: Thresholds defined per Historical Data: The the Green level is defined considering the average of Jan15 - Dec15 and the added the Standard Deviation for the same period. After Green Level is defined, the Red Limit is set using a 20% deviation. The Amber threshold is the remaining range between the Green and the Red threshold. The 20% deviation from the Green to the Red (Limit) represents the buffer permitted by the BOD to the Senior Management to manage the risks without risking the Bank’s capital. Per the Capital Stress Test (CCAR), there is ~20% distance from the baseline to the adverse scenario (stressed) while still maintaining the capital levels above the limits required by the regulator. That ~20% deviation is used from the Green level to the Red (Limit) in the RAS thus integrating the Capital Stress Test (CCAR) into the RAS. | AQ24: =STDEV(AT24:BE24)+(AVERAGE(AT24:BE24)) -> 827.25576 | AR24: =AQ24+1 -> 828.25576 | AS24: =AQ24*1.2 -> 992.70691 | AT24: 836.27936 | AU24: 802.55633 | AV24: 800.59972 | AW24: 801.34267 | AX24: 809.52345 | AY24: 806.86273 | AZ24: 798.30047 | BA24: 790.27428 | BB24: 680.28242 | BC24: 684.70841 | BD24: 658.98479 | BE24: 691.24722 | BF24: 689.08854 | BG24: 687.3231 | BH24: 687.61237 | BR24: =+IFERROR(AVERAGE(AT24:BQ24),"") -> 748.33239 | BS24: =+IFERROR(VAR(AT24:BQ24),"") -> 4177.311 | BT24: =+IFERROR(STDEV(AT24:BQ24)*(1-$BS$1),"") -> 32.31606 | BU24: =+IF(OR(BT24="",OFFSET(AT24,0,MATCH($B$1,AT$2:BQ$2,0)-1)=""),"",IFERROR(IF(ABS(OFFSET(AT24,0,MATCH($B$1,AT$2:BQ$2,0)-1)-OFFSET(AT24,0,MATCH($B$1,AT$2:BQ$2,0)-2))>BT24,"N","µ"),"")) -> µ | BW24: Used to be Top 20
C25: # of counterparties with Santander Risk Rating (internal) < 4.5 and exposure>$10MM (PR) | D25: New 2016 | E25: New 2016 | F25: Solvency | H25: Y | L25: Y | P25: Y | Z25: YES | AC25: Monthly | AE25: # of counterparties with Santander Risk Rating (internal) < 4.5 and exposure>$10MM | AF25: Risk MI / Rafael Martínez | AG25: TABLA 1001 | AH25: day 10th of each month depending on Accounting reconciliation | AJ25: Thresholds defined per Historical Data - The average of Jan15 - Dec15 is calculated and the added the Standard Deviation for the same period to define the Green level. In this case since the difference the 20% deviation to the Red Limit is not significant, the gap between the thresholds were be manually adjusted. | AQ25: =STDEV(AT25:BE25)+(AVERAGE(AT25:BE25)) -> 4.2598196 | AR25: 5 | AS25: 6 | AT25: 2 | AU25: 5 | AV25: 5 | AW25: 5 | AX25: 4 | AY25: 2 | AZ25: 1 | BA25: 1 | BB25: 1 | BC25: 1 | BD25: 2 | BE25: 2 | BF25: 2 | BG25: 3 | BH25: 3
C26: Industry Exposure (by OCC group) | D26: New 2016 | E26: New 2016 | F26: Solvency | H26: Y | L26: Y | P26: Y | T26: PR analysing Altair system | Y26: 1) Confirm with SHUSA if we can use Outstanding instead of Exposure to be aligned with BSPR local Concentration Guideline. 2) Will this metrics be divided per industry? All the industries will be included in the RAS or just the material industries? 3) Compared the SBNA OCC grouping vs. BSPR current local Concentration Guideline. Overall we can work on the segmentation however in some cases locally we would need another level of segregation (for risk management purposes as well as definition of strategies per our credit policies) which we can later aggregate to reach the SBNA OCC grouping. Groups which BSPR will have a higher level of segregation for further aggregation for the RAS: Government & Education: -Government & Education (Municipalities) -Government & Education (Indirect Risk (PRIDCO)) -Government & Education (Sovereign Risk / Agencies / Public Corp.) -Government & Education (Education) Health Care & Pharmaceuticals -Health Care & Pharmaceuticals (Health Care) -Health Care & Pharmaceuticals (Hospital) Real Estate & Construction -Real Estate & Construction (Commercial Real Estate) -Real Estate & Construction (Construction Developers) Restaurant & Hotel -Hotels and Tourism (Excluding Restaurant) Retail Stores Exc. Food & Drug -Retail Stores Exc. Food & Drug (Retail Sales including Auto Sales and Restaurant) -Retail Stores Exc. Food & Drug (Construction Related) | Z26: YES | AA26: Excludes CRE and Public Sector because there are separate specific metrics to monitor these exposures. SHUSA: Per SBNA methodology for calibration of OCC limit - We set a max $ amount for all industries (e.g. SBNA is $5 bn max per industry), any industry which goes above that needs special approval from the Board; SBNA set the limit as being approx. 50% of SBNA CET1+ACL) BSPR: Currently, the BSPR Concentration Guideline (which is approved by the BOD) has a maximum exposure of 10% (excluding CRE and Public Sector. This means that 10% of our total portfolio would be $4,004MM x 10% = $1,400MM. Therefore, we would have to apply the max concentration approved by the BOD for an industry to set the Red Limit and apply as a standard max limit for the rest of the industries in order to remain consistent with the BSPR Concentration Guideline. After Red Limit is defined, the Green Limit is set using a 20% deviation. The Amber threshold is the remaining range between the Green and the Red threshold. SHUSA said they will discuss further and provide feedback | AC26: Monthly | AE26: Highest industry exposure according to OCC segmentation excluding Realestate & Construction (which includes CRE) and Government and Education (which inclides Public Sector). Excludes CRE and Public Sector because there are specific metrics to monitor those portfolios. | AF26: Concentration Guideline (threshold calibration) Risk MI / Rafael Martínez | AG26: TABLA 1001 | AH26: day 10th of each month depending on Accounting reconciliation | AI26: Concentration Guideline | AJ26: Currently, the BSPR Concentration Guideline (which is approved by the BOD) has a maximum exposure of 10% (excluding CRE and Public Sector). This means that 10% of Bancorp total portfolio would be $4,004MM x 10% = $400MM (considered the March 2016 Total Exposure Portfolio of $4,004MM). Therefore, we would have to apply the max concentration approved by the BOD for an industry to set the Red Limit and apply as a standard max limit for the rest of the industries in order to remain consistent with the BSPR Concentration Guideline. After Red Limit is defined, the Green Limit is set using a 20% deviation. The Amber threshold is the remaining range between the Green and the Red threshold. The 20% deviation from the Red (Limit) to the Green level represents the buffer permitted by the BOD to the Senior Management to manage the risks without risking the Bank’s capital. Per the Capital Stress Test (CCAR), there is ~20% distance from the baseline to the adverse scenario (stressed) while still maintaining the capital levels above the limits required by the regulator. That ~20% deviation is used from the Red (Limit) to the Green level in the RAS thus integrating the Capital Stress Test (CCAR) into the RAS. | AQ26: =AS26*(1-0.2) -> 320.32 | AR26: =AQ26+1 -> 321.32 | AS26: =4004*0.1 -> 400.4 | AY26: ='Industry Exposure OCC'!H43 -> 314.925 | BB26: ='Industry Exposure OCC'!K43 -> 296.575 | BE26: ='Industry Exposure OCC'!N43 -> 291.76 | BH26: ='Industry Exposure OCC'!T43 -> 290.008 | BI26: 189.74833 | BR26: =+IFERROR(AVERAGE(AT26:BQ26),"") -> 276.60327 | BS26: =+IFERROR(VAR(AT26:BQ26),"") -> 2455.1548 | BT26: =+IFERROR(STDEV(AT26:BQ26)*(1-$BS$1),"") -> 24.774759 | BU26: =+IF(OR(BT26="",OFFSET(AT26,0,MATCH($B$1,AT$2:BQ$2,0)-1)=""),"",IFERROR(IF(ABS(OFFSET(AT26,0,MATCH($B$1,AT$2:BQ$2,0)-1)-OFFSET(AT26,0,MATCH($B$1,AT$2:BQ$2,0)-2))>BT26,"N","µ"),"")) | BV26: Per SBNA methodology for calibration of OCC limit - We set a max $ amount for all industries (e.g. SBNA is $5 bn max per industry), any industry which goes above that needs special approval from the Board; SBNA set the limit as being approx. 50% of SBNA CET1+ACL) | BY26: ?
C27: CRE Exposure | D27: New 2016 | E27: New 2016 | F27: Solvency | H27: Y | L27: Y | P27: Y | Y27: Confirm with SHUSA if we can use Outstanding instead of Exposure to be aligned with BSPR local Concentration Guideline. [SA]: As above - align to SBNA 4/22/2016 According to information included for BSPR and Glossary it is CRE excluding Multifamily. Pending equivalent data for Bancorp. | Z27: YES | AC27: Monthly | AE27: CRE exposure - pendiente confirmar cual es la metodología de calculo CRE exposure (excl. Multifamily) (PR) | AF27: Risk MI / Rafael Martínez | AG27: PROBLEMA IDENTIFICANDO STOCK, NO HAY MARCA EN SISTEMA Y LO QUE SE LLEVA ES MANUAL. Data included is Exposure provided by Rafa in 0000 RISK TOLERANCE | AH27: day 10th of each month depending on Accounting reconciliation | AI27: Concentration Guideline | AJ27: Currently, the BSPR Concentration Guideline (which is approved by the BOD) has a maximum exposure of 28% for the industry of CRE (portfolio with the highest allowed concentration). This means that 28% of our total portfolio would be $4,004MM x 28% = $1,121MM (considered the March 2016 Total Exposure Portfolio of $4,004MM). Therefore, we would have to apply the max concentration approved by the BOD for an industry to set the Red Limit and apply as a standard max limit for the rest of the industries in order to remain consistent with the BSPR Concentration Guideline. After Red Limit is defined, the Green Limit is set using a 20% deviation. The Amber threshold is the remaining range between the Green and the Red threshold. The 20% deviation from the Green to the Red (Limit) represents the buffer permitted by the BOD to the Senior Management to manage the risks without risking the Bank’s capital. Per the Capital Stress Test (CCAR), there is ~20% distance from the baseline to the adverse scenario (stressed) while still maintaining the capital levels above the limits required by the regulator. That ~20% deviation is used from the Red level (Limit) to the Green in the RAS thus integrating the Capital Stress Test (CCAR) into the RAS | AQ27: =AS27*(1-0.2) -> 896.896 | AR27: =AQ27+1 -> 897.896 | AS27: =4004*0.28 -> 1121.12 | AT27: 559.69855 | AU27: 565.73656 | AV27: 570.88634 | AW27: 583.31506 | AX27: 614.1112 | AY27: 612.13727 | AZ27: 614.66466 | BA27: 607.7376 | BB27: 602.4066 | BC27: 599.30244 | BD27: 598.24647 | BE27: 513.5657 | BF27: 512.26922 | BG27: 510.02835 | BH27: 508.19472 | BR27: =+IFERROR(AVERAGE(AT27:BQ27),"") -> 571.48672 | BS27: =+IFERROR(VAR(AT27:BQ27),"") -> 1717.8908 | BT27: =+IFERROR(STDEV(AT27:BQ27)*(1-$BS$1),"") -> 20.723723 | BU27: =+IF(OR(BT27="",OFFSET(AT27,0,MATCH($B$1,AT$2:BQ$2,0)-1)=""),"",IFERROR(IF(ABS(OFFSET(AT27,0,MATCH($B$1,AT$2:BQ$2,0)-1)-OFFSET(AT27,0,MATCH($B$1,AT$2:BQ$2,0)-2))>BT27,"N","µ"),"")) -> µ | BV27: Pending to confirm with SHUSA how metric will be calibrated. Shouldn't this limit be the same as the 'Industry exposure (by OCC group) (PR)'? The local Concentration Guideline indicates 150% of Tier 1 | BY27: Concentration Guideline
C28: Public Sector Exposure | D28: New 2016 | E28: New 2016 | F28: Solvency | H28: Y | L28: Y | P28: Y | Y28: Metric was change from 'Institutional exposure (PR)' to 'Public sector exposure (PR)' in order to include all exposure with PR government, municipalities, government agencies, etc. [SA]: OK Confirm with SHUSA if we can use Outstanding instead of Exposure to be aligned with local Concentration Guideline. Concenration Guideline presented Quarterly. [SA]: As above - align to SBNA 4/22/2016 Pendiente infromación, tenemos para Bancrp en 0000 Risk Tolerance para BSPR. | Z28: YES | AC28: Monthly | AE28: Total Exposure equals Drawn plus Available plus Contingencies for PR Government, Municipalities, Government Agencies, etc. | AF28: Risk MI / Rafael Martínez | AG28: TABLA 1001 | AH28: day 10th of each month depending on Accounting reconciliation | AI28: Concentration Guideline | AJ28: Currently, the BSPR Concentration Guideline (which is approved by the BOD) has a maximum exposure of 14% for the Public Sector. This means that 14% of our total portfolio would be $4,004MM x 14% = $561MM (considered the March 2016 Total Exposure Portfolio of $4,004MM). Therefore, we would have to apply the max concentration approved by the BOD for an industry to set the Red Limit and apply as a standard max limit for the rest of the industries in order to remain consistent with the BSPR Concentration Guideline. After Red Limit is defined, the Green Limit is set using a 20% deviation. The Amber threshold is the remaining range between the Green and the Red threshold. The 20% deviation from the Green to the Red (Limit) represents the buffer permitted by the BOD to the Senior Management to manage the risks without risking the Bank’s capital. Per the Capital Stress Test (CCAR), there is ~20% distance from the baseline to the adverse scenario (stressed) while still maintaining the capital levels above the limits required by the regulator. That ~20% deviation is used from the Red level (Limit) to the Green in the RAS thus integrating the Capital Stress Test (CCAR) into the RAS. | AQ28: =AS28*(1-0.2) -> 448.448 | AR28: =AQ28+1 -> 449.448 | AS28: =4004*0.14 -> 560.56 | AT28: 474.77383 | AU28: 471.88535 | AV28: 471.47619 | AW28: 471.08293 | AX28: 468.20172 | AY28: 460.37746 | AZ28: 456.86937 | BA28: 453.97987 | BB28: 326.12961 | BC28: 325.71993 | BD28: 321.74299 | BE28: 349.69984 | BF28: 349.13849 | BG28: 348.5808 | BH28: 347.97281 | BR28: =+IFERROR(AVERAGE(AT28:BQ28),"") -> 406.50875 | BS28: =+IFERROR(VAR(AT28:BQ28),"") -> 4449.7109 | BT28: =+IFERROR(STDEV(AT28:BQ28)*(1-$BS$1),"") -> 33.353077 | BU28: =+IF(OR(BT28="",OFFSET(AT28,0,MATCH($B$1,AT$2:BQ$2,0)-1)=""),"",IFERROR(IF(ABS(OFFSET(AT28,0,MATCH($B$1,AT$2:BQ$2,0)-1)-OFFSET(AT28,0,MATCH($B$1,AT$2:BQ$2,0)-2))>BT28,"N","µ"),"")) -> µ | BV28: Pending to confirm with SHUSA how metric will be calibrated. Shouldn't this limit be the same as the 'Industry exposure (by OCC group) (PR)'? The local Concentration Guideline indicates 75% of Tier 1 | BY28: Aplicamos el max de CRE
B29: Liquidity / Funding Risk | C29: Stressed Survival Period (days) | D29: 90 | E29: 60 | F29: Market Risk | H29: Y | L29: Y | P29: Y | Z29: YES | AA29: Historical Data is not available as this is a newly implemented metric | AC29: Monthly | AE29: The amount of days remaining until there is a cash shortfall under stressed conditions. | AF29: Market Risk / Marilena Castro | AG29: Metric is stored in EXCEL in a Local Network. Currently data is extracted from Balance Sheet statements for BSPR, SSC LLC and BanCorp, OFSA system, NMD Calculador (corporate system), which are consolidated into one spreadsheet (Excel). As part of the Market Risk Efficiency Plan, a server is being developed in which this data will be stored. | AH29: The availability depends on ALCO Committee date towards the end of the month. | AI29: Liquidity Policy | AJ29: Liquidity Policy Pending updated Liquidity Policy, triggers and limits provided by Market Risk Department according to analysis and presentation done and approved by the Board on February 2016. Refer to document Market Risk 2016 Limits Analysis v2 - Copy.docx, section 2.2. The 2016 Local Limit was set as the Ambar trigger and the 2016 RAS was set as the Red limit. | AL29: Market Risk Update Risk Committee as Liquidity Horizon ALCO Risk Scorecard | AQ29: > 90 days | AR29: < 90 days | AS29: <= 60 days | AT29: N/Avail | AU29: N/Avail | AV29: N/Avail | AW29: N/Avail | AX29: N/Avail | AY29: N/Avail | AZ29: N/Avail | BA29: N/Avail | BB29: N/Avail | BC29: N/Avail | BD29: N/Avail | BE29: N/Avail | BF29: N/Avail | BG29: N/Avail | BH29: N/Avail | BR29: =+IFERROR(AVERAGE(AT29:BQ29),"") | BS29: =+IFERROR(VAR(AT29:BQ29),"") | BT29: =+IFERROR(STDEV(AT30:BQ30)*(1-$BS$1),"") -> 0.010351391 | BU29: =+IF(OR(BT29="",OFFSET(AT30,0,MATCH($B$1,AT$2:BQ$2,0)-1)=""),"",IFERROR(IF(ABS(OFFSET(AT30,0,MATCH($B$1,AT$2:BQ$2,0)-1)-OFFSET(AT30,0,MATCH($B$1,AT$2:BQ$2,0)-2))>BT29,"N","µ"),"")) -> µ
C30: Structural funding ratio (%) | D30: 1.05 | E30: 1 | F30: Market Risk | H30: Y | L30: Y | P30: Y | Y30: 4/22/2016 Information gathered from Bancorp's RTS according to the corresponding metric. | Z30: YES | AC30: Monthly | AD30: RTS SBC #0170 | AE30: Calculation is adapted based on the additional assets that require stable funding (illiquid assets in the portfolio). As a general rule, wholesale short term financing cannot be considered as stable funding. The limit will be set according to the situation, generally >100% and with a minimum surplus. In some cases a limit under 100% could be set, but adding a maximum deficit amount. | AF30: Market Risk / Marilena Castro | AG30: Metric is stored in EXCEL in a Local Network. Currently data is extracted from Balance Sheet statements for BSPR, SSC LLC and BanCorp, OFSA system, NMD Calculador (corporate system), which are consolidated into one spreadsheet (Excel). As part of the Market Risk Efficiency Plan, a server is being developed in which this data will be stored. | AH30: The availability depends on ALCO Committee date towards the end of the month. | AI30: Liquidity Policy | AJ30: Liquidity Policy Pending updated Liquidity Policy, triggers and limits provided by Market Risk Department according to analysis and presentation done and approved by the Board on February 2016. Refer to document Market Risk 2016 Limits Analysis v2 - Copy.docx, section 2.2. The 2016 Local Limit was set as the Ambar trigger and the 2016 RAS was set as the Red limit. | AL30: Market Risk Update Risk Committee ALCO Risk Scorecard | AM30: 2015 February, March, May, June, August, September, November and December OK In Alco Risk Scorecard December is 107.72% Dec 2015 different than Dec 2015 in ALCO Risk Scorecard report (107.72%) (Jan 2016 107.87%) | AP30: 1 | AQ30: > 104% | AR30: <=104% | AS30: <= 102% | AT30: N/Avail | AU30: N/Avail | AV30: 1.0831 | AW30: 1.0804 | AX30: 1.0531 | AY30: 1.0392 | AZ30: 1.05 | BA30: 1.0567 | BB30: 1.0961044 | BC30: 1.090901 | BD30: 1.0969 | BE30: 1.0861 | BF30: 1.0885 | BG30: 1.089 | BH30: 1.1025 | BR30: =+IFERROR(AVERAGE(AT30:BQ30),"") -> 1.077885 | BS30: =+IFERROR(VAR(AT30:BQ30),"") -> 0.00042860516 | BT30: =+IFERROR(STDEV(AT30:BQ30)*(1-$BS$1),"") -> 0.010351391 | BU30: =+IF(OR(BT30="",OFFSET(AT30,0,MATCH($B$1,AT$2:BQ$2,0)-1)=""),"",IFERROR(IF(ABS(OFFSET(AT30,0,MATCH($B$1,AT$2:BQ$2,0)-1)-OFFSET(AT30,0,MATCH($B$1,AT$2:BQ$2,0)-2))>BT30,"N","µ"),"")) -> µ
C31: Liquidity Coverage Ratio (%) | E31: YES | F31: Historical Data is not available as this is a newly implemented metric | Y31: 4/27/2016 Eliminated from the RAS according to email from Scott Amarucci stating it would be redundant considering BSPR’s profile. However it will be maintained as operating limit and monitored by local market risk area. | Z31: YES | AC31: Monthly | AF31: Market Risk / Marilena Castro | AI31: Liquidity Policy | AJ31: Liquidity Policy Pending updated Liquidity Policy, triggers and limits provided by Market Risk Department according to analysis and presentation done and approved by the Board on February 2016. Refer to document Market Risk 2016 Limits Analysis v2 - Copy.docx, section 2.2. The 2016 Local Limit was set as the Ambar trigger and the 2016 RAS was set as the Red limit. | AL31: ALCO Risk Scorecard | AQ31: >110% | AR31: <= 110% | AS31: <= 100% | AT31: N/Avail | AU31: N/Avail | AV31: N/Avail | AW31: N/Avail | AX31: N/Avail | AY31: N/Avail | AZ31: N/Avail | BA31: N/Avail | BB31: N/Avail | BC31: N/Avail | BD31: N/Avail | BH31: 1.6257 | BR31: =+IFERROR(AVERAGE(AT31:BQ31),"") -> 1.6257 | BS31: =+IFERROR(VAR(AT31:BQ31),"") | BT31: =+IFERROR(STDEV(AT31:BQ31)*(1-$CL$1),"") | BU31: =+IF(OR(BT31="",OFFSET(AT31,0,MATCH($B$1,AT$2:BQ$2,0)-1)=""),"",IFERROR(IF(ABS(OFFSET(AT31,0,MATCH($B$1,AT$2:BQ$2,0)-1)-OFFSET(AT31,0,MATCH($B$1,AT$2:BQ$2,0)-2))>BT31,"N","µ"),""))
B32: Interest Rate Risk | C32: ALM NII (+/-100bps) | D32: ($120)MM | E32: ($140)MM | F32: Market Risk | H32: Y | L32: Y | P32: Y | T32: New for Group Dec-15 - with 100bps | V32: Ensure alignment with Group definition | W32: Finance / Treasury | X32: Market & Liquidity | Y32: 4/27/2016 Required to be calculated in percentage | Z32: YES | AC32: Monthly | AD32: RTS SBC #0030 | AE32: Worst case net interest income sensitivity between a parallel shock of +100bps and -100bps over a one year horizon. | AF32: Market Risk / Marilena Castro | AG32: Metric is stored in EXCEL in a Local Network. Currently data is extracted from ORACLE, OFSA, MIAC, Calculador (corporate system), and other working papers (Excels) which are consolidated into one spreadsheet (Excel). As part of the Market Risk Efficiency Plan, a server is being developed in which this data will be stored. | AH32: The availability depends on ALCO Committee date towards the end of the month. | AI32: IRR Policy | AJ32: IRR Policy Pending updated IRR Policy, triggers and limits provided by Market Risk Department according to analysis and presentation done and approved by the Board on February 2016. Refer to document Market Risk 2016 Limits Analysis v2 - Copy.docx, section 2.1. The Local Limit 2016 was set as the Ambar trigger and the RAS 2016 was set as the Red limit. These were then translated into percentages as per SHUSA's request, which is included in RAS Limits porcentual v3 excel document provided by the Market Risk Department. | AL32: Market Risk Update Risk Committee as NIM | AM32: 2015 March OK June OK September OK | AO32: ($12.0MM) | AP32: ($15.0MM) | AQ32: > -4.0% | AR32: <=-4.0% | AS32: <= -5.0% | AT32: N/Avail | AU32: N/Avail | AV32: N/Avail | AW32: N/Avail | AX32: N/Avail | AY32: N/Avail | AZ32: N/Avail | BA32: N/Avail | BB32: N/Avail | BC32: N/Avail | BD32: N/Avail | BE32: N/Avail | BF32: 0.0148 | BG32: 0.019 | BH32: 0.0217 | BR32: =+IFERROR(AVERAGE(AT32:BQ32),"") -> 0.0185 | BS32: =+IFERROR(VAR(AT32:BQ32),"") -> 1.209e-05 | BT32: =+IFERROR(STDEV(AT32:BQ32)*(1-$BS$1),"") -> 0.0017385339 | BU32: =+IF(OR(BT32="",OFFSET(AT32,0,MATCH($B$1,AT$2:BQ$2,0)-1)=""),"",IFERROR(IF(ABS(OFFSET(AT32,0,MATCH($B$1,AT$2:BQ$2,0)-1)-OFFSET(AT32,0,MATCH($B$1,AT$2:BQ$2,0)-2))>BT32,"N","µ"),"")) -> N
C33: ALM MVE (+/-100bps) | D33: ($1,070)MM | E33: ($1,220)MM | F33: Market Risk | H33: Y | L33: Y | P33: TBD | T33: New for Group Dec-15 - with 100bps | V33: Ensure alignment with Group definition | W33: Finance / Treasury | X33: Market & Liquidity | Y33: 4/27/2016 Agreed to be +/- 100 and required to be calculated in percentage Currently the Market Risk area calculates the 'ALM MVE (+200bps)' since interest curve cannot go down to (-200bps). The risk is with the (+200bps) which is the more severe since it's where we could experience losses. [SA]: Ok - will need to follow up with M. Lasso As discussed with Beatriz Shapiro on 2/12/2016 - Manolo Lasso will be discussing metric with Spain. 4/19/16 Confirmed with Market Risk Area. OK | Z33: YES | AC33: Monthly | AD33: RTS BSPR #0169 | AE33: Worst case market value of equity sensitivity between a parallel shock of +100bps over a one year horizon. | AF33: Market Risk / Marilena Castro | AG33: Metric is stored in EXCEL in a Local Network. Currently data is extracted from ORACLE, OFSA, MIAC, Calculador (corporate system), and other working papers (Excels) which are consolidated into one spreadsheet (Excel). As part of the Market Risk Efficiency Plan, a server is being developed in which this data will be stored. | AH33: The availability depends on ALCO Committee date towards the end of the month. | AI33: IRR Policy | AJ33: IRR Policy Pending updated IRR Policy, triggers and limits provided by Market Risk Department according to analysis and presentation done and approved by the Board on February 2016. Refer to document Market Risk 2016 Limits Analysis v2 - Copy.docx, section 2.1. The Local Limit 2016 was set as the Ambar trigger and the RAS 2016 was set as the Red limit. These were then translated into percentages as per SHUSA's request, which is included in RAS Limits porcentual v3 excel document provided by the Market Risk Department. | AL33: Market Risk Update Risk Committee | AM33: 2015 February, March, May, June, August, September, November and December OK | AQ33: > -5.4% | AR33: <=5.4% | AS33: <= -6.0% | AT33: N/Avail | AU33: N/Avail | AV33: N/Avail | AW33: N/Avail | AX33: N/Avail | AY33: N/Avail | AZ33: N/Avail | BA33: N/Avail | BB33: N/Avail | BC33: N/Avail | BD33: N/Avail | BE33: N/Avail | BF33: -0.0205 | BG33: -0.0175 | BH33: -0.0157 | BR33: =+IFERROR(AVERAGE(AT33:BQ33),"") -> -0.0179 | BS33: =+IFERROR(VAR(AT33:BQ33),"") -> 5.88e-06 | BT33: =+IFERROR(STDEV(AT33:BQ33)*(1-$BS$1),"") -> 0.0012124356 | BU33: =+IF(OR(BT33="",OFFSET(AT33,0,MATCH($B$1,AT$2:BQ$2,0)-1)=""),"",IFERROR(IF(ABS(OFFSET(AT33,0,MATCH($B$1,AT$2:BQ$2,0)-1)-OFFSET(AT33,0,MATCH($B$1,AT$2:BQ$2,0)-2))>BT33,"N","µ"),"")) -> N | BV33: Used 'ALM MVE (+ 200bps)' | BW33: Slide 7: Indicates it is included
B34: Operational Risk | C34: Gross Operational Risk Losses / Gross Marginon a 12 month trailing basis | D34: 0.03 | E34: 0.05 | F34: OP Risk Team | H34: Y | L34: Y | P34: Y | Z34: YES | AA34: SHUSA Operational Team is proposing to eliminate this metric | AC34: Quarterly | AE34: Total Gross Operational Risk Losses / Total Gross Margin on a 12 month trailing basis | AF34: Operational Risk Team | AG34: Altair/MOB Excel file sent by the Operations team | AJ34: Calibration provided by the SHUSA Operaterational Risk Team in coordination with the PR Ops Risk Team. Data is extracted from the Excel file New Group Metrics_ORM_020516 - Consolidated v6 on the sheet Gross Loss Gross Margin. | AK34: =1.781092/(261.891872409047+6.4759) -> 0.0066367581 | AQ34: =AK34 -> 0.0066367581 | AR34: 0.02 | AS34: 0.025 | BR34: =+IFERROR(AVERAGE(AT34:BQ34),"") | BS34: =+IFERROR(VAR(AT34:BQ34),"") | BT34: =+IFERROR(STDEV(AT34:BQ34)*(1-$BS$1),"") | BU34: =+IF(OR(BT34="",OFFSET(AT34,0,MATCH($B$1,AT$2:BQ$2,0)-1)=""),"",IFERROR(IF(ABS(OFFSET(AT34,0,MATCH($B$1,AT$2:BQ$2,0)-1)-OFFSET(AT34,0,MATCH($B$1,AT$2:BQ$2,0)-2))>BT34,"N","µ"),"")) | BV34: Under discussion between SHUSA and Local Operational Teams
C35: Material Operational Risk Events | D35: 9 | E35: 16 | F35: OP Risk Team | H35: Y | L35: Y | P35: Y | T35: SIS Levels TBD | Z35: YES | AA35: SHUSA Operational Team is proposing to eliminate this metric | AC35: Quarterly | AE35: The number of material operational risk events (as Defined by the SHUSA Operational Risk Event Escalation) . Methodology: No calculation necessary. Data extraction of Operational Risk Events Measures the ratio of gross operational risk losses to gross margin - Operational Risk Losses reported in the period (excluding recoveries – direct or indirect, excluding legal reserves and including legal settlements) Gross Margin (Net Revenue) is defined as: Net Interest Income + Fees + Other Fees + Security and Related Derivatives Gains – Security and Related Derivatives losses reported in the period | AF35: Operational Risk Team | AG35: Altair | AJ35: Zero tolerance to Operational Risk events | AR35: 0 | AS35: 0 | BR35: =+IFERROR(AVERAGE(AT35:BQ35),"") | BS35: =+IFERROR(VAR(AT35:BQ35),"") | BT35: =+IFERROR(STDEV(AT35:BQ35)*(1-$BS$1),"") | BU35: =+IF(OR(BT35="",OFFSET(AT35,0,MATCH($B$1,AT$2:BQ$2,0)-1)=""),"",IFERROR(IF(ABS(OFFSET(AT35,0,MATCH($B$1,AT$2:BQ$2,0)-1)-OFFSET(AT35,0,MATCH($B$1,AT$2:BQ$2,0)-2))>BT35,"N","µ"),"")) | BV35: Under discussion between SHUSA and Local Operational Teams | BW35: Changed from Frequency of material risk events >$200k in losses.
B36: Model | C36: Legacy Tier 1 Models in Production w/o Appropriate Approval | D36: N/A | E36: 4Q15-102 / 2Q16-90 / 4Q16-60 / 2Q17-30 / 4Q17-0 | F36: MRMG | H36: N | L36: Y | P36: Y | Z36: YES | AC36: Monthly | AE36: Currently there are 3 Tier I Models: 1) NMD (model id: 558 / use id: 521) 2) OFSA – Cash Flow (model id: 568 / use id: 531) 3) Anti Money Laundering (model id: 366 / use id: 364) 1) Model NMD (model id: 558 / use id: 521) approved on 2/26/2016. 2) OFSA – Cash Flow (model id: 568 / use id: 531) - Thsi model will be eliminated upon migration to QRM on 3Q16. Therefore model will not be validated nor approved. 3) Anti Money Laundering (model id: 366 / use id: 364) - Validation process should begin in July 2016 upon implementation of IHC. Due to the model's complexity, the validation / approval for this model is expected to take 60-90 days finishing on 4Q 2016. | AF36: Model Risk Managament | AG36: Metric is stored in EXCEL in a Local Network. | AJ36: Currently there are 3 Tier I Models: 1) NMD (model id: 558 / use id: 521) 2) OFSA – Cash Flow (model id: 568 / use id: 531) 3) Anti Money Laundering (model id: 366 / use id: 364) 1) Model NMD (model id: 558 / use id: 521) approved on 2/26/2016. 2) OFSA – Cash Flow (model id: 568 / use id: 531) - Thsi model will be eliminated upon migration to QRM on 3Q16. Therefore model will not be validated nor approved. 3) Anti Money Laundering (model id: 366 / use id: 364) - Validation process should begin in July 2016 upon implementation of IHC. Due to the model's complexity, the validation / approval for this model is expected to take 60-90 days finishing on 4Q 2016. | AQ36: N/A | AR36: N/A | AS36: 4Q15-3 / 1Q16-2 / 2Q16-2 / 3Q16-2 / 4Q16-0 | AT36: 3 | AU36: 3 | AV36: 3 | AW36: 3 | AX36: 3 | AY36: 3 | AZ36: 3 | BA36: 3 | BB36: 3 | BC36: 3 | BD36: 3 | BE36: 3 | BF36: 3 | BG36: 2 | BH36: 2 | BR36: =+IFERROR(AVERAGE(AT36:BQ36),"") -> 2.8666667 | BS36: =+IFERROR(VAR(AT36:BQ36),"") -> 0.12380952 | BT36: =+IFERROR(STDEV(AT36:BQ36)*(1-$BS$1),"") -> 0.17593289 | BU36: =+IF(OR(BT36="",OFFSET(AT36,0,MATCH($B$1,AT$2:BQ$2,0)-1)=""),"",IFERROR(IF(ABS(OFFSET(AT36,0,MATCH($B$1,AT$2:BQ$2,0)-1)-OFFSET(AT36,0,MATCH($B$1,AT$2:BQ$2,0)-2))>BT36,"N","µ"),"")) -> N | BV36: Under discussion between SHUSA and Local MRM Teams
B37: Compliance and Reputational | C37: Open MRIAs or equivalent matters requiring immediate attention (MRIA) | D37: N/A | E37: 0 | F37: Compliance | H37: N | L37: Y | P37: Y | T37: MRIAs / OCC, whatever is relevant for the entity | Z37: YES | AC37: Monthly | AE37: Considers only regulatory matters no Internal Audit recommendations | AF37: Internal Controls | AG37: Regulators -Recommendations Database | AJ37: As established in the BSPR Strategic Plan “Visión 360 (2016-2018)”, there will be 0 tolerance regarding Laws and Regulatory Compliance. Any indicator measuring compliance or related to a regulatory requirement, the Green level is established as 0 or 100% compliance. | AO37: 0 | AP37: 0 | AQ37: 0 | AR37: 0 | AS37: 0 | AT37: 0 | AU37: 0 | AV37: 0 | AW37: 0 | AX37: 0 | AY37: 0 | AZ37: 0 | BA37: 0 | BB37: 0 | BC37: 0 | BD37: 0 | BE37: 0 | BF37: 0 | BG37: 0 | BH37: 0 | BR37: =+IFERROR(AVERAGE(AT37:BQ37),"") -> 0 | BS37: =+IFERROR(VAR(AT37:BQ37),"") -> 0 | BT37: =+IFERROR(STDEV(AT37:BQ37)*(1-$BS$1),"") -> 0 | BU37: =+IF(OR(BT37="",OFFSET(AT37,0,MATCH($B$1,AT$2:BQ$2,0)-1)=""),"",IFERROR(IF(ABS(OFFSET(AT37,0,MATCH($B$1,AT$2:BQ$2,0)-1)-OFFSET(AT37,0,MATCH($B$1,AT$2:BQ$2,0)-2))>BT37,"N","µ"),"")) -> µ
C40: Corporate Metric

Sheet Eliminated from RAS
B1: 42401 | W1: ACTION PLAN OWNER | AC1: PR - BSPR | BR1: Sensitivity | BS1: 0.5
C2: SHUSA RISK APPETITE METRICS | D2: 2015 TRIGGER LIMIT | E2: 2015 RED LIMIT | F2: SOURCE FOR 2016 RAS LIMIT SETTING | H2: SHUSA IN GROUP RAS | I2: 2016 TRIGGER LIMIT | J2: 2016 RED LIMIT | L2: SHUSA US RAS | M2: 2016 TRIGGER LIMIT | N2: 2016 RED LIMIT | P2: BSPR | Q2: 2016 TRIGGER LIMIT | R2: 2016 RED LIMIT | T2: COMMENTS | U2: GROUP DEFINITION | V2: ACTION PLAN | W2: LINE 1 | X2: LINE 2 | Y2: BSPR Comments | Z2: Metric Applicability Confirmed with SHUSA | AA2: Calibration Comments | AC2: Frequency | AD2: Current RTS / RSC metric | AE2: SAN-PR Definition | AF2: SOURCE FOR 2016 RAS LIMIT SETTING | AG2: Source | AH2: Availability | AI2: Level | AJ2: Rationale for threshold definition | AK2: Budget | AL2: Reports Affected | AM2: Reports Consistency Validation | AN2: Differences: SHUSA RAS Glossary vs. BSPR Methodology | AO2: 2015 TRIGGER LIMIT | AP2: 2015 RED LIMIT | AQ2: 2016 GREEN | AR2: 2016 TRIGGER LIMIT | AS2: 2016 RED LIMIT | AT2: 42035 | AU2: 42063 | AV2: 42094 | AW2: 42124 | AX2: 42155 | AY2: 42185 | AZ2: 42216 | BA2: 42247 | BB2: 42277 | BC2: 42308 | BD2: 42338 | BE2: 42369 | BF2: 42400 | BG2: 42401 | BH2: 42430 | BI2: 42461 | BJ2: 42491 | BK2: 42522 | BL2: 42552 | BM2: 42583 | BN2: 42614 | BO2: 42644 | BP2: 42675 | BQ2: 42705 | BR2: Average | BS2: Variance | BT2: Standard Deviation | BU2: AVS | BV2: Local Comments - Cristina's Review | BW2: Comparación 4/8/16
C3: Large Exposures | D3: New 2016 | E3: New 2016 | F3: Solvency | H3: New 2016 | L3: New 2016 | P3: TBD | T3: Pending from Group Jun-15 For SBNA and PR this metric is practically the same as the Top 20. | U3: % of equity of the aggregate exposure with customers and counterparties classified as "large exposures", i.e. > "% of Equity (Group) and CET1 + ACL (US) | V3: Request and analyze historical data and compare to Top 20. Recommend exemption if metric is too similar | W3: Business Heads | X3: Solvency for historical data / RAS Team | Z3: PENDING | AA3: 4/8/2016 Eliminated according to 2016 RAS Calibration Supporting Documentation Plan received from SHUSA. | AC3: ? | BR3: =+IFERROR(AVERAGE(AT3:BQ3),"") | BS3: =+IFERROR(VAR(AT3:BQ3),"") | BT3: =+IFERROR(STDEV(AT3:BQ3)*(1-$BS$1),"") | BU3: =+IF(OR(BT3="",OFFSET(AT3,0,MATCH($B$1,AT$2:BQ$2,0)-1)=""),"",IFERROR(IF(ABS(OFFSET(AT3,0,MATCH($B$1,AT$2:BQ$2,0)-1)-OFFSET(AT3,0,MATCH($B$1,AT$2:BQ$2,0)-2))>BT3,"N","µ"),"")) | BW3: Not included anywhere in presentation
C4: Financial Institutions (single counterparty) | D4: New 2016 | E4: New 2016 | F4: Solvency | H4: Y | L4: Y | P4: TBD | T4: New from Group Dec-15 PR probably not material | U4: Maximum individual exposure in terms of maximum REC Net, at Financial Institution economic group level, excluding public and quasi public and clearing houses (LCH, Freddie, Fannie) - against Equity (Group) and CET1 + ACL (US) | V4: Analyze Group metric definition (esp. REC definition). Request and analyze historical data SBNA. Review against CET1+ACL | W4: Head of GCB | X4: Solvency / GCB Credit Risk Control for historical data | Y4: The exposure with Financial Institutions are 2 uncommited lines totaling $13MM and with Mortgage Banks totaling $7.6MM. Financial Institutions exposure is not considered material therefore would not include in the RAS. [SA]: Likely will treat same way as we are proposing for SBNA; have same limit as Corporates (single CP) BSPR - Considering Financial Institutions are not material in PR, could we just keep the 'Single obligor exposure' metric in which if esposure in Financial Institution reaches a significant level we would catch it in this metric? | Z4: PENDING | AA4: 4/8/2016 Eliminated according to 2016 RAS Calibration Supporting Documentation Plan received from SHUSA. | AC4: ? | BR4: =+IFERROR(AVERAGE(AT4:BQ4),"") | BS4: =+IFERROR(VAR(AT4:BQ4),"") | BT4: =+IFERROR(STDEV(AT4:BQ4)*(1-$BS$1),"") | BU4: =+IF(OR(BT4="",OFFSET(AT4,0,MATCH($B$1,AT$2:BQ$2,0)-1)=""),"",IFERROR(IF(ABS(OFFSET(AT4,0,MATCH($B$1,AT$2:BQ$2,0)-1)-OFFSET(AT4,0,MATCH($B$1,AT$2:BQ$2,0)-2))>BT4,"N","µ"),"")) | BW4: Not included anywhere in presentation
C5: 60+ PR TOTAL | P5: Y | Y5: Included a new 60+ Total Metric to monitor NCOs at a Consolidadted Bank level Portfolio Management: 60+ Total PR: sugiero eliminarlo pues en realidad no hay un gestor identificado en el Banco que observe esta cifra agregada. Aún más, las estrategias para los productos/segmentos son tan distintas que se recogen en PEC’s distintos administrados por grupos ejecutivos distintos. | Z5: YES | AA5: 4/18/16 Eliminated according to conversation with Portfolio Management (Luis Lopez) and with approval of JPJP. They do have a budget for the Standardized portfolio but not for the Non-Standardized since the management procedures and strategies are different. | AE5: NUMERATOR: 60+ Total Portfolio divided by DENOMINATOR: Total Portfolio % | AJ5: Thresholds defined per Historical Data - The average of Jan15 - Dec15 is calculated and the added the Standard Deviation for the same period to define the Green level. After Green Level is defined, the Red Limit is set using a 20% deviation. The Amber threshold is the remaining range between the Green and the Red threshold. | AQ5: =STDEV(AT5:BE5)+(AVERAGE(AT5:BE5)) -> 0.046380138 | AR5: =AQ5+0.0001 -> 0.046480138 | AS5: =AQ5*1.2 -> 0.055656166 | AT5: =182989324.76/4191543000 -> 0.043656793 | AU5: =178367192.12/4168446000 -> 0.042789853 | AV5: =175851005.05/4172064000 -> 0.042149642 | AW5: =177754108.64/4181531000 -> 0.042509337 | AX5: =176312206.56/4227487000 -> 0.04170615 | AY5: =174068811.14/4255324000 -> 0.040906124 | AZ5: =194601535.07/4232319000 -> 0.045979884 | BA5: =183942890.73/4182179000 -> 0.043982549 | BB5: =184023179.92/4015154137 -> 0.045832158 | BC5: =179064582.69/3984909000 -> 0.044935677 | BD5: =192243342.94/3934542000 -> 0.048860412 | BE5: =181405966.58/3954119546.76 -> 0.045877714 | BF5: =179220626.72/3922925000 -> 0.045685458 | BR5: =+IFERROR(AVERAGE(AT5:BQ5),"") -> 0.044220904 | BS5: =+IFERROR(VAR(AT5:BQ5),"") -> 4.9641923e-06 | BT5: =+IFERROR(STDEV(AT5:BQ5)*(1-$BS$1),"") -> 0.0011140234 | BU5: =+IF(OR(BT5="",OFFSET(AT5,0,MATCH($B$1,AT$2:BQ$2,0)-1)=""),"",IFERROR(IF(ABS(OFFSET(AT5,0,MATCH($B$1,AT$2:BQ$2,0)-1)-OFFSET(AT5,0,MATCH($B$1,AT$2:BQ$2,0)-2))>BT5,"N","µ"),""))
B6: Operational Risk | C6: Fraud (number) | D6: New 2016 | E6: New 2016 | F6: OP Risk Team | H6: Y | L6: Y | P6: Y | T6: New from Group Dec-16 Op Risk SHUSA is coordinating with the entities to understand the quality of the underlying data for each indicator | U6: Synthetic indicator. Card Fraud Ratio (70% weight) = Total number of debit or credit card fraud / total active cards. Telephone banking Fraud (10% weight) = total fraud cases / total calls received. E-banking fraud (20% weighting) = number of fraud cases through E-banking / total users of E-banking | V6: Analyse Group metric definition and historical ratios at SHUSA and subs in order to determine trigger and thresholds | W6: T&O | X6: Operational Risk Team | Y6: Metric cannot be currently calculated unless divided by components. As confirmed with the local Ops Team (who are discussing Ops metrics with the SHUSA Ops Team), the Card Fraud component can be calculated however the Telephone Banking and E-banking components cannot be divided for BSPR and SSLLC with the current tool. Metric could be divided for BSPR and SSLLC upon implementation of SHUSA IGRC tool expected for 3Q2016. | Z6: PENDING | AA6: 4/8/2016 Eliminated according to 2016 RAS Calibration Supporting Documentation Plan received from SHUSA. | AC6: ? | BR6: =+IFERROR(AVERAGE(AT6:BQ6),"") | BS6: =+IFERROR(VAR(AT6:BQ6),"") | BT6: =+IFERROR(STDEV(AT6:BQ6)*(1-$BS$1),"") | BU6: =+IF(OR(BT6="",OFFSET(AT6,0,MATCH($B$1,AT$2:BQ$2,0)-1)=""),"",IFERROR(IF(ABS(OFFSET(AT6,0,MATCH($B$1,AT$2:BQ$2,0)-1)-OFFSET(AT6,0,MATCH($B$1,AT$2:BQ$2,0)-2))>BT6,"N","µ"),"")) | BV6: Under discussion between SHUSA and Local Operational Teams | BW6: Not included anywhere in the presentation.
C7: Technology (number) | D7: New 2016 | E7: New 2016 | F7: OP Risk Team | H7: Y | L7: Y | P7: Y | T7: New from Group Dec-16 Op Risk SHUSA is coordinating with the entities to understand the quality of the underlying data for each indicator | U7: Synthetic indicator. P1 and P2 incidents in production (33.3% weight). % availability of the systems (33.3% weight) Weighted average of the availability of percentages of each of the services identified as critical by the entity. % server software in obsolete versions of critical services (33.3% weight) | V7: Analyze Group metric definition and historical ratios at SHUSA and subs in order to determine trigger and thresholds. May not be relevant to SIS | W7: T&O | X7: Operational Risk Team | Y7: As confirmed with the local Ops Team (who are discussing Ops metrics with the SHUSA Ops Team), the metrics components cannot be divided for BSPR and SSLLC with the current tool. Metric could be divided for BSPR and SSLLC upon implementation of SHUSA IGRC tool expected for 3Q2016. | Z7: PENDING | AA7: 4/8/2016 Eliminated according to 2016 RAS Calibration Supporting Documentation Plan received from SHUSA. | AC7: ? | BR7: =+IFERROR(AVERAGE(AT7:BQ7),"") | BS7: =+IFERROR(VAR(AT7:BQ7),"") | BT7: =+IFERROR(STDEV(AT7:BQ7)*(1-$BS$1),"") | BU7: =+IF(OR(BT7="",OFFSET(AT7,0,MATCH($B$1,AT$2:BQ$2,0)-1)=""),"",IFERROR(IF(ABS(OFFSET(AT7,0,MATCH($B$1,AT$2:BQ$2,0)-1)-OFFSET(AT7,0,MATCH($B$1,AT$2:BQ$2,0)-2))>BT7,"N","µ"),"")) | BV7: Under discussion between SHUSA and Local Operational Teams | BW7: Not included anywhere in the presentation.
C8: Cyber Risk (number) | D8: New 2016 | E8: New 2016 | F8: OP Risk Team | H8: Y | L8: Y | P8: Y | T8: New from Group Dec-16 Op Risk SHUSA is coordinating with the entities to understand the quality of the underlying data for each indicator | U8: Synthetic indicator. Number of high-risk vulnerabilities detected in ethical hacking tests awaiting corrections for > 3 months (33.3% weight). Number of security incidents in relation to distributed denial of service (DDoS) (33.3% weight). Number of security incidents with customer data leaks (33.3% weight) | V8: Analyze Group metric definition and historical ratios at SHUSA and subs in order to determine trigger and thresholds | W8: T&O | X8: Operational Risk Team | Y8: Metric cannot be currently calculated unless divided by components. As confirmed with the local Ops Team (who are discussing Ops metrics with the SHUSA Ops Team), the Information Leakages component can be calculated however the Ethical hacking tests component cannot be divided for BSPR and SSLLC with the current tool. Metric could be divided for BSPR and SSLLC upon implementation of SHUSA IGRC tool expected for 3Q2016. The Distributed Denial of Service (DDoS) component cannot be calculated since a tool is needed in order to obtain the data. Is pending evaluation for Systems Plan 2017. | Z8: PENDING | AA8: 4/8/2016 Eliminated according to 2016 RAS Calibration Supporting Documentation Plan received from SHUSA. | AC8: ? | BR8: =+IFERROR(AVERAGE(AT8:BQ8),"") | BS8: =+IFERROR(VAR(AT8:BQ8),"") | BT8: =+IFERROR(STDEV(AT8:BQ8)*(1-$BS$1),"") | BU8: =+IF(OR(BT8="",OFFSET(AT8,0,MATCH($B$1,AT$2:BQ$2,0)-1)=""),"",IFERROR(IF(ABS(OFFSET(AT8,0,MATCH($B$1,AT$2:BQ$2,0)-1)-OFFSET(AT8,0,MATCH($B$1,AT$2:BQ$2,0)-2))>BT8,"N","µ"),"")) | BV8: Under discussion between SHUSA and Local Operational Teams | BW8: Not included anywhere in the presentation.
B9: Interest Rate Risk | C9: ALM MVE (+/-200bps) BSPR | D9: ($1,070)MM | E9: ($1,220)MM | F9: Market Risk | H9: Y | L9: Y | P9: TBD | T9: New for Group Dec-15 - with 100bps | V9: Ensure alignment with Group definition | W9: Finance / Treasury | X9: Market & Liquidity | Y9: 4/27/2016 Changedfor +/- 100 Currently the Market Risk area calculates the 'ALM MVE (+200bps)' since interest curve cannot go down to (-200bps). The risk is with the (+200bps) which is the more severe since it's where we could experience losses. [SA]: Ok - will need to follow up with M. Lasso As discussed with Beatriz Shapiro on 2/12/2016 - Manolo Lasso will be discussing metric with Spain. 4/19/16 Confirmed with Market Risk Area. OK | Z9: YES | AA9: 4/27/2016 Changedfor +/- 100bsp | AC9: Monthly | AD9: RTS BSPR #0031 | AE9: Worst case market value of equity sensitivity between a parallel shock of +200bps over a one year horizon. | AF9: Market Risk / Marilena Castro | AG9: Metric is stored in EXCEL in a Local Network. Currently data is extracted from ORACLE, OFSA, MIAC, Calculador (corporate system), and other working papers (Excels) which are consolidated into one spreadsheet (Excel). As part of the Market Risk Efficiency Plan, a server is being developed in which this data will be stored. | AH9: The availability depends on ALCO Committee date towards the end of the month. | AI9: IRR Policy | AJ9: IRR Policy | AL9: Market Risk Update Risk Committee | AM9: 2015 February, March, May, June, August, September, November and December OK | AQ9: ($85MM) | AR9: ($85MM ) | AS9: ($95MM) | AT9: -36.95 | AU9: -51.47 | AV9: -49.4 | AW9: -51.348205 | AX9: -53.75 | AY9: -59.1 | AZ9: -55.048283 | BA9: -42.729659 | BB9: -40.399868 | BC9: -43.484393 | BD9: -42.9 | BE9: -48.85 | BF9: -45.4 | BG9: -41.768116 | BH9: -41.768116 | BR9: =+IFERROR(AVERAGE(AT9:BQ9),"") -> -46.957776 | BS9: =+IFERROR(VAR(AT9:BQ9),"") -> 39.576118 | BT9: =+IFERROR(STDEV(AT9:BQ9)*(1-$BS$1),"") -> 3.1454776 | BU9: =+IF(OR(BT9="",OFFSET(AT9,0,MATCH($B$1,AT$2:BQ$2,0)-1)=""),"",IFERROR(IF(ABS(OFFSET(AT9,0,MATCH($B$1,AT$2:BQ$2,0)-1)-OFFSET(AT9,0,MATCH($B$1,AT$2:BQ$2,0)-2))>BT9,"N","µ"),"")) -> N | BV9: Used 'ALM MVE (+ 200bps)' | BW9: Slide 7: Indicates it is included
B10: Compliance and Reputational | C10: High risk customers as % of total customers | D10: TBD | E10: TBD | F10: Compliance | H10: N | L10: Y | P10: Y | T10: Being evaluated at SBNA, PR and Miami | Y10: 4/27/2016 Eliminated according to discuttion with Corey Shaw. To be included later in the year when the customer risk rating process is fully developed for and implemented BSPR. Pending methodology from SHUSA | Z10: NO | AA10: 4/28/2016 SHUSA Compliance team informed that the SAN-PR customer risk rating process wasn't fully built out for all customers so we are going to wait to develop triggers and thresholds until later in this year. | AC10: Monthly | AE10: NUMERATOR:The total number of existing customers, to date, for the Operating Entity with high risk profiles divided by DENOMINATOR: Total clients | AF10: Compliance Department | AT10: N/A | AU10: N/A | AV10: N/A | AW10: N/A | AX10: N/A | AY10: N/A | AZ10: N/A | BA10: N/A | BB10: N/A | BC10: N/A | BD10: N/A | BE10: N/A | BF10: =2655/287766 -> 0.0092262463 | BG10: =2803/238867 -> 0.011734564 | BR10: =+IFERROR(AVERAGE(AT10:BQ10),"") -> 0.010480405 | BS10: =+IFERROR(VAR(AT10:BQ10),"") -> 3.1458277e-06 | BT10: =+IFERROR(STDEV(AT10:BQ10)*(1-$BS$1),"") -> 0.00088682407 | BU10: =+IF(OR(BT10="",OFFSET(AT10,0,MATCH($B$1,AT$2:BQ$2,0)-1)=""),"",IFERROR(IF(ABS(OFFSET(AT10,0,MATCH($B$1,AT$2:BQ$2,0)-1)-OFFSET(AT10,0,MATCH($B$1,AT$2:BQ$2,0)-2))>BT10,"N","µ"),"")) -> N | BV10: Pending methodology from SHUSA. Confirmed with the Compliance team that they have not been contacted by the SHUSA Compliance team. | BW10: Has been changed from New High Risk Customers as % of Total New Customers
C11: CFPB Complaints | D11: TBD | E11: TBD | F11: Compliance | H11: N | L11: Y | P11: Y | T11: Whatever regulator is relevant for each entity | Y11: 4/27/2016 Eliminated according to discuttion with Corey Shaw. To be included later in the year. | Z11: PENDING | AA11: 4/28/2016 SHUSA Compliance team informed that we are going to wait to develop triggers and thresholds until later in this year. | AC11: Monthly | AE11: Montlhly complaints received from the CFPB | AF11: Customer Experience | AG11: Informe Acum Enero 2014 hasta XXXXX | AJ11: Thresholds defined per Historical Data: The the Green level is defined considering the average of Jan15 - Dec15 and the added the Standard Deviation for the same period. After Green Level is defined, the Red Limit is set using a 20% deviation. The Amber threshold is the remaining range between the Green and the Red threshold. In this case since the difference the 20% deviation to the Red Limit is not significant, the gap between the thresholds were be manually adjusted. | AL11: SAC Corporativo (Informe de Reclamos Formales PR para España) Formal Complaints BanCorp- Risk Committee | AQ11: =STDEV(AT11:BE11)+(AVERAGE(AT11:BE11)) -> 4.9069252 | AR11: 6 | AS11: 7 | AT11: 0 | AU11: 2 | AV11: 5 | AW11: 2 | AX11: 2 | AY11: 1 | AZ11: 4 | BA11: 7 | BB11: 4 | BC11: 3 | BD11: 4 | BE11: 2 | BF11: 4 | BG11: 1 | BH11: 3 | BR11: =+IFERROR(AVERAGE(AT11:BQ11),"") -> 2.9333333 | BS11: =+IFERROR(VAR(AT11:BQ11),"") -> 3.2095238 | BT11: =+IFERROR(STDEV(AT11:BQ11)*(1-$BS$1),"") -> 0.89575719 | BU11: =+IF(OR(BT11="",OFFSET(AT11,0,MATCH($B$1,AT$2:BQ$2,0)-1)=""),"",IFERROR(IF(ABS(OFFSET(AT11,0,MATCH($B$1,AT$2:BQ$2,0)-1)-OFFSET(AT11,0,MATCH($B$1,AT$2:BQ$2,0)-2))>BT11,"N","µ"),"")) -> N | BV11: Confirm with Ivelisse
B12: Interest Rate Risk | C12: ALM MVE (+/-200bps) BANCORP | D12: ($1,070)MM | E12: ($1,220)MM | F12: Market Risk | H12: Y | L12: Y | P12: TBD | T12: New for Group Dec-15 - with 100bps | V12: Ensure alignment with Group definition | W12: Finance / Treasury | X12: Market & Liquidity | Y12: 4/27/2016 Changedfor +/- 100 Currently the Market Risk area calculates the 'ALM MVE (+200bps)' since interest curve cannot go down to (-200bps). The risk is with the (+200bps) which is the more severe since it's where we could experience losses. [SA]: Ok - will need to follow up with M. Lasso As discussed with Beatriz Shapiro on 2/12/2016 - Manolo Lasso will be discussing metric with Spain. 4/19/16 Confirmed with Market Risk Area. OK | Z12: YES | AA12: 4/27/2016 Changedfor +/- 100 | AC12: Monthly | AD12: RTS BSPR #0031 | AE12: Worst case market value of equity sensitivity between a parallel shock of +200bps over a one year horizon. | AF12: Market Risk / Marilena Castro | AG12: Metric is stored in EXCEL in a Local Network. Currently data is extracted from ORACLE, OFSA, MIAC, Calculador (corporate system), and other working papers (Excels) which are consolidated into one spreadsheet (Excel). As part of the Market Risk Efficiency Plan, a server is being developed in which this data will be stored. | AH12: The availability depends on ALCO Committee date towards the end of the month. | AI12: IRR Policy | AJ12: IRR Policy | AL12: Market Risk Update Risk Committee | AM12: 2015 February, March, May, June, August, September, November and December OK | AQ12: ($100.0MM) | AR12: ($101.0MM ) | AS12: ($135.0MM) | AT12: -48.38 | AU12: -63.04 | AV12: -60.83 | AW12: -62.380593 | AX12: -64.8 | AY12: -70 | AZ12: -65.9 | BA12: -53.844531 | BB12: -51.106315 | BC12: -53.982363 | BD12: -53.2 | BE12: -58.97 | BF12: -55.562196 | BG12: -51.8 | BR12: =+IFERROR(AVERAGE(AT12:BQ12),"") -> -58.128286 | BS12: =+IFERROR(VAR(AT12:BQ12),"") -> 42.066162 | BT12: =+IFERROR(STDEV(AT12:BQ12)*(1-$BS$1),"") -> 3.2429216 | BU12: =+IF(OR(BT12="",OFFSET(AT12,0,MATCH($B$1,AT$2:BQ$2,0)-1)=""),"",IFERROR(IF(ABS(OFFSET(AT12,0,MATCH($B$1,AT$2:BQ$2,0)-1)-OFFSET(AT12,0,MATCH($B$1,AT$2:BQ$2,0)-2))>BT12,"N","µ"),"")) -> N | BV12: Used 'ALM MVE (+ 200bps)' | BW12: Slide 7: Indicates it is included
B13: Liquidity / Funding Risk | C13: Asset Encumbrance (%) | D13: New 2016 | E13: New 2016 | F13: Market Risk | H13: Y | L13: Y | P13: TBD | T13: New from Group Dec-15 | U13: Calculated as (total encumbered assets + total collateral received re-used) / (total assets + total collateral received available for encumbrance). Encumbered assets are those assigned to: covered bonds, securitisations and TLTRO. | V13: Analyze Group metric definition and how to apply to SHUSA and all Subs, including IHC | W13: Finance / Treasury | X13: Market & Liquidity | Y13: 4/27/2016 Eliminated from the RAS according to email from Scott Amarucci. However it will be maintained as operating limit and monitored by local market risk area. In BSPR there are no covered bonds, securitisations nor TLTRO. [SA]: Agree As discussed with Beatriz Shapiro on 2/12/2016 - Metric is being analyzed by Manolo Lasso. He should inform the BSPR Market Risk area directly on applicability. | Z13: PENDING | AA13: 4/27/2016 Eliminated from the RAS according to email from Scott Amarucci. However it will be maintained as operating limit and monitored by local market risk area. | AC13: ? | AF13: Treasury / Victor Montes Market Risk / Marilena Castro | BR13: =+IFERROR(AVERAGE(AT13:BQ13),"") | BS13: =+IFERROR(VAR(AT13:BQ13),"") | BT13: =+IFERROR(STDEV(#REF!)*(1-$BS$1),"") | BU13: =+IF(OR(BT13="",OFFSET(#REF!,0,MATCH($B$1,AT$2:BQ$2,0)-1)=""),"",IFERROR(IF(ABS(OFFSET(#REF!,0,MATCH($B$1,AT$2:BQ$2,0)-1)-OFFSET(#REF!,0,MATCH($B$1,AT$2:BQ$2,0)-2))>BT13,"N","µ"),"")) -> #REF! | BW13: Slide 7: Indicates it is included
B14: Interest Rate Risk | C14: ALM NII (+/-100bps) BSPR | D14: ($120)MM | E14: ($140)MM | F14: Market Risk | H14: Y | L14: Y | P14: Y | T14: New for Group Dec-15 - with 100bps | V14: Ensure alignment with Group definition | W14: Finance / Treasury | X14: Market & Liquidity | Y14: 4/27/2016 Changed for percentage instead of dollar value | Z14: YES | AA14: 4/27/2016 Changed for percentage instead of dollar value | AC14: Monthly | AD14: RTS BSPR #0030 | AE14: Worst case net interest income sensitivity between a parallel shock of +100bps and -100bps over a one year horizon. | AF14: Market Risk / Marilena Castro | AG14: Metric is stored in EXCEL in a Local Network. Currently data is extracted from ORACLE, OFSA, MIAC, Calculador (corporate system), and other working papers (Excels) which are consolidated into one spreadsheet (Excel). As part of the Market Risk Efficiency Plan, a server is being developed in which this data will be stored. | AH14: The availability depends on ALCO Committee date towards the end of the month. | AI14: IRR Policy | AJ14: IRR Policy | AL14: Market Risk Update Risk Committee as NIM | AM14: 2015 March OK June OK September OK | AO14: ($12.0MM) | AP14: ($15.0MM) | AQ14: >($6MM) | AR14: ($6MM) | AS14: ($10MM) | AT14: -2.42 | AU14: -0.07 | AV14: =-142047.019494295/1000000 -> -0.14204702 | AW14: -2.1221236 | AX14: -1.92 | AY14: -3.32 | AZ14: -1.0950627 | BA14: -0.20498104 | BB14: =3948208.23575136/1000000 -> 3.9482082 | BC14: =2953605.46328443/1000000 -> 2.9536055 | BD14: 3.7 | BE14: 1.61 | BF14: 3.2 | BG14: 4.0381037 | BH14: 4.0381037 | BR14: =+IFERROR(AVERAGE(AT14:BQ14),"") -> 0.81292045 | BS14: =+IFERROR(VAR(AT14:BQ14),"") -> 7.1335048 | BT14: =+IFERROR(STDEV(AT15:BQ15)*(1-$BS$1),"") -> 1.8488186 | BU14: =+IF(OR(BT14="",OFFSET(AT15,0,MATCH($B$1,AT$2:BQ$2,0)-1)=""),"",IFERROR(IF(ABS(OFFSET(AT15,0,MATCH($B$1,AT$2:BQ$2,0)-1)-OFFSET(AT15,0,MATCH($B$1,AT$2:BQ$2,0)-2))>BT14,"N","µ"),"")) -> N | BV14: Used 'ALM MVE (+ 200bps)'
C15: ALM MVE (+/-100bps) BSPR | D15: ($1,070)MM | E15: ($1,220)MM | F15: Market Risk | H15: Y | L15: Y | P15: TBD | T15: New for Group Dec-15 - with 100bps | V15: Ensure alignment with Group definition | W15: Finance / Treasury | X15: Market & Liquidity | Y15: 4/27/2016 Changed for percentage instead of dollar value Currently the Market Risk area calculates the 'ALM MVE (+200bps)' since interest curve cannot go down to (-200bps). The risk is with the (+200bps) which is the more severe since it's where we could experience losses. [SA]: Ok - will need to follow up with M. Lasso As discussed with Beatriz Shapiro on 2/12/2016 - Manolo Lasso will be discussing metric with Spain. 4/19/16 Confirmed with Market Risk Area. OK | Z15: YES | AA15: 4/27/2016 Changed for percentage instead of dollar value Currently the Market Risk area calculates the 'ALM MVE (+200bps)' since interest curve cannot go down to (-200bps). The risk is with the (+200bps) which is the more severe since it's where we could experience losses. [SA]: Ok - will need to follow up with M. Lasso As discussed with Beatriz Shapiro on 2/12/2016 - Manolo Lasso will be discussing metric with Spain. 4/19/16 Confirmed with Market Risk Area. OK | AC15: Monthly | AD15: RTS BSPR #0169 | AE15: Worst case market value of equity sensitivity between a parallel shock of +100bps over a one year horizon. | AF15: Market Risk / Marilena Castro | AG15: Metric is stored in EXCEL in a Local Network. Currently data is extracted from ORACLE, OFSA, MIAC, Calculador (corporate system), and other working papers (Excels) which are consolidated into one spreadsheet (Excel). As part of the Market Risk Efficiency Plan, a server is being developed in which this data will be stored. | AH15: The availability depends on ALCO Committee date towards the end of the month. | AI15: IRR Policy | AJ15: IRR Policy | AL15: Market Risk Update Risk Committee | AM15: 2015 February, March, May, June, August, September, November and December OK | AQ15: ≥($40.0MM) | AR15: ($40.0MM) | AS15: ($55.0MM) | AT15: N/Avail | AU15: N/Avail | AV15: -19.92 | AW15: -21.85 | AX15: -23.06 | AY15: -26.88 | AZ15: -23.938431 | BA15: -17.514523 | BB15: -15.860447 | BC15: -18.026248 | BD15: -16.9 | BE15: -20.93 | BF15: -17.2 | BG15: -15.130693 | BH15: -15.130693 | BR15: =+IFERROR(AVERAGE(AT15:BQ15),"") -> -19.410849 | BS15: =+IFERROR(VAR(AT15:BQ15),"") -> 13.672521 | BT15: =+IFERROR(STDEV(AT16:BQ16)*(1-$BS$1),"") -> 1.3080287 | BU15: =+IF(OR(BT15="",OFFSET(AT16,0,MATCH($B$1,AT$2:BQ$2,0)-1)=""),"",IFERROR(IF(ABS(OFFSET(AT16,0,MATCH($B$1,AT$2:BQ$2,0)-1)-OFFSET(AT16,0,MATCH($B$1,AT$2:BQ$2,0)-2))>BT15,"N","µ"),"")) -> µ | BV15: Under discussion between SHUSA and Local Operational Teams | BW15: Slide 7: Indicates it is included
B16: Interest Rate Risk | C16: ALM NII (+/-100bps) BANCORP | D16: ($120)MM | E16: ($140)MM | F16: Market Risk | H16: Y | L16: Y | P16: Y | T16: New for Group Dec-15 - with 100bps | V16: Ensure alignment with Group definition | W16: Finance / Treasury | X16: Market & Liquidity | Y16: 4/27/2016 Changed for percentage instead of dollar value | Z16: YES | AA16: 4/27/2016 Changed for percentage instead of dollar value | AC16: Monthly | AD16: RTS SBC #0030 | AE16: Worst case net interest income sensitivity between a parallel shock of +100bps and -100bps over a one year horizon. | AF16: Market Risk / Marilena Castro | AG16: Metric is stored in EXCEL in a Local Network. Currently data is extracted from ORACLE, OFSA, MIAC, Calculador (corporate system), and other working papers (Excels) which are consolidated into one spreadsheet (Excel). As part of the Market Risk Efficiency Plan, a server is being developed in which this data will be stored. | AH16: The availability depends on ALCO Committee date towards the end of the month. | AI16: IRR Policy | AJ16: IRR Policy | AL16: Market Risk Update Risk Committee as NIM | AM16: 2015 March OK June OK September OK | AO16: ($12.0MM) | AP16: ($15.0MM) | AQ16: >($6MM) | AR16: ($6MM) | AS16: ($10MM) | AT16: -2.5 | AU16: -0.07 | AV16: -0.29 | AW16: -2.2740029 | AX16: -2.1 | AY16: -3.5 | AZ16: -1.2 | BA16: -0.33539839 | BB16: 3.8190938 | BC16: 2.8493693 | BD16: 3.6 | BE16: 1.51 | BF16: 3.0451165 | BG16: 3.87 | BR16: =+IFERROR(AVERAGE(AT16:BQ16),"") -> 0.45886988 | BS16: =+IFERROR(VAR(AT16:BQ16),"") -> 6.8437566 | BT16: =+IFERROR(STDEV(AT16:BQ16)*(1-$BS$1),"") -> 1.3080287 | BU16: =+IF(OR(BT16="",OFFSET(AT16,0,MATCH($B$1,AT$2:BQ$2,0)-1)=""),"",IFERROR(IF(ABS(OFFSET(AT16,0,MATCH($B$1,AT$2:BQ$2,0)-1)-OFFSET(AT16,0,MATCH($B$1,AT$2:BQ$2,0)-2))>BT16,"N","µ"),"")) -> µ
C17: ALM MVE (+/-100bps) BANCORP | D17: ($1,070)MM | E17: ($1,220)MM | F17: Market Risk | H17: Y | L17: Y | P17: TBD | T17: New for Group Dec-15 - with 100bps | V17: Ensure alignment with Group definition | W17: Finance / Treasury | X17: Market & Liquidity | Y17: 4/27/2016 Changed for percentage instead of dollar value Currently the Market Risk area calculates the 'ALM MVE (+200bps)' since interest curve cannot go down to (-200bps). The risk is with the (+200bps) which is the more severe since it's where we could experience losses. [SA]: Ok - will need to follow up with M. Lasso As discussed with Beatriz Shapiro on 2/12/2016 - Manolo Lasso will be discussing metric with Spain. 4/19/16 Confirmed with Market Risk Area. OK | Z17: YES | AA17: 4/27/2016 Changed for percentage instead of dollar value Currently the Market Risk area calculates the 'ALM MVE (+200bps)' since interest curve cannot go down to (-200bps). The risk is with the (+200bps) which is the more severe since it's where we could experience losses. [SA]: Ok - will need to follow up with M. Lasso As discussed with Beatriz Shapiro on 2/12/2016 - Manolo Lasso will be discussing metric with Spain. 4/19/16 Confirmed with Market Risk Area. OK | AC17: Monthly | AD17: RTS BSPR #0169 | AE17: Worst case market value of equity sensitivity between a parallel shock of +100bps over a one year horizon. | AF17: Market Risk / Marilena Castro | AG17: Metric is stored in EXCEL in a Local Network. Currently data is extracted from ORACLE, OFSA, MIAC, Calculador (corporate system), and other working papers (Excels) which are consolidated into one spreadsheet (Excel). As part of the Market Risk Efficiency Plan, a server is being developed in which this data will be stored. | AH17: The availability depends on ALCO Committee date towards the end of the month. | AI17: IRR Policy | AJ17: IRR Policy | AL17: Market Risk Update Risk Committee | AM17: 2015 February, March, May, June, August, September, November and December OK | AQ17: ≥($40.0MM) | AR17: ($40.0MM) | AS17: ($55.0MM) | AT17: N/Avail. | AU17: N/Avail. | AV17: -25.83 | AW17: -27.57 | AX17: -28.72 | AY17: -32.46 | AZ17: -29.5 | BA17: -23.194343 | BB17: -21.321669 | BC17: -23.386236 | BD17: -22.2 | BE17: -26.09 | BF17: -22.36653 | BG17: -20.22 | BR17: =+IFERROR(AVERAGE(AT17:BQ17),"") -> -25.238231 | BS17: =+IFERROR(VAR(AT17:BQ17),"") -> 14.050833 | BT17: =+IFERROR(STDEV(AT17:BQ17)*(1-$BS$1),"") -> 1.8742221 | BU17: =+IF(OR(BT17="",OFFSET(AT17,0,MATCH($B$1,AT$2:BQ$2,0)-1)=""),"",IFERROR(IF(ABS(OFFSET(AT17,0,MATCH($B$1,AT$2:BQ$2,0)-1)-OFFSET(AT17,0,MATCH($B$1,AT$2:BQ$2,0)-2))>BT17,"N","µ"),"")) -> N | BV17: Used 'ALM MVE (+ 200bps)' | BW17: Slide 7: Indicates it is included
B18: Capital | C18: Tangible Common Equity Ratio BSPR | D18: 0.105 | E18: 0.1 | F18: Capital Mgmt Group | H18: N | L18: N | P18: TBD | Z18: YES | AA18: 5/6/2016Entonces no se incluirá en RAS aunque sigamos nosotros calculandola. Parece mejor circunscribirnos a las métricas asociadas al New Capital Rule | AC18: Monthly | AD18: RTS BSPR #0171 | AE18: Total Tangible Common Equity / (Total Assets - Goodwill) | AF18: Leslie Adames (threshold calibration) Treasury | AG18: Consolidated Capital Report | AH18: 10th-12th of each mont | AI18: Capital Policy | AJ18: Capital Policy from November 27, 2015 which was approved by the Board on December 8, 2015. Information is located in page 7, Table 3: 2015 SBC/BSPR Capital Expectations. the Planned capital hold was considered for the Amber trigger and the Business-as-usual was consideredfor the Red limit. | AL18: ALCO Risk Scorecard Quarterly Capital Trends | AM18: ALCO: December 2015 OK January 2016 is 16.00% Different Quarterly: June 15.2%Different, September 2015 OK | AO18: 0.0851 | AP18: 0.08 | AR18: 0.1062 | AS18: 0.0862 | AT18: N/Avail | AU18: N/Avail | AV18: N/Avail | AW18: 0.1464 | AX18: 0.1496 | AY18: 0.1514 | AZ18: 0.1508 | BA18: 0.15221336 | BB18: =828705/5433623 -> 0.15251426 | BC18: =829825/5382917 -> 0.15415898 | BD18: =831576.05456/5368834.299 -> 0.1548895 | BE18: =840007.713990001/5333502.97335 -> 0.15749644 | BF18: =843882.000719997/5264748.94318 -> 0.16028912 | BG18: =846058.057370008/5277491.15576 -> 0.16031444 | BH18: =847434.153269995/5333610.94634 -> 0.15888563 | BR18: =+IFERROR(AVERAGE(AT18:BQ18),"") -> 0.15408015 | BS18: =+IFERROR(VAR(AT18:BQ18),"") -> 1.9616243e-05 | BT18: =+IFERROR(STDEV(AT18:BQ18)*(1-$BS$1),"") -> 0.0022145114 | BU18: =+IF(OR(BT18="",OFFSET(AT18,0,MATCH($B$1,AT$2:BQ$2,0)-1)=""),"",IFERROR(IF(ABS(OFFSET(AT18,0,MATCH($B$1,AT$2:BQ$2,0)-1)-OFFSET(AT18,0,MATCH($B$1,AT$2:BQ$2,0)-2))>BT18,"N","µ"),"")) -> µ | BW18: Slide 6: Indicates it is not included.
C19: Tangible Common Equity Ratio BANCORP | D19: 0.105 | E19: 0.1 | F19: Capital Mgmt Group | H19: N | L19: N | P19: TBD | Z19: YES | AA19: 5/6/2016Entonces no se incluirá en RAS aunque sigamos nosotros calculandola. Parece mejor circunscribirnos a las métricas asociadas al New Capital Rule | AC19: Monthly | AD19: RTS SBC #0171 | AE19: Total Tangible Common Equity / (Total Assets - Goodwill) | AF19: Leslie Adames (threshold calibration) Treasury | AG19: Consolidated Capital Report | AH19: 10th-12th of each mont | AI19: Capital Policy | AJ19: Capital Policy from November 27, 2015 which was approved by the Board on December 8, 2015. Information is located in page 7, Table 3: 2015 SBC/BSPR Capital Expectations. the Planned capital hold was considered for the Amber trigger and the Business-as-usual was considered for the Red limit. | AL19: ALCO Risk Scorecard Quarterly Capital Trends | AM19: ALCO: December 2015 OK January 2016 is 16.00% Different Quarterly: June 15.2%Different, September 2015 OK | AO19: 0.0851 | AP19: 0.08 | AR19: 0.1062 | AS19: 0.0862 | AT19: N/Avail. | AU19: N/Avail. | AV19: N/Avail. | AW19: 0.1777 | AX19: 0.1811 | AY19: 0.1834 | AZ19: 0.1815 | BA19: 0.1828176 | BB19: 0.18286826 | BC19: 0.18464742 | BD19: 0.1850639 | BE19: 0.18552013 | BF19: 0.18823632 | BG19: 0.18686662 | BH19: 0.18504887 | BR19: =+IFERROR(AVERAGE(AT19:BQ19),"") -> 0.18373076 | BS19: =+IFERROR(VAR(AT19:BQ19),"") -> 7.9677174e-06 | BT19: =+IFERROR(STDEV(AT19:BQ19)*(1-$BS$1),"") -> 0.0014113573 | BU19: =+IF(OR(BT19="",OFFSET(AT19,0,MATCH($B$1,AT$2:BQ$2,0)-1)=""),"",IFERROR(IF(ABS(OFFSET(AT19,0,MATCH($B$1,AT$2:BQ$2,0)-1)-OFFSET(AT19,0,MATCH($B$1,AT$2:BQ$2,0)-2))>BT19,"N","µ"),"")) -> µ | BW19: Slide 6: Indicates it is not included.
B20: Credit Risk | C20: Total Credit Losses Mortgages | AA20: 5/10/2016 Eliminated according to email from Katherine Schade from OW that indicated the Total Losses metric is reported as a dingle item aggregated for all BSPR portfolios. | AE20: 9Q stressed cummulativw credit losses and any available capital surplus under the CCAR BHC Stress scenario allocated by material portfolio | AF20: CCAR (threshold calibration) | AJ20: The Capital Policy was used to calibrate , refer to page 7, Table 3. The Post-stress minimum was used to set the Red limit. To this the Stress absorption (1.71%) was added to calculate the Business-as-usual minimum, which was set as the Ambar trigger. This methodology was discussed and approved between the PR Capital Team and SHUSA's Capital Team. | AR20: =AS20+1.71% -> 0.1101 | AS20: 0.093
C21: Total Credit Losses Commercial Banking | AA21: 5/10/2016 Eliminated according to email from Katherine Schade from OW that indicated the Total Losses metric is reported as a dingle item aggregated for all BSPR portfolios. | AE21: 9Q stressed cummulativw credit losses and any available capital surplus under the CCAR BHC Stress scenario allocated by material portfolio | AF21: CCAR (threshold calibration) | AJ21: The Capital Policy was used to calibrate , refer to page 7, Table 3. The Post-stress minimum was used to set the Red limit. To this the Management Adjustment was added in order to set as the Ambar trigger (10.75% + 2.00%). This methodology was discussed and approved between the PR Capital Team and SHUSA's Capital Team. | AR21: =AS21+2% -> 0.1275 | AS21: 0.1075
C22: Total Credit Losses Personal Loans | AA22: 5/10/2016 Eliminated according to email from Katherine Schade from OW that indicated the Total Losses metric is reported as a dingle item aggregated for all BSPR portfolios. | AE22: 9Q stressed cummulativw credit losses and any available capital surplus under the CCAR BHC Stress scenario allocated by material portfolio | AF22: CCAR (threshold calibration) | AJ22: The Capital Policy was used to calibrate , refer to page 7, Table 3. The Post-stress minimum was used to set the Red limit. To this the Management Adjustment was added in order to set as the Ambar trigger (12.15% + 2.00%). This methodology was discussed and approved between the PR Capital Team and SHUSA's Capital Team. | AR22: =AS22+2% -> 0.1415 | AS22: 0.1215
C23: Total Credit Losses Credit Cards | AA23: 5/10/2016 Eliminated according to email from Katherine Schade from OW that indicated the Total Losses metric is reported as a dingle item aggregated for all BSPR portfolios. | AE23: 9Q stressed cummulativw credit losses and any available capital surplus under the CCAR BHC Stress scenario allocated by material portfolio | AF23: CCAR (threshold calibration) | AJ23: The Capital Policy was used to calibrate , refer to page 7, Table 3. The Post-stress minimum was used to set the Red limit. To this the Management Adjustment was added in order to set as the Ambar trigger (6.80% + 2.00%). This methodology was discussed and approved between the PR Capital Team and SHUSA's Capital Team. | AR23: =AS23+2% -> 0.088 | AS23: 0.068

Sheet Not included in RAS-Only Monit 
B1: 42401 | W1: ACTION PLAN OWNER | AC1: PR - BSPR | BR1: Sensitivity | BS1: 0.5
C2: SHUSA RISK APPETITE METRICS | D2: 2015 TRIGGER LIMIT | E2: 2015 RED LIMIT | F2: SOURCE FOR 2016 RAS LIMIT SETTING | H2: SHUSA IN GROUP RAS | I2: 2016 TRIGGER LIMIT | J2: 2016 RED LIMIT | L2: SHUSA US RAS | M2: 2016 TRIGGER LIMIT | N2: 2016 RED LIMIT | P2: BSPR | Q2: 2016 TRIGGER LIMIT | R2: 2016 RED LIMIT | T2: COMMENTS | U2: GROUP DEFINITION | V2: ACTION PLAN | W2: LINE 1 | X2: LINE 2 | Y2: BSPR Comments | Z2: Metric Applicability Confirmed with SHUSA | AA2: Calibration Comments | AC2: Frequency | AD2: Current RTS / RSC metric | AE2: SAN-PR Definition | AF2: SOURCE FOR 2016 RAS LIMIT SETTING | AG2: Source | AH2: Availability | AI2: Level | AJ2: Rationale for threshold definition | AK2: Budget | AL2: Reports Affected | AM2: Reports Consistency Validation | AN2: Differences: SHUSA RAS Glossary vs. BSPR Methodology | AO2: 2015 TRIGGER LIMIT | AP2: 2015 RED LIMIT | AQ2: 2016 GREEN | AR2: 2016 TRIGGER LIMIT | AS2: 2016 RED LIMIT | AT2: 42035 | AU2: 42063 | AV2: 42094 | AW2: 42124 | AX2: 42155 | AY2: 42185 | AZ2: 42216 | BA2: 42247 | BB2: 42277 | BC2: 42308 | BD2: 42338 | BE2: 42369 | BF2: 42400 | BG2: 42401 | BH2: 42430 | BI2: 42461 | BJ2: 42491 | BK2: 42522 | BL2: 42552 | BM2: 42583 | BN2: 42614 | BO2: 42644 | BP2: 42675 | BQ2: 42705 | BR2: Average | BS2: Variance | BT2: Standard Deviation | BU2: AVS | BV2: Local Comments - Cristina's Review | BW2: Comparación 4/8/16
B3: Included in Monthly Risk Report for monitoring purposes only | C3: Cost of Credit | D3: New 2016 | E3: New 2016 | F3: CCAR | H3: Y | L3: Y | P3: Y | T3: New from Group Dec-15 / New 2016 SHUSA and Subs | U3: Cumulative net provisions over the last 12 months / Average loan portfolio over the same period. Where Net Credit Losses = Gross credit losses minus Recovery of NPLs during the period AND Loan Portfolio = Amount drawn down + SBLCs - Limit should not go beyond a medium volatility setting measured as 2 standard deviations in a historic series or maximum change in ICAAP stress exercise (FRB adverse for SHUSA and subs?) | V3: US entities will use the cost of credit metric that is included in the Monthly Risk Report as coordinated by Risk MI. Calibration TBD | W3: New 2016 | X3: RAS Team | Y3: 4/8/16 We don't have a Recovery and Resolution team to oversee these metrics. Do they have to be included in the Monthly only for monitoring purposes? | Z3: YES | AC3: Monthly | AD3: RSC BSPR #0113 Corporate criteria | AE3: Metric is calculated as the total provisions divided by the total lending. (PROVISION EXPENSE SPAIN (12M) (SE COPIA TODO EL PERIODO POR SI HAY AJUSTES divided by CARTERA PROMEDIO 12M (NET OF INTERCOMPANY LOANS)) | AF3: Risk MI / Rafael Martínez | AG3: Database 1001 | AH3: day 5th of each month | AI3: Budget | AK3: 0.0174 | AM3: Change in RTS Limit/EWIs per budget performed during month of March 2016. The historical data of months of 2015 and Jan/Feb 2016 were compared to limits approved per 2015 budget. | AO3: 0.0116 | AP3: 0.0139 | AQ3: N/A | AR3: N/A | AS3: N/A | AT3: =0.00810754155711443 -> 0.0081075416 | AU3: =0.00904669294295699 -> 0.0090466929 | AV3: 0.0090446632 | AW3: =0.00962495997732189 -> 0.00962496 | AX3: =0.0109976463079174 -> 0.010997646 | AY3: =0.0116054735329468 -> 0.011605474 | AZ3: =53810655.7451/4060531973.02463 -> 0.01325212 | BA3: =0.013437354510884 -> 0.013437355 | BB3: =0.0136517166858552 -> 0.013651717 | BC3: 0.015008679 | BD3: =0.0152614696712326 -> 0.01526147 | BE3: =0.0163434059590632 -> 0.016343406 | BF3: =0.0164429879095369 -> 0.016442988 | BG3: 0.0165 | BH3: =0.0175726480186129 -> 0.017572648 | BR3: =+IFERROR(AVERAGE(AT3:BQ3),"") -> 0.013059824 | BS3: =+IFERROR(VAR(AT3:BQ3),"") -> 9.8943617e-06 | BT3: =+IFERROR(STDEV(AT4:BQ4)*(1-$BS$1),"") -> 0.0092754021 | BU3: =+IF(OR(BT3="",OFFSET(AT4,0,MATCH($B$1,AT$2:BQ$2,0)-1)=""),"",IFERROR(IF(ABS(OFFSET(AT4,0,MATCH($B$1,AT$2:BQ$2,0)-1)-OFFSET(AT4,0,MATCH($B$1,AT$2:BQ$2,0)-2))>BT3,"N","µ"),"")) -> N | BW3: Slide 8: Not included in RAS - Monitoring Only | BY3: Propuesta no llevarala (pero si tenemos presupuesto)
C4: NPL coverage ratio (%) | D4: New 2016 | E4: New 2016 | F4: Solvency | H4: Y | L4: Y | P4: TBD | T4: New from Group Dec-15 PR comments: Why put a limit to this metric? It is a very subjective metric and establishing a limit is not liked by the auditors nor regulator. Metric could be monitored to ensure that expected losses are adequately provisioned but metric should not be limited. In Puerto Rico by regulation and as a regular prudent practice, we recognize losses as partial charge offs if needed. If results are higher, it can be interpreted as a method of tax evasion. If results are lower, it means that expected losses are not provisioned as needed. | U4: Provisions reserves / non-performing loans - Limit should not go beyond a medium volatility setting measured as 2 standard deviations in a historic series | V4: To be discussed with Group | W4: Business Heads | X4: Solvency for historical data | Y4: As agreed in the Conference Call, we will be using the local criteria if metric is required. [SA]: OK 4/8/16 We don't have a Recovery and Resolution team to oversee these metrics. Do they have to be included in the Monthly only for monitoring purposes? | Z4: YES | AA4: Pending confirmation from Zhiyi / Scott as metric is being discussed with Santander Group. | AC4: Monthly | AE4: NUMERATOR: LOCAL ALLOWANCE FOR LOAN AND LEASE LOSSES (ALLL) divided by DENOMINATOR: TOTAL NPL (MORA LOCAL) | AF4: Risk MI / Rafael Martínez | AG4: TABLA 1001 | AH4: day 10th of each month depending on Accounting reconciliation | AL4: Report: Credit Trends as reported by Portfolio Management Metric: NPL & Coverage (Net) local criteria | AQ4: N/A | AR4: N/A | AS4: N/A | AT4: =75014895.0009579/197947193.26 -> 0.37896418 | AU4: =76147115.132738/198273240.08 -> 0.3840514 | AV4: =75719695.7491383/198234332.48 -> 0.38197064 | AW4: =76056100.5293789/196614524.89 -> 0.38682849 | AX4: =78186868.0533333/195226229.66 -> 0.40049366 | AY4: =77375165.3484528/202262388.68 -> 0.38254846 | AZ4: =79224772.1989476/207673969.88 -> 0.38148629 | BA4: =79540396.9918334/212484335.34 -> 0.37433535 | BB4: =80703898.7429197/212684600.61 -> 0.37945342 | BC4: =83891140.9921274/212475311.95 -> 0.39482771 | BD4: =83856488.4469171/209966946.39 -> 0.39937947 | BE4: =83139711.015894/198361162.25 -> 0.41913301 | BF4: =81980765.2654417/193587991.8 -> 0.42348063 | BG4: =82335767.2443788/189567135.59 -> 0.43433566 | BH4: =84946017.6122911/207444464.55 -> 0.40948799 | BR4: =+IFERROR(AVERAGE(AT4:BQ4),"") -> 0.39538509 | BS4: =+IFERROR(VAR(AT4:BQ4),"") -> 0.00034413234 | BT4: =+IFERROR(STDEV(AT5:BQ5)*(1-$BS$1),"") -> 0.0013994973 | BU4: =+IF(OR(BT4="",OFFSET(AT5,0,MATCH($B$1,AT$2:BQ$2,0)-1)=""),"",IFERROR(IF(ABS(OFFSET(AT5,0,MATCH($B$1,AT$2:BQ$2,0)-1)-OFFSET(AT5,0,MATCH($B$1,AT$2:BQ$2,0)-2))>BT4,"N","µ"),"")) -> µ | BV4: Información tomada del RSC. Cálculo es: Mora 404 for the month divided by Cartera Promedio 12 M of the month | BW4: Slide 8: Not included in RAS - Monitoring only
C5: NPL Entries (VMG) | D5: New 2016 | E5: New 2016 | F5: Solvency | H5: Y | L5: Y | P5: Y | T5: New from Group Dec-15 US will use local criteria for NPL entries | U5: NPL entries (last 12 months) / avg credit exposure (last 12 months) - Limit should not go beyond a medium volatility setting measured as 2 standard deviations in a historic series | V5: US entities will apply group definition. Calibration TBD | W5: Business Heads | X5: Solvency for historical data | Y5: As agreed in the Conference Call, we will be using the local criteria: The sum of all NPL entries in the last 12 months divided by the average portfolio of the last 12 months (both in local criteria) [SA]: Sounds good - will need to discuss with Jennifer if she wants to use this method 4/8/16 Variación Mora por Gestión is defined as follows New NPL minus Old NPLs) plus (Charge-offs minus recoveries) | Z5: PENDING | AA5: Pending confirmation from Zhiyi / Scott as metric is being discussed with Santander Group BSPR - our original proposal was based on budget however the SHUSA team understands they should actually be calculating those limits at SHUSA when they calculate all of the CCAR stress-related metrics’ limits (according to Scott's e-mail). | AC5: Monthly | AD5: RSC BSPR #0109 Corporate criteria | AE5: Percentage of the YTD NPL (Circular BDE 4/04- due to NPL criteria and DNP criteria) in relation to Total Drawn Exposure. | AF5: Risk MI / Rafael Martínez | AG5: Database 1001 | AH5: day 5th of each month | AI5: Budget | AJ5: The Strategic Plan/budget was considered as the target (Green level) and the Amber / Red thresholds were defined from that point. Once Green Level is defined, a deviation of 20% until the Red Limit is set. The Amber threshold is the remaining range between the Green and the Red threshold. We set the Green level (objective) considering the Strategic Plan/budget and add a 20% deviation to the Red (Limit) which represents the buffer permitted by the BOD to the Senior Management to manage the risks without risking the Bank’s capital. Per the Capital Stress Test (CCAR), there is ~20% distance from the baseline to the adverse scenario (stressed) while still maintaining the capital levels above the limits required by the regulator. That ~20% deviation is used from the Green level to the Red (Limit) in the RAS thus integrating both the Strategic Plan/budget and the Capital Stress Test (CCAR) into the RAS. | AK5: 0.068 | AO5: 0.068 | AP5: 0.081 | AQ5: =AK5 -> 0.068 | AR5: =AK5+0.001 -> 0.069 | AS5: =AK5*1.2 -> 0.0816 | AT5: =235583893.39/4404662513.72629 -> 0.053485118 | AU5: =238895891.12/4321124267.57379 -> 0.055285587 | AV5: =236549591.49/4245957192.36462 -> 0.055711723 | AW5: =235892330.27/4179845295.93796 -> 0.056435661 | AX5: =242848327.31/4133547027.57379 -> 0.05875059 | AY5: =240896981.08/4097831828.92879 -> 0.058786449 | AZ5: =247317000.29/4060531973.02463 -> 0.060907537 | BA5: =246587569.7/4025508309.39129 -> 0.061256257 | BB5: =243925753/3980634168.14129 -> 0.061278114 | BC5: =245414444.56/3937414970.39046 -> 0.062328824 | BD5: =240942643.98/3897127183.77379 -> 0.061825707 | BE5: =238271529.15/3868142340.95079 -> 0.061598439 | BF5: =234223407.06/3845877339.42333 -> 0.060902464 | BG5: =230447226.35/3821779569.84417 -> 0.060298409 | BH5: =232192923.62/3797502562.88167 -> 0.061143586 | BR5: =+IFERROR(AVERAGE(AT5:BQ5),"") -> 0.059332964 | BS5: =+IFERROR(VAR(AT5:BQ5),"") -> 7.8343704e-06 | BT5: =+IFERROR(STDEV(AT6:BQ6)*(1-$BS$1),"") | BU5: =+IF(OR(BT5="",OFFSET(AT6,0,MATCH($B$1,AT$2:BQ$2,0)-1)=""),"",IFERROR(IF(ABS(OFFSET(AT6,0,MATCH($B$1,AT$2:BQ$2,0)-1)-OFFSET(AT6,0,MATCH($B$1,AT$2:BQ$2,0)-2))>BT5,"N","µ"),"")) | BW5: Slide 6: Included, unconsolidated. Variación Mora por Gestión is defined as follows New NPL minus Old NPLs) plus (Charge-offs minus recoveries)
C6: Financial Intitutions Top 20 | Z6: PENDING | AA6: New metric identified in 2016 RAS Calibration Supporting Documentation Plan. We need the definition, methodology and requirements. | BR6: =+IFERROR(AVERAGE(AT6:BQ6),"") | BS6: =+IFERROR(VAR(AT6:BQ6),"") | BT6: =+IFERROR(STDEV(AT7:BQ7)*(1-$BS$1),"") | BU6: =+IF(OR(BT6="",OFFSET(AT7,0,MATCH($B$1,AT$2:BQ$2,0)-1)=""),"",IFERROR(IF(ABS(OFFSET(AT7,0,MATCH($B$1,AT$2:BQ$2,0)-1)-OFFSET(AT7,0,MATCH($B$1,AT$2:BQ$2,0)-2))>BT6,"N","µ"),""))
C7: Card fraud | Z7: PENDING | AA7: New metric identified in 2016 RAS Calibration Supporting Documentation Plan. We need the definition, methodology and requirements. | AJ7: Thresholds for the monitoring metrics that are currently on the Corporate tool as part of the 140 core KRI’s | AQ7: x ≤ 5 | AR7: 5 < x ≤ 10 | AS7: x > 10 | BR7: =+IFERROR(AVERAGE(AT7:BQ7),"") | BS7: =+IFERROR(VAR(AT7:BQ7),"") | BT7: =+IFERROR(STDEV(AT8:BQ8)*(1-$BS$1),"") | BU7: =+IF(OR(BT7="",OFFSET(AT8,0,MATCH($B$1,AT$2:BQ$2,0)-1)=""),"",IFERROR(IF(ABS(OFFSET(AT8,0,MATCH($B$1,AT$2:BQ$2,0)-1)-OFFSET(AT8,0,MATCH($B$1,AT$2:BQ$2,0)-2))>BT7,"N","µ"),""))
C8: Online banking fraud | Z8: PENDING | AA8: New metric identified in 2016 RAS Calibration Supporting Documentation Plan. We need the definition, methodology and requirements. | AJ8: Thresholds for the monitoring metrics that are currently on the Corporate tool as part of the 140 core KRI’s | AQ8: x < 0.1 | AR8: 0.1 ≤ x < 0.2 | AS8: x ≥ 0.2 | BR8: =+IFERROR(AVERAGE(AT8:BQ8),"") | BS8: =+IFERROR(VAR(AT8:BQ8),"") | BT8: =+IFERROR(STDEV(AT9:BQ9)*(1-$BS$1),"") | BU8: =+IF(OR(BT8="",OFFSET(AT9,0,MATCH($B$1,AT$2:BQ$2,0)-1)=""),"",IFERROR(IF(ABS(OFFSET(AT9,0,MATCH($B$1,AT$2:BQ$2,0)-1)-OFFSET(AT9,0,MATCH($B$1,AT$2:BQ$2,0)-2))>BT8,"N","µ"),""))
C9: IT relevant incidents | Y9: Corporate tool as part of the 140 core KRI’s: CI22187 P1 and P2 incidents in production (33.3% weight) | Z9: PENDING | AA9: New metric identified in 2016 RAS Calibration Supporting Documentation Plan. We need the definition, methodology and requirements. | AJ9: Thresholds for the monitoring metrics that are currently on the Corporate tool as part of the 140 core KRI’s | AQ9: x < 2 | AR9: 2 ≤ x < 3 | AS9: x ≥ 3 | BR9: =+IFERROR(AVERAGE(AT9:BQ9),"") | BS9: =+IFERROR(VAR(AT9:BQ9),"") | BT9: =+IFERROR(STDEV(AT10:BQ10)*(1-$BS$1),"") | BU9: =+IF(OR(BT9="",OFFSET(AT10,0,MATCH($B$1,AT$2:BQ$2,0)-1)=""),"",IFERROR(IF(ABS(OFFSET(AT10,0,MATCH($B$1,AT$2:BQ$2,0)-1)-OFFSET(AT10,0,MATCH($B$1,AT$2:BQ$2,0)-2))>BT9,"N","µ"),""))
C10: % IT systems availability | Z10: PENDING | AA10: New metric identified in 2016 RAS Calibration Supporting Documentation Plan. We need the definition, methodology and requirements. | AJ10: Thresholds for the monitoring metrics that are currently on the Corporate tool as part of the 140 core KRI’s | AQ10: x ≥ 99.75 | AR10: 99.75 > x ≥ 99.5 | AS10: x < 99.5 | BR10: =+IFERROR(AVERAGE(AT10:BQ10),"") | BS10: =+IFERROR(VAR(AT10:BQ10),"") | BT10: =+IFERROR(STDEV(AT11:BQ11)*(1-$BS$1),"") | BU10: =+IF(OR(BT10="",OFFSET(AT11,0,MATCH($B$1,AT$2:BQ$2,0)-1)=""),"",IFERROR(IF(ABS(OFFSET(AT11,0,MATCH($B$1,AT$2:BQ$2,0)-1)-OFFSET(AT11,0,MATCH($B$1,AT$2:BQ$2,0)-2))>BT10,"N","µ"),""))
C11: % Servers with obsolete operating systems | Z11: PENDING | AA11: New metric identified in 2016 RAS Calibration Supporting Documentation Plan. We need the definition, methodology and requirements. | AJ11: Thresholds for the monitoring metrics that are currently on the Corporate tool as part of the 140 core KRI’s | AQ11: x ≤ 3 | AR11: 3 < x ≤ 5 | AS11: x > 5 | BR11: =+IFERROR(AVERAGE(AT11:BQ11),"") | BS11: =+IFERROR(VAR(AT11:BQ11),"") | BT11: =+IFERROR(STDEV(AT12:BQ12)*(1-$BS$1),"") | BU11: =+IF(OR(BT11="",OFFSET(AT12,0,MATCH($B$1,AT$2:BQ$2,0)-1)=""),"",IFERROR(IF(ABS(OFFSET(AT12,0,MATCH($B$1,AT$2:BQ$2,0)-1)-OFFSET(AT12,0,MATCH($B$1,AT$2:BQ$2,0)-2))>BT11,"N","µ"),""))
C12: Ethical hacking vulnerabilities | Z12: PENDING | AA12: New metric identified in 2016 RAS Calibration Supporting Documentation Plan. We need the definition, methodology and requirements. | AJ12: Thresholds for the monitoring metrics that are currently on the Corporate tool as part of the 140 core KRI’s | AQ12: x < 3 | AR12: 3 ≤ x < 6 | AS12: x ≥ 6 | BR12: =+IFERROR(AVERAGE(AT12:BQ12),"") | BS12: =+IFERROR(VAR(AT12:BQ12),"")
C13: Relevant OR Events R1 (number) | D13: New 2016 | E13: New 2016 | F13: OP Risk Team | H13: Y | L13: Y | P13: Y | T13: New from Group Dec-15 | U13: Measures the concentration of significant events. Events > € 1mill / Events > 20k - calculated quarterly. | V13: Analyze Group metric definition and how to apply to SHUSA and all Subs, including IHC | W13: Business Heads | X13: Operational Risk Team | Z13: YES | AA13: SHUSA Operational Team is proposing to eliminate this metric | AC13: ? | AF13: Operational Risk Team | AR13: OW | AS13: OW | BR13: =+IFERROR(AVERAGE(AT13:BQ13),"") | BS13: =+IFERROR(VAR(AT13:BQ13),"") | BT13: =+IFERROR(STDEV(AT14:BQ14)*(1-$BS$1),"") | BU13: =+IF(OR(BT13="",OFFSET(AT14,0,MATCH($B$1,AT$2:BQ$2,0)-1)=""),"",IFERROR(IF(ABS(OFFSET(AT14,0,MATCH($B$1,AT$2:BQ$2,0)-1)-OFFSET(AT14,0,MATCH($B$1,AT$2:BQ$2,0)-2))>BT13,"N","µ"),"")) | BV13: Under discussion between SHUSA and Local Operational Teams
B16: PENDING | C16: Card Fraud | AC16: Quarterly | AE16: Card Fraud Ratio (70% weight) = # of debit or credit card fraud cases / total # active cards Corporate KRI # CI21607 | AF16: Operational Risk Team | AJ16: Calibration provided by the SHUSA Operaterational Risk Team in coordination with the PR Ops Risk Team. Data is extracted from the Excel file New Group Metrics_ORM_020516 - Consolidated v6 on the sheet Group OR Metrics - Proposed. | AS16: 1

Sheet Industry Exposure OCC
A1: OCC - SHUSA | B1: BSPR | C1: 42035 | D1: 42063 | E1: 42094 | F1: 42124 | G1: 42155 | H1: 42185 | I1: 42216 | J1: 42247 | K1: 42277 | L1: 42308 | M1: 42338 | N1: 42369 | O1: 42400 | P1: 42401 | Q1: 42430 | R1: 42461 | S1: 42491 | T1: 42522 | U1: 42552 | V1: 42583 | W1: 42614 | X1: 42644 | Y1: 42675 | Z1: 42705
A2: Agribusiness | B2: Agriculture | H2: 27042 | K2: 26616 | N2: 24653 | O2: =31526635.42/1000 -> 31526.635 | P2: =31266469.05/1000 -> 31266.469 | Q2: =31062683.01/1000 -> 31062.683 | R2: =30883506.55/1000 -> 30883.507 | T2: 24079
A3: Apparel & Textiles Manufacturing
A4: Auto-Related
A5: Banks
A6: Commercial Services
A7: Consumer Services
A8: Durables Manufacturing Exc. Auto
A9: Entertainment & Recreation
A10: Finance & Insurance | B10: Financial Institutions and Insurance | H10: 57994 | K10: 55697 | N10: 56137 | O10: =27906461.1/1000 -> 27906.461 | P10: =11781068.91/1000 -> 11781.069 | Q10: =34708723.73/1000 -> 34708.724 | R10: =26352727.59/1000 -> 26352.728 | T10: 41520
A11: Food & Beverage Manufacturing
A12: Food & Drug Stores
A13: Government & Education | B13: Government & Education (Municipalities) | H13: 252155 | K13: 241694 | N13: 241714 | T13: 241741
B14: Government & Education (Indirect Risk (PRIDCO)) | H14: 66416 | K14: 65270 | N14: 62173 | T14: 60776
B15: Government & Education (Sovereign Risk / Agencies / Public Corp.) | H15: 151167 | K15: 21110 | N15: 47752 | O15: =325856490.57/1000 -> 325856.49 | P15: =325400094.01/1000 -> 325400.09 | Q15: =325402450.25/1000 -> 325402.45 | R15: =325255084.53/1000 -> 325255.08 | T15: 47422
B16: Government & Education (Education) | H16: 25230 | K16: 30205 | N16: 29749 | O16: =11712692.25/1000 -> 11712.692 | P16: =11645820.99/1000 -> 11645.821 | Q16: =11580163.95/1000 -> 11580.164 | R16: =16024332.05/1000 -> 16024.332 | T16: 27849
A17: Health Care & Pharmaceuticals | B17: Health Care & Pharmaceuticals (Health Care) | H17: 93307 | K17: 93289 | N17: 83350 | T17: 80705
B18: Health Care & Pharmaceuticals (Hospital) | H18: 115108 | K18: 113804 | N18: 112766 | O18: =140493383.13/1000 -> 140493.38 | P18: =139494406.51/1000 -> 139494.41 | Q18: =138450778.8/1000 -> 138450.78 | R18: =139027661.42/1000 -> 139027.66 | T18: 111430
A19: Loans to Individuals on Commercial Systems
A20: Materials & Commodities Exc. Energy
A21: Media & Telecom
A22: Oil & Gas & Coal | B22: Oil & Gas | H22: 13010 | K22: 12632 | N22: 11864 | O22: =13370063.04/1000 -> 13370.063 | P22: =12952155.98/1000 -> 12952.156 | Q22: =12193058.39/1000 -> 12193.058 | R22: =11968495.52/1000 -> 11968.496 | T22: 10713
A23: Professional Services
A24: Real Estate & Construction | B24: Real Estate & Construction (Commercial Real Estate) | H24: 525266 | K24: 518665 | N24: 515381 | O24: =538987387.32/1000 -> 538987.39 | P24: =510083557.16/1000 -> 510083.56 | Q24: =537536185.57/1000 -> 537536.19 | R24: =534813506.21/1000 -> 534813.51 | T24: 515783
